Workbook
Name K: Project_Page_5_RP!$P$22

Sheet Data
B1: Asset 1 | C1: Asset 2 | D1: Asset3 | E1: Asset 4 | F1: Asset 5 | H1: =COUNT(B2:B121) -> 120
A2: 38016 | B2: 0.006265643 | C2: 0.034770515 | D2: 0.032609824 | E2: 0.0064599983 | F2: 0.011827397
A3: 38044 | B3: 0.0084282173 | C3: -0.032526882 | D3: 0.083965425 | E3: 0.019989996 | F3: 0.023758424
A4: 38077 | B4: 0.0043830411 | C4: -0.026674076 | D4: -0.003585315 | E4: 0.01123 | F4: 0.016515692
A5: 38107 | B5: -0.017804105 | C5: -0.046674279 | D5: -0.085476236 | E5: -0.028399998 | F5: -0.043864055
A6: 38138 | B6: -0.0021877217 | C6: 0.049558317 | D6: 0.043707136 | E6: -0.0069499962 | F6: 0.015257637
A7: 38168 | B7: 0.0088462613 | C7: 0.02767475 | D7: -0.003405782 | E7: -0.0011000051 | F7: -0.0014189512
A8: 38198 | B8: 0.0089616863 | C8: -0.075513604 | D8: 0.019774085 | E8: -0.0032899965 | F8: 0.014743519
A9: 38230 | B9: 0.015418905 | C9: -0.053303303 | D9: -0.02423192 | E9: -0.0023300047 | F9: 0.023573374
A10: 38260 | B10: 0.0015233914 | C10: 0.029183188 | D10: 0.12160577 | E10: 0.0083500021 | F10: 0.0022524055
A11: 38289 | B11: 0.0080551512 | C11: 0.052396363 | D11: -0.04206768 | E11: 0.0083800005 | F11: 0.014042126
A12: 38321 | B12: -0.0024905287 | C12: 0.048616196 | D12: 0.050911975 | E12: 0.028050002 | F12: -0.0045737489
A13: 38352 | B13: 0.0070429408 | C13: 0.028487641 | D13: 0.050918294 | E13: 0.0060599975 | F13: 0.012207878
... A121: 41639 | B121: -0.0047182963 | C121: 0.041327863 | D121: 0.048938505 | E121: 0.0047046249 | F121: -0.020848048

Sheet Factors
B1: US Muni | C1: US Tbill 1-3yr | D1: US AGG | E1: Global AGG | F1: US Dollar | G1: Commodities | H1: Long Short HF | I1: Event Driven HF | J1: HF FOF Div | K1: Relative Value HF | L1: EM Bond | M1: TIPs | N1: High Yield | O1: MSCI World | P1: MSCI Canada | Q1: MSCI EAFE | R1: MSCI EM Equity | S1: MSCI Europe | T1: MSCI Japan | U1: MSCI Asia ex-J | V1: US Growth | W1: US Value | X1: US Small Cap | Y1: US Mid Cap | Z1: Gold | AA1: S&P500 | AB1: Cash
B2: LM17TR | C2: LT01TRUU | D2: LBUSTRUU | E2: LEGATRUU | F2: USTW$ | G2: BCOMTR | H2: HFRIEHI | I2: HFRIEDI | J2: HFRIFOFD | K2: HFRIRVA | L2: JPEIGLBL | M2: SPBDU1ST | N2: H0A0 | O2: NDDUWI | P2: NDDUCA | Q2: NDDUEAFE | R2: NDUEEGF | S2: NDDUE15 | T2: NDDUJN | U2: NDUECAXJ | V2: RU10GRTR | W2: RU10VATR | X2: RU20INTR | Y2: RUMCINTR | Z2: GOLDS | AA2: SPTR | AB2: LD12TRUU
B3: Factor | C3: Factor | D3: Factor | E3: Factor | F3: Factor | G3: Factor | H3: Factor | I3: Factor | J3: Factor | K3: Factor | L3: Factor | M3: Factor | N3: Factor | O3: Factor | P3: Factor | Q3: Factor | R3: Factor | S3: Factor | T3: Factor | U3: Factor | V3: Factor | W3: Factor | X3: Factor | Y3: Factor | Z3: Factor | AA3: Factor | AB3: Factor | AD3: =COUNT(D4:D123) -> 120
A4: 38016 | B4: 0.0045136227 | C4: 0.0021072108 | D4: 0.0080453023 | E4: 0.0037328896 | F4: -0.020592772 | G4: 0.018131402 | H4: 0.019500002 | I4: 0.027989998 | J4: 0.01538002 | K4: 0.012109999 | L4: 0.0051267546 | M4: 0.012326082 | N4: 0.016153008 | O4: 0.016045881 | P4: 0.010467978 | Q4: 0.014140666 | R4: 0.034921371 | S4: 0.01169109 | T4: 0.018092314 | U4: 0.060155692 | V4: 0.020422332 | W4: 0.017583724 | X4: 0.043445899 | Y4: 0.029050476 | Z4: -0.031291371 | AA4: 0.018354972 | AB4: 0.00073130599 | AD4: {=SUMPRODUCT(--(Data!A2:A121<>Factors!A4:A123))} -> 0
A5: 38044 | B5: 0.014482164 | C5: 0.0050261565 | D5: 0.010824142 | E5: 0.0051522151 | F5: 0.0056063938 | G5: 0.06488201 | H5: 0.011099999 | I5: 0.012020003 | J5: 0.010909983 | K5: 0.0055000077 | L5: 0.0034824821 | M5: 0.024775375 | N5: -0.001096591 | O5: 0.016745271 | P5: 0.021644467 | Q5: 0.023084357 | R5: 0.045857115 | S5: 0.029289311 | T5: -0.0029369057 | U5: 0.033519226 | V5: 0.0063532895 | W5: 0.0214318 | X5: 0.0089643315 | Y5: 0.0215344 | Z5: -0.015654119 | AA5: 0.013899444 | AB5: 0.00073077157
A6: 38077 | B6: -0.0047764906 | C6: 0.0032149418 | D6: 0.0074889868 | E6: 0.011076524 | F6: 0.018216191 | G6: 0.030877435 | H6: 0.0035899977 | I6: 0.00057999971 | J6: 0.0044400219 | K6: 0.0043299894 | L6: 0.024958811 | M6: 0.017390173 | N6: 0.0066713818 | O6: -0.0066356142 | P6: -0.0049301964 | Q6: 0.0056267339 | R6: 0.012497891 | S6: -0.031163746 | T6: 0.1342725 | U6: -0.017081109 | V6: -0.01855019 | W6: -0.0087520788 | X6: 0.0093196653 | Y6: 0.00020896228 | Z6: 0.076486179 | AA6: -0.015086233 | AB6: 0.0007910911
A7: 38107 | B7: -0.020876864 | C7: -0.010071723 | D7: -0.026016616 | E7: -0.036564036 | F7: 0.011406884 | G7: -0.017736548 | H7: -0.020779997 | I7: -0.005619991 | J7: -0.0070900013 | K7: -0.0050599988 | L7: -0.054311023 | M7: -0.046496063 | N7: -0.0066013073 | O7: -0.020481468 | P7: -0.08338931 | Q7: -0.022620941 | R7: -0.08188064 | S7: -0.0082941921 | T7: -0.054216945 | U7: -0.054968837 | V7: -0.011625293 | W7: -0.024439606 | X7: -0.050984404 | Y7: -0.036717449 | Z7: -0.093094149 | AA7: -0.015698428 | AB7: 0.00079046577
A8: 38138 | B8: -0.0022641617 | C8: -0.0011304661 | D8: -0.0040058707 | E8: 0.0049003612 | F8: 0.016968154 | G8: 0.016954736 | H8: -0.0019099969 | I8: -0.0031200008 | J8: -0.008780017 | K8: -0.0034499938 | L8: -0.014827674 | M8: 0.016443736 | N8: -0.015711509 | O8: 0.0091110062 | P8: 0.026529007 | Q8: 0.0033625107 | R8: -0.019950299 | S8: 0.016240393 | T8: -0.035112696 | U8: -0.033586761 | V8: 0.018638848 | W8: 0.010198344 | X8: 0.015916286 | Y8: 0.024813011 | Z8: 0.022753717 | AA8: 0.013722899 | AB8: 0.00078984142
A9: 38168 | B9: 0.0033728521 | C9: -0.00010288595 | D9: 0.0056515785 | E9: 0.002922566 | F9: -0.015797072 | G9: -0.041462267 | H9: 0.010649995 | I9: 0.017579991 | J9: 0.0036000126 | K9: 0.0016100011 | L9: 0.014683749 | M9: -0.0026148152 | N9: 0.014527413 | O9: 0.020528812 | P9: 0.042358963 | Q9: 0.021910249 | R9: 0.0042593199 | S9: 0.013375713 | T9: 0.053855015 | U9: -0.0090281508 | V9: 0.012495751 | W9: 0.023628198 | X9: 0.042113399 | Y9: 0.027662371 | Z9: -0.003286563 | AA9: 0.019444937 | AB9: 0.0006677999
A10: 38198 | B10: 0.011548622 | C10: 0.0036528271 | D10: 0.009912255 | E10: -0.0002074828 | F10: -0.012661881 | G10: 0.017666821 | H10: -0.01882 | I10: -0.0093100039 | J10: -0.0056499986 | K10: 0.0065199865 | L10: 0.029702254 | M10: 0.016134553 | N10: 0.013476433 | O10: -0.032649904 | P10: 0.00078729651 | Q10: -0.032453533 | R10: -0.018305484 | S10: -0.027519388 | T10: -0.059280322 | U10: -0.020739513 | V10: -0.056532161 | W10: -0.014086673 | X10: -0.067333187 | Y10: -0.043723073 | Z10: -0.0081166772 | AA10: -0.033096938 | AB10: 0.00097069708
A11: 38230 | B11: 0.01810155 | C11: 0.0071252819 | D11: 0.019075174 | E11: 0.021887267 | F11: 0.002919278 | G11: -0.018225954 | H11: -0.0036700004 | I11: 0.0049100023 | J11: -9.0006463e-05 | K11: 0.0082500151 | L11: 0.041283114 | M11: 0.025976512 | N11: 0.018171957 | O11: 0.0043952194 | P11: 0.00018400079 | Q11: 0.0044161094 | R11: 0.041469494 | S11: 0.00060337248 | T11: 0.0072436226 | U11: 0.048217876 | V11: -0.0049383484 | W11: 0.01422138 | X11: -0.005139345 | Y11: 0.0043296667 | Z11: 0.048075694 | AA11: 0.0040449416 | AB11: 0.0010909752
A12: 38260 | B12: 0.0037546187 | C12: -0.0008143737 | D12: 0.0027134997 | E12: 0.01181709 | F12: -0.0052064615 | G12: 0.068466451 | H12: 0.019870006 | I12: 0.013649999 | J12: 0.0082399999 | K12: 0.003559986 | L12: 0.016634612 | M12: 0.0015744976 | N12: 0.013931553 | O12: 0.018917544 | P12: 0.075638449 | Q12: 0.026135669 | R12: 0.057694842 | S12: 0.040104962 | T12: -0.02345812 | U12: 0.038444515 | V12: 0.0095108983 | W12: 0.015501419 | X12: 0.046945559 | Y12: 0.032462293 | Z12: 0.020495303 | AA12: 0.010830591 | AB12: 0.0012108736
A13: 38289 | B13: 0.0067472552 | C13: 0.0031582701 | D13: 0.0083857442 | E13: 0.023953957 | F13: -0.022843063 | G13: 0.016922451 | H13: 0.0047499926 | I13: 0.014890002 | J13: 0.0077799954 | K13: 0.0031099991 | L13: 0.016096913 | M13: 0.014200355 | N13: 0.019280206 | O13: 0.024470422 | P13: 0.062899424 | Q13: 0.034099709 | R13: 0.023892911 | S13: 0.036095656 | T13: 0.026112689 | U13: 0.0065278837 | V13: 0.015596337 | W13: 0.016623798 | X13: 0.019683992 | Y13: 0.027577689 | Z13: 0.02462642 | AA13: 0.015277272 | AB13: 0.0012094092
A14: 38321 | B14: -0.0086422779 | C14: -0.0051287259 | D14: -0.0079764104 | E14: 0.026496979 | F14: -0.038898974 | G14: -0.011978445 | H14: 0.033700004 | I14: 0.040329999 | J14: 0.026389991 | K14: 0.010670007 | L14: 0.0069900376 | M14: -0.0070595322 | N14: 0.01040404 | O14: 0.052531245 | P14: 0.040706624 | Q14: 0.068313245 | R14: 0.092572783 | S14: 0.073360512 | T14: 0.048261417 | U14: 0.088702668 | V14: 0.034398424 | W14: 0.050557961 | X14: 0.08673848 | Y14: 0.060929688 | Z14: 0.05226928 | AA14: 0.040461567 | AB14: 0.0013891405
A15: 38352 | B15: 0.0097161351 | C15: 0.0021437321 | D15: 0.0092011222 | E15: 0.015321934 | F15: -0.010706752 | G15: -0.049106105 | H15: 0.017610003 | I15: 0.027990001 | J15: 0.01505 | K15: 0.0074600062 | L15: 0.025041357 | M15: 0.013768153 | N15: 0.015081436 | O15: 0.038173111 | P15: 0.018426114 | Q15: 0.043862591 | R15: 0.048028048 | S15: 0.042347221 | T15: 0.05128994 | U15: 0.030686401 | V15: 0.039208485 | W15: 0.033486511 | X15: 0.029599683 | Y15: 0.042566524 | Z15: -0.027719259 | AA15: 0.034028662 | AB15: 0.0019300362
A16: 38383 | B16: 0.0052499575 | C16: -0.00040745645 | D16: 0.0062794738 | E16: -0.010524264 | F16: 0.011685047 | G16: 0.010434131 | H16: -0.0058200013 | I16: -0.0014799961 | J16: 0.00017001186 | K16: 0.0030099913 | L16: 0.0062656245 | M16: 0.0054076539 | N16: -0.001018961 | O16: -0.022514369 | P16: -0.039803124 | Q16: -0.018347112 | R16: 0.0025397323 | S16: -0.018534402 | T16: -0.023222332 | U16: 0.0063491433 | V16: -0.033348503 | W16: -0.017750648 | X16: -0.041723392 | Y16: -0.024751523 | Z16: -0.036150074 | AA16: -0.02437501 | AB16: 0.0016855285
... A123: 41639 | B123: -0.0015690491 | C123: -0.0013934785 | D123: -0.0056511476 | E123: -0.005970907 | F123: 0.0021583472 | G123: 0.01239895 | H123: 0.014143492 | I123: 0.011934679 | J123: 0.015226749 | K123: 0.0076849904 | L123: 0.0058312774 | M123: -0.020891371 | N123: 0.0054797726 | O123: 0.02115966 | P123: 0.016119331 | Q123: 0.014962929 | R123: -0.014457785 | S123: 0.02238006 | T123: 0.0079577136 | U123: -0.010935544 | V123: 0.028564868 | W123: 0.025327426 | X123: 0.019680206 | Y123: 0.029770245 | Z123: -0.04125743 | AA123: 0.025316045 | AB123: 5.2050802e-05

Sheet Asset_Stats
B1: A1 | C1: A2 | D1: A3 | E1: A4 | F1: A5 | H1: Date | I1: Cumulative Return A1 | J1: Drawdown A1 | K1: Cumulative Return A2 | L1: Drawdown A2 | M1: Cumulative Return A3 | N1: Drawdown A3 | O1: Cumulative Return A4 | P1: Drawdown A4 | Q1: Cumulative Return A5 | R1: Drawdown A5
A2: Mean (Monthly) | B2: =AVERAGE(Data!B2:B121) -> 0.0037928377 | C2: =AVERAGE(Data!C2:C121) -> 0.0070011042 | D2: =AVERAGE(Data!D2:D121) -> 0.007773466 | E2: =AVERAGE(Data!E2:E121) -> 0.0035551713 | F2: =AVERAGE(Data!F2:F121) -> 0.004531784 | H2: =Data!A2 -> 38016 | I2: =1+Data!B2 -> 1.0062656 | J2: =I2/MAX($I$2:I2) - 1 -> 0 | K2: =1+Data!C2 -> 1.0347705 | L2: =K2/MAX($K$2:K2) - 1 -> 0 | M2: =1+Data!D2 -> 1.0326098 | N2: =M2/MAX($M$2:M2) - 1 -> 0 | O2: =1+Data!E2 -> 1.00646 | P2: =O2/MAX($O$2:O2) - 1 -> 0 | Q2: =1+Data!F2 -> 1.0118274 | R2: =Q2/MAX($Q$2:Q2) - 1 -> 0
A3: Mean (Annualized) | B3: =B2*12 -> 0.045514052 | C3: =C2*12 -> 0.08401325 | D3: =D2*12 -> 0.093281592 | E3: =E2*12 -> 0.042662055 | F3: =F2*12 -> 0.054381408 | H3: =Data!A3 -> 38044 | I3: =I2*(1+Data!B3) -> 1.0147467 | J3: =I3/MAX($I$2:I3) - 1 -> 0 | K3: =K2*(1+Data!C3) -> 1.0011127 | L3: =K3/MAX($K$2:K3) - 1 -> -0.032526882 | M3: =M2*(1+Data!D3) -> 1.1193133 | N3: =M3/MAX($M$2:M3) - 1 -> 0 | O3: =O2*(1+Data!E3) -> 1.0265791 | P3: =O3/MAX($O$2:O3) - 1 -> 0 | Q3: =Q2*(1+Data!F3) -> 1.0358668 | R3: =Q3/MAX($Q$2:Q3) - 1 -> 0
A4: Std Dev Monthly (sample) | B4: =_xlfn.STDEV.S(Data!B2:B121) -> 0.0076565012 | C4: =_xlfn.STDEV.S(Data!C2:C121) -> 0.053770802 | D4: =_xlfn.STDEV.S(Data!D2:D121) -> 0.072056103 | E4: =_xlfn.STDEV.S(Data!E2:E121) -> 0.014021218 | F4: =_xlfn.STDEV.S(Data!F2:F121) -> 0.020592099 | H4: =Data!A4 -> 38077 | I4: =I3*(1+Data!B4) -> 1.0191943 | J4: =I4/MAX($I$2:I4) - 1 -> 0 | K4: =K3*(1+Data!C4) -> 0.9744089 | L4: =K4/MAX($K$2:K4) - 1 -> -0.058333333 | M4: =M3*(1+Data!D4) -> 1.1153003 | N4: =M4/MAX($M$2:M4) - 1 -> -0.003585315 | O4: =O3*(1+Data!E4) -> 1.0381076 | P4: =O4/MAX($O$2:O4) - 1 -> 0 | Q4: =Q3*(1+Data!F4) -> 1.0529749 | R4: =Q4/MAX($Q$2:Q4) - 1 -> 0
A5: Std Dev Annualized | B5: =B4*SQRT(12) -> 0.026522898 | C5: =C4*SQRT(12) -> 0.18626752 | D5: =D4*SQRT(12) -> 0.24960966 | E5: =E4*SQRT(12) -> 0.048570925 | F5: =F4*SQRT(12) -> 0.071333122 | H5: =Data!A5 -> 38107 | I5: =I4*(1+Data!B5) -> 1.0010485 | J5: =I5/MAX($I$2:I5) - 1 -> -0.017804105 | K5: =K4*(1+Data!C5) -> 0.92892907 | L5: =K5/MAX($K$2:K5) - 1 -> -0.10228495 | M5: =M4*(1+Data!D5) -> 1.0199686 | N5: =M5/MAX($M$2:M5) - 1 -> -0.088755092 | O5: =O4*(1+Data!E5) -> 1.0086254 | P5: =O5/MAX($O$2:O5) - 1 -> -0.028399998 | Q5: =Q4*(1+Data!F5) -> 1.0067871 | R5: =Q5/MAX($Q$2:Q5) - 1 -> -0.043864055
A6: Worst Month | B6: =MIN(Data!B2:B121) -> -0.017804105 | C6: =MIN(Data!C2:C121) -> -0.17793994 | D6: =MIN(Data!D2:D121) -> -0.26884656 | E6: =MIN(Data!E2:E121) -> -0.028399998 | F6: =MIN(Data!F2:F121) -> -0.09429025 | H6: =Data!A6 -> 38138 | I6: =I5*(1+Data!B6) -> 0.99885849 | J6: =I6/MAX($I$2:I6) - 1 -> -0.019952876 | K6: =K5*(1+Data!C6) -> 0.97496523 | L6: =K6/MAX($K$2:K6) - 1 -> -0.057795699 | M6: =M5*(1+Data!D6) -> 1.0645485 | N6: =M6/MAX($M$2:M6) - 1 -> -0.048927187 | O6: =O5*(1+Data!E6) -> 1.0016154 | P6: =O6/MAX($O$2:O6) - 1 -> -0.035152615 | Q6: =Q5*(1+Data!F6) -> 1.0221483 | R6: =Q6/MAX($Q$2:Q6) - 1 -> -0.02927568
A7: Best Month | B7: =MAX(Data!B2:B121) -> 0.039284057 | C7: =MAX(Data!C2:C121) -> 0.12138805 | D7: =MAX(Data!D2:D121) -> 0.22182415 | E7: =MAX(Data!E2:E121) -> 0.042192468 | F7: =MAX(Data!F2:F121) -> 0.072092418 | H7: =Data!A7 -> 38168 | I7: =I6*(1+Data!B7) -> 1.0076946 | J7: =I7/MAX($I$2:I7) - 1 -> -0.011283123 | K7: =K6*(1+Data!C7) -> 1.0019471 | L7: =K7/MAX($K$2:K7) - 1 -> -0.03172043 | M7: =M6*(1+Data!D7) -> 1.0609229 | N7: =M7/MAX($M$2:M7) - 1 -> -0.052166334 | O7: =O6*(1+Data!E7) -> 1.0005136 | P7: =O7/MAX($O$2:O7) - 1 -> -0.036213952 | Q7: =Q6*(1+Data!F7) -> 1.0206979 | R7: =Q7/MAX($Q$2:Q7) - 1 -> -0.03065309
A8: Skewness | B8: =SKEW(Data!B2:B121) -> 0.46230495 | C8: =SKEW(Data!C2:C121) -> -0.53708439 | D8: =SKEW(Data!D2:D121) -> -0.3399279 | E8: =SKEW(Data!E2:E121) -> 0.24160526 | F8: =SKEW(Data!F2:F121) -> -0.91822856 | H8: =Data!A8 -> 38198 | I8: =I7*(1+Data!B8) -> 1.0167253 | J8: =I8/MAX($I$2:I8) - 1 -> -0.002422553 | K8: =K7*(1+Data!C8) -> 0.92628651 | L8: =K8/MAX($K$2:K8) - 1 -> -0.10483871 | M8: =M7*(1+Data!D8) -> 1.0819017 | N8: =M8/MAX($M$2:M8) - 1 -> -0.03342379 | O8: =O7*(1+Data!E8) -> 0.99722195 | P8: =O8/MAX($O$2:O8) - 1 -> -0.039384804 | Q8: =Q7*(1+Data!F8) -> 1.0357466 | R8: =Q8/MAX($Q$2:Q8) - 1 -> -0.016361506
A9: Excess kurtosis | B9: =KURT(Data!B2:B121) -> 3.3598901 | C9: =KURT(Data!C2:C121) -> 0.69459609 | D9: =KURT(Data!D2:D121) -> 1.4988551 | E9: =KURT(Data!E2:E121) -> -0.21081532 | F9: =KURT(Data!F2:F121) -> 5.3680402 | H9: =Data!A9 -> 38230 | I9: =I8*(1+Data!B9) -> 1.0324021 | J9: =I9/MAX($I$2:I9) - 1 -> 0 | K9: =K8*(1+Data!C9) -> 0.87691238 | L9: =K9/MAX($K$2:K9) - 1 -> -0.15255376 | M9: =M8*(1+Data!D9) -> 1.0556851 | N9: =M9/MAX($M$2:M9) - 1 -> -0.056845788 | O9: =O8*(1+Data!E9) -> 0.99489842 | P9: =O9/MAX($O$2:O9) - 1 -> -0.041623042 | Q9: =Q8*(1+Data!F9) -> 1.0601627 | R9: =Q9/MAX($Q$2:Q9) - 1 -> 0
A10: Jarque-Bera stat | B10: =120/6 * (B8^2 + B9^2/4) -> 60.718824 | C10: =120/6 * (C8^2 + C9^2/4) -> 8.1815115 | D10: =120/6 * (D8^2 + D9^2/4) -> 13.543853 | E10: =120/6 * (E8^2 + E9^2/4) -> 1.3896775 | F10: =120/6 * (F8^2 + F9^2/4) -> 160.94215 | G10: (n / 6) * (S^2 + K^2 / 4) | H10: =Data!A10 -> 38260 | I10: =I9*(1+Data!B10) -> 1.0339748 | J10: =I10/MAX($I$2:I10) - 1 -> 0 | K10: =K9*(1+Data!C10) -> 0.90250348 | L10: =K10/MAX($K$2:K10) - 1 -> -0.12782258 | M10: =M9*(1+Data!D10) -> 1.1840625 | N10: =M10/MAX($M$2:M10) - 1 -> 0 | O10: =O9*(1+Data!E10) -> 1.0032058 | P10: =O10/MAX($O$2:O10) - 1 -> -0.033620593 | Q10: =Q9*(1+Data!F10) -> 1.0625506 | R10: =Q10/MAX($Q$2:Q10) - 1 -> 0
A11: JB p-value | B11: =_xlfn.CHISQ.DIST.RT(B10, 2) -> 6.5324331e-14 | C11: =_xlfn.CHISQ.DIST.RT(C10, 2) -> 0.016726587 | D11: =_xlfn.CHISQ.DIST.RT(D10, 2) -> 0.0011454859 | E11: =_xlfn.CHISQ.DIST.RT(E10, 2) -> 0.49915493 | F11: =_xlfn.CHISQ.DIST.RT(F10, 2) -> 1.1268223e-35 | H11: =Data!A11 -> 38289 | I11: =I10*(1+Data!B11) -> 1.0423037 | J11: =I11/MAX($I$2:I11) - 1 -> 0 | K11: =K10*(1+Data!C11) -> 0.94979138 | L11: =K11/MAX($K$2:K11) - 1 -> -0.082123656 | M11: =M10*(1+Data!D11) -> 1.1342517 | N11: =M11/MAX($M$2:M11) - 1 -> -0.04206768 | O11: =O10*(1+Data!E11) -> 1.0116127 | P11: =O11/MAX($O$2:O11) - 1 -> -0.025522333 | Q11: =Q10*(1+Data!F11) -> 1.0774711 | R11: =Q11/MAX($Q$2:Q11) - 1 -> 0
A12: Normality | B12: =IF(B11<0.05, "REJECT", "PASS") -> REJECT | C12: =IF(C11<0.05, "REJECT", "PASS") -> REJECT | D12: =IF(D11<0.05, "REJECT", "PASS") -> REJECT | E12: =IF(E11<0.05, "REJECT", "PASS") -> PASS | F12: =IF(F11<0.05, "REJECT", "PASS") -> REJECT | H12: =Data!A12 -> 38321 | I12: =I11*(1+Data!B12) -> 1.0397078 | J12: =I12/MAX($I$2:I12) - 1 -> -0.0024905287 | K12: =K11*(1+Data!C12) -> 0.99596662 | L12: =K12/MAX($K$2:K12) - 1 -> -0.0375 | M12: =M11*(1+Data!D12) -> 1.1919987 | N12: =M12/MAX($M$2:M12) - 1 -> 0 | O12: =O11*(1+Data!E12) -> 1.0399884 | P12: =O12/MAX($O$2:O12) - 1 -> 0 | Q12: =Q11*(1+Data!F12) -> 1.072543 | R12: =Q12/MAX($Q$2:Q12) - 1 -> -0.0045737489
A13: 95% historical VaR | B13: =_xlfn.PERCENTILE.INC(Data!B2:B121, 0.05) -> -0.0070430627 | C13: =_xlfn.PERCENTILE.INC(Data!C2:C121, 0.05) -> -0.081664641 | D13: =_xlfn.PERCENTILE.INC(Data!D2:D121, 0.05) -> -0.096636539 | E13: =_xlfn.PERCENTILE.INC(Data!E2:E121, 0.05) -> -0.017456733 | F13: =_xlfn.PERCENTILE.INC(Data!F2:F121, 0.05) -> -0.029011251 | H13: =Data!A13 -> 38352 | I13: =I12*(1+Data!B13) -> 1.0470304 | J13: =I13/MAX($I$2:I13) - 1 -> 0 | K13: =K12*(1+Data!C13) -> 1.0243394 | L13: =K13/MAX($K$2:K13) - 1 -> -0.010080645 | M13: =M12*(1+Data!D13) -> 1.2526933 | N13: =M13/MAX($M$2:M13) - 1 -> 0 | O13: =O12*(1+Data!E13) -> 1.0462907 | P13: =O13/MAX($O$2:O13) - 1 -> 0 | Q13: =Q12*(1+Data!F13) -> 1.0856364 | R13: =Q13/MAX($Q$2:Q13) - 1 -> 0
A14: 99% historical VaR | B14: =_xlfn.PERCENTILE.INC(Data!B2:B121, 0.01) -> -0.015093948 | C14: =_xlfn.PERCENTILE.INC(Data!C2:C121, 0.01) -> -0.12683051 | D14: =_xlfn.PERCENTILE.INC(Data!D2:D121, 0.01) -> -0.18773159 | E14: =_xlfn.PERCENTILE.INC(Data!E2:E121, 0.01) -> -0.025625164 | F14: =_xlfn.PERCENTILE.INC(Data!F2:F121, 0.01) -> -0.052599643 | H14: =Data!A14 -> 38383 | I14: =I13*(1+Data!B14) -> 1.0526027 | J14: =I14/MAX($I$2:I14) - 1 -> 0 | K14: =K13*(1+Data!C14) -> 0.97065369 | L14: =K14/MAX($K$2:K14) - 1 -> -0.061962366 | M14: =M13*(1+Data!D14) -> 1.2198205 | N14: =M14/MAX($M$2:M14) - 1 -> -0.02624166 | O14: =O13*(1+Data!E14) -> 1.0402641 | P14: =O14/MAX($O$2:O14) - 1 -> -0.005760002 | Q14: =Q13*(1+Data!F14) -> 1.0881686 | R14: =Q14/MAX($Q$2:Q14) - 1 -> 0
A15: 95% historical CVaR | B15: =AVERAGEIF(Data!B2:B121, "<="&B13) -> -0.012979702 | C15: =AVERAGEIF(Data!C2:C121, "<="&C13) -> -0.11998939 | D15: =AVERAGEIF(Data!D2:D121, "<="&D13) -> -0.15337411 | E15: =AVERAGEIF(Data!E2:E121, "<="&E13) -> -0.022777601 | F15: =AVERAGEIF(Data!F2:F121, "<="&F13) -> -0.0526241 | H15: =Data!A15 -> 38411 | I15: =I14*(1+Data!B15) -> 1.0477237 | J15: =I15/MAX($I$2:I15) - 1 -> -0.0046350966 | K15: =K14*(1+Data!C15) -> 0.97107093 | L15: =K15/MAX($K$2:K15) - 1 -> -0.06155914 | M15: =M14*(1+Data!D15) -> 1.2925751 | N15: =M15/MAX($M$2:M15) - 1 -> 0 | O15: =O14*(1+Data!E15) -> 1.0590513 | P15: =O15/MAX($O$2:O15) - 1 -> 0 | Q15: =Q14*(1+Data!F15) -> 1.0818062 | R15: =Q15/MAX($Q$2:Q15) - 1 -> -0.0058469197
A16: 99% historical CVaR | B16: =AVERAGEIF(Data!B2:B121, "<="&B14) -> -0.016568381 | C16: =AVERAGEIF(Data!C2:C121, "<="&C14) -> -0.1525952 | D16: =AVERAGEIF(Data!D2:D121, "<="&D14) -> -0.2347165 | E16: =AVERAGEIF(Data!E2:E121, "<="&E14) -> -0.027318726 | F16: =AVERAGEIF(Data!F2:F121, "<="&F14) -> -0.074086158 | H16: =Data!A16 -> 38442 | I16: =I15*(1+Data!B16) -> 1.0457789 | J16: =I16/MAX($I$2:I16) - 1 -> -0.0064827088 | K16: =K15*(1+Data!C16) -> 0.9488178 | L16: =K16/MAX($K$2:K16) - 1 -> -0.083064516 | M16: =M15*(1+Data!D16) -> 1.30815 | N16: =M16/MAX($M$2:M16) - 1 -> 0 | O16: =O15*(1+Data!E16) -> 1.0526864 | P16: =O16/MAX($O$2:O16) - 1 -> -0.0060100031 | Q16: =Q15*(1+Data!F16) -> 1.0786971 | R16: =Q16/MAX($Q$2:Q16) - 1 -> -0.0087041046
A17: Sharpe (monthly) | B17: =(B2 - AVERAGE(Factors!AB4:AB123)) / B4 -> 0.32340152 | C17: =(C2 - AVERAGE(Factors!AB4:AB123)) / C4 -> 0.10571519 | D17: =(D2 - AVERAGE(Factors!AB4:AB123)) / D4 -> 0.089607294 | E17: =(E2 - AVERAGE(Factors!AB4:AB123)) / E4 -> 0.15964787 | F17: =(F2 - AVERAGE(Factors!AB4:AB123)) / F4 -> 0.15613126 | H17: =Data!A17 -> 38471 | I17: =I16*(1+Data!B17) -> 1.0573547 | J17: =I17/MAX($I$2:I17) - 1 -> 0 | K17: =K16*(1+Data!C17) -> 0.91126565 | L17: =K17/MAX($K$2:K17) - 1 -> -0.11935484 | M17: =M16*(1+Data!D17) -> 1.2503684 | N17: =M17/MAX($M$2:M17) - 1 -> -0.044170462 | O17: =O16*(1+Data!E17) -> 1.0415174 | P17: =O17/MAX($O$2:O17) - 1 -> -0.016556239 | Q17: =Q16*(1+Data!F17) -> 1.1021515 | R17: =Q17/MAX($Q$2:Q17) - 1 -> 0
A18: Sharpe (annualized) | B18: =B17 *SQRT(12) -> 1.1202957 | C18: =C17 *SQRT(12) -> 0.36620817 | D18: =D17 *SQRT(12) -> 0.31040877 | E18: =E17 *SQRT(12) -> 0.55303645 | F18: =F17 *SQRT(12) -> 0.54085456 | H18: =Data!A18 -> 38503 | I18: =I17*(1+Data!B18) -> 1.0656836 | J18: =I18/MAX($I$2:I18) - 1 -> 0 | K18: =K17*(1+Data!C18) -> 0.9821975 | L18: =K18/MAX($K$2:K18) - 1 -> -0.050806452 | M18: =M17*(1+Data!D18) -> 1.2357414 | N18: =M18/MAX($M$2:M18) - 1 -> -0.05535192 | O18: =O17*(1+Data!E18) -> 1.0451106 | P18: =O18/MAX($O$2:O18) - 1 -> -0.013163355 | Q18: =Q17*(1+Data!F18) -> 1.1084098 | R18: =Q18/MAX($Q$2:Q18) - 1 -> 0
A19: Max Drawdown | B19: =MIN(J2:J121) -> -0.028466629 | C19: =MIN(L2:L121) -> -0.50806048 | D19: =MIN(N2:N121) -> -0.62329575 | E19: =MIN(P2:P121) -> -0.080200886 | F19: =MIN(R2:R121) -> -0.13545668 | H19: =Data!A19 -> 38533 | I19: =I18*(1+Data!B19) -> 1.0695478 | J19: =I19/MAX($I$2:I19) - 1 -> 0 | K19: =K18*(1+Data!C19) -> 0.9650904 | L19: =K19/MAX($K$2:K19) - 1 -> -0.06733871 | M19: =M18*(1+Data!D19) -> 1.2306282 | N19: =M19/MAX($M$2:M19) - 1 -> -0.05926067 | O19: =O18*(1+Data!E19) -> 1.0561365 | P19: =O19/MAX($O$2:O19) - 1 -> -0.0027522269 | Q19: =Q18*(1+Data!F19) -> 1.1118635 | R19: =Q19/MAX($Q$2:Q19) - 1 -> 0
H20: =Data!A20 -> 38562 | I20: =I19*(1+Data!B20) -> 1.0641869 | J20: =I20/MAX($I$2:I20) - 1 -> -0.0050122936 | K20: =K19*(1+Data!C20) -> 1.0215577 | L20: =K20/MAX($K$2:K20) - 1 -> -0.012768817 | M20: =M19*(1+Data!D20) -> 1.3075273 | N20: =M20/MAX($M$2:M20) - 1 -> -0.0004760318 | O20: =O19*(1+Data!E20) -> 1.0639625 | P20: =O20/MAX($O$2:O20) - 1 -> 0 | Q20: =Q19*(1+Data!F20) -> 1.0930085 | R20: =Q20/MAX($Q$2:Q20) - 1 -> -0.016957947
A21: Correlation Matrix | B21: Asset 1 | C21: Asset 2 | D21: Asset3 | E21: Asset 4 | F21: Asset 5 | H21: =Data!A21 -> 38595 | I21: =I20*(1+Data!B21) -> 1.073615 | J21: =I21/MAX($I$2:I21) - 1 -> 0 | K21: =K20*(1+Data!C21) -> 1.0191933 | L21: =K21/MAX($K$2:K21) - 1 -> -0.015053763 | M21: =M20*(1+Data!D21) -> 1.3358611 | N21: =M21/MAX($M$2:M21) - 1 -> 0 | O21: =O20*(1+Data!E21) -> 1.0716762 | P21: =O21/MAX($O$2:O21) - 1 -> 0 | Q21: =Q20*(1+Data!F21) -> 1.1177211 | R21: =Q21/MAX($Q$2:Q21) - 1 -> 0
A22: Asset 1 | B22: 1 | H22: =Data!A22 -> 38625 | I22: =I21*(1+Data!B22) -> 1.0679666 | J22: =I22/MAX($I$2:I22) - 1 -> -0.0052610853 | K22: =K21*(1+Data!C22) -> 1.022114 | L22: =K22/MAX($K$2:K22) - 1 -> -0.012231183 | M22: =M21*(1+Data!D22) -> 1.3601749 | N22: =M22/MAX($M$2:M22) - 1 -> 0 | O22: =O21*(1+Data!E22) -> 1.0942672 | P22: =O22/MAX($O$2:O22) - 1 -> 0 | Q22: =Q21*(1+Data!F22) -> 1.1139549 | R22: =Q22/MAX($Q$2:Q22) - 1 -> -0.0033695138
A23: Asset 2 | B23: -0.14089657 | C23: 1 | H23: =Data!A23 -> 38656 | I23: =I22*(1+Data!B23) -> 1.0605256 | J23: =I23/MAX($I$2:I23) - 1 -> -0.012191856 | K23: =K22*(1+Data!C23) -> 0.99972184 | L23: =K23/MAX($K$2:K23) - 1 -> -0.033870968 | M23: =M22*(1+Data!D23) -> 1.425104 | N23: =M23/MAX($M$2:M23) - 1 -> 0 | O23: =O22*(1+Data!E23) -> 1.0873295 | P23: =O23/MAX($O$2:O23) - 1 -> -0.0063400049 | Q23: =Q22*(1+Data!F23) -> 1.1005729 | R23: =Q23/MAX($Q$2:Q23) - 1 -> -0.015342041
A24: Asset3 | B24: -0.07002401 | C24: 0.48638569 | D24: 1 | H24: =Data!A24 -> 38686 | I24: =I23*(1+Data!B24) -> 1.0639755 | J24: =I24/MAX($I$2:I24) - 1 -> -0.0089784989 | K24: =K23*(1+Data!C24) -> 1.0636996 | L24: =K24/MAX($K$2:K24) - 1 -> 0 | M24: =M23*(1+Data!D24) -> 1.5575636 | N24: =M24/MAX($M$2:M24) - 1 -> 0 | O24: =O23*(1+Data!E24) -> 1.1032263 | P24: =O24/MAX($O$2:O24) - 1 -> 0 | Q24: =Q23*(1+Data!F24) -> 1.1021836 | R24: =Q24/MAX($Q$2:Q24) - 1 -> -0.013901037
A25: Asset 4 | B25: 0.032551131 | C25: 0.22608792 | D25: 0.3819485 | E25: 1 | H25: =Data!A25 -> 38716 | I25: =I24*(1+Data!B25) -> 1.0743844 | J25: =I25/MAX($I$2:I25) - 1 -> 0 | K25: =K24*(1+Data!C25) -> 1.0325452 | L25: =K25/MAX($K$2:K25) - 1 -> -0.029288703 | M25: =M24*(1+Data!D25) -> 1.6719713 | N25: =M25/MAX($M$2:M25) - 1 -> 0 | O25: =O24*(1+Data!E25) -> 1.1172924 | P25: =O25/MAX($O$2:O25) - 1 -> 0 | Q25: =Q24*(1+Data!F25) -> 1.1107256 | R25: =Q25/MAX($Q$2:Q25) - 1 -> -0.0062586926
A26: Asset 5 | B26: 0.66610041 | C26: 0.12518698 | D26: 0.22467058 | E26: 0.1519541 | F26: 1 | H26: =Data!A26 -> 38748 | I26: =I25*(1+Data!B26) -> 1.0778428 | J26: =I26/MAX($I$2:I26) - 1 -> 0 | K26: =K25*(1+Data!C26) -> 1.0656467 | L26: =K26/MAX($K$2:K26) - 1 -> 0 | M26: =M25*(1+Data!D26) -> 1.867568 | N26: =M26/MAX($M$2:M26) - 1 -> 0 | O26: =O25*(1+Data!E26) -> 1.1441186 | P26: =O26/MAX($O$2:O26) - 1 -> 0 | Q26: =Q25*(1+Data!F26) -> 1.1118715 | R26: =Q26/MAX($Q$2:Q26) - 1 -> -0.0052335001
H27: =Data!A27 -> 38776 | I27: =I26*(1+Data!B27) -> 1.0828655 | J27: =I27/MAX($I$2:I27) - 1 -> 0 | K27: =K26*(1+Data!C27) -> 1.055911 | L27: =K27/MAX($K$2:K27) - 1 -> -0.0091359958 | M27: =M26*(1+Data!D27) -> 1.834287 | N27: =M27/MAX($M$2:M27) - 1 -> -0.017820491 | O27: =O26*(1+Data!E27) -> 1.1387184 | P27: =O27/MAX($O$2:O27) - 1 -> -0.0047199914 | Q27: =Q26*(1+Data!F27) -> 1.1086342 | R27: =Q27/MAX($Q$2:Q27) - 1 -> -0.0081298482
H28: =Data!A28 -> 38807 | I28: =I27*(1+Data!B28) -> 1.0736826 | J28: =I28/MAX($I$2:I28) - 1 -> -0.0084801349 | K28: =K27*(1+Data!C28) -> 1.0751043 | L28: =K28/MAX($K$2:K28) - 1 -> 0 | M28: =M27*(1+Data!D28) -> 1.9737627 | N28: =M28/MAX($M$2:M28) - 1 -> 0 | O28: =O27*(1+Data!E28) -> 1.1517795 | P28: =O28/MAX($O$2:O28) - 1 -> 0 | Q28: =Q27*(1+Data!F28) -> 1.0900677 | R28: =Q28/MAX($Q$2:Q28) - 1 -> -0.024740834
H29: =Data!A29 -> 38835 | I29: =I28*(1+Data!B29) -> 1.0737418 | J29: =I29/MAX($I$2:I29) - 1 -> -0.0084254748 | K29: =K28*(1+Data!C29) -> 1.0628651 | L29: =K29/MAX($K$2:K29) - 1 -> -0.011384217 | M29: =M28*(1+Data!D29) -> 2.4115909 | N29: =M29/MAX($M$2:M29) - 1 -> 0 | O29: =O28*(1+Data!E29) -> 1.1836146 | P29: =O29/MAX($O$2:O29) - 1 -> 0 | Q29: =Q28*(1+Data!F29) -> 1.0928563 | R29: =Q29/MAX($Q$2:Q29) - 1 -> -0.02224596
H30: =Data!A30 -> 38868 | I30: =I29*(1+Data!B30) -> 1.071704 | J30: =I30/MAX($I$2:I30) - 1 -> -0.010307346 | K30: =K29*(1+Data!C30) -> 0.98748261 | L30: =K30/MAX($K$2:K30) - 1 -> -0.081500647 | M30: =M29*(1+Data!D30) -> 2.6245477 | N30: =M30/MAX($M$2:M30) - 1 -> 0 | O30: =O29*(1+Data!E30) -> 1.1674701 | P30: =O30/MAX($O$2:O30) - 1 -> -0.013640001 | Q30: =Q29*(1+Data!F30) -> 1.0953163 | R30: =Q30/MAX($Q$2:Q30) - 1 -> -0.020045022
H31: =Data!A31 -> 38898 | I31: =I30*(1+Data!B31) -> 1.0737756 | J31: =I31/MAX($I$2:I31) - 1 -> -0.0083942404 | K31: =K30*(1+Data!C31) -> 0.97121001 | L31: =K31/MAX($K$2:K31) - 1 -> -0.096636481 | M31: =M30*(1+Data!D31) -> 2.4886353 | N31: =M31/MAX($M$2:M31) - 1 -> -0.051785046 | O31: =O30*(1+Data!E31) -> 1.1618196 | P31: =O31/MAX($O$2:O31) - 1 -> -0.018413978 | Q31: =Q30*(1+Data!F31) -> 1.0998197 | R31: =Q31/MAX($Q$2:Q31) - 1 -> -0.016015944
H32: =Data!A32 -> 38929 | I32: =I31*(1+Data!B32) -> 1.0891565 | J32: =I32/MAX($I$2:I32) - 1 -> 0 | K32: =K31*(1+Data!C32) -> 0.93449235 | L32: =K32/MAX($K$2:K32) - 1 -> -0.13078913 | M32: =M31*(1+Data!D32) -> 2.6483494 | N32: =M32/MAX($M$2:M32) - 1 -> 0 | O32: =O31*(1+Data!E32) -> 1.1587989 | P32: =O32/MAX($O$2:O32) - 1 -> -0.020966101 | Q32: =Q31*(1+Data!F32) -> 1.1159902 | R32: =Q32/MAX($Q$2:Q32) - 1 -> -0.0015485425
H33: =Data!A33 -> 38960 | I33: =I32*(1+Data!B33) -> 1.1049855 | J33: =I33/MAX($I$2:I33) - 1 -> 0 | K33: =K32*(1+Data!C33) -> 1.0127955 | L33: =K33/MAX($K$2:K33) - 1 -> -0.057956016 | M33: =M32*(1+Data!D33) -> 2.6873871 | N33: =M33/MAX($M$2:M33) - 1 -> 0 | O33: =O32*(1+Data!E33) -> 1.1614873 | P33: =O33/MAX($O$2:O33) - 1 -> -0.018694746 | Q33: =Q32*(1+Data!F33) -> 1.1340038 | R33: =Q33/MAX($Q$2:Q33) - 1 -> 0
H34: =Data!A34 -> 38989 | I34: =I33*(1+Data!B34) -> 1.1127139 | J34: =I34/MAX($I$2:I34) - 1 -> 0 | K34: =K33*(1+Data!C34) -> 1.0534075 | L34: =K34/MAX($K$2:K34) - 1 -> -0.020181113 | M34: =M33*(1+Data!D34) -> 2.720246 | N34: =M34/MAX($M$2:M34) - 1 -> 0 | O34: =O33*(1+Data!E34) -> 1.15266 | P34: =O34/MAX($O$2:O34) - 1 -> -0.026152669 | Q34: =Q33*(1+Data!F34) -> 1.1375696 | R34: =Q34/MAX($Q$2:Q34) - 1 -> 0
H35: =Data!A35 -> 39021 | I35: =I34*(1+Data!B35) -> 1.1207806 | J35: =I35/MAX($I$2:I35) - 1 -> 0 | K35: =K34*(1+Data!C35) -> 1.0968011 | L35: =K35/MAX($K$2:K35) - 1 -> 0 | M35: =M34*(1+Data!D35) -> 2.9369737 | N35: =M35/MAX($M$2:M35) - 1 -> 0 | O35: =O34*(1+Data!E35) -> 1.1657657 | P35: =O35/MAX($O$2:O35) - 1 -> -0.01508002 | Q35: =Q34*(1+Data!F35) -> 1.1350695 | R35: =Q35/MAX($Q$2:Q35) - 1 -> -0.0021977558
H36: =Data!A36 -> 39051 | I36: =I35*(1+Data!B36) -> 1.1336332 | J36: =I36/MAX($I$2:I36) - 1 -> 0 | K36: =K35*(1+Data!C36) -> 1.1324061 | L36: =K36/MAX($K$2:K36) - 1 -> 0 | M36: =M35*(1+Data!D36) -> 2.957143 | N36: =M36/MAX($M$2:M36) - 1 -> 0 | O36: =O35*(1+Data!E36) -> 1.1932428 | P36: =O36/MAX($O$2:O36) - 1 -> 0 | Q36: =Q35*(1+Data!F36) -> 1.1478585 | R36: =Q36/MAX($Q$2:Q36) - 1 -> 0
H37: =Data!A37 -> 39080 | I37: =I36*(1+Data!B37) -> 1.1305131 | J37: =I37/MAX($I$2:I37) - 1 -> -0.0027523346 | K37: =K36*(1+Data!C37) -> 1.1172462 | L37: =K37/MAX($K$2:K37) - 1 -> -0.013387374 | M37: =M36*(1+Data!D37) -> 2.8816069 | N37: =M37/MAX($M$2:M37) - 1 -> -0.025543594 | O37: =O36*(1+Data!E37) -> 1.208397 | P37: =O37/MAX($O$2:O37) - 1 -> 0 | Q37: =Q36*(1+Data!F37) -> 1.1218558 | R37: =Q37/MAX($Q$2:Q37) - 1 -> -0.022653179
H38: =Data!A38 -> 39113 | I38: =I37*(1+Data!B38) -> 1.1312403 | J38: =I38/MAX($I$2:I38) - 1 -> -0.0021108691 | K38: =K37*(1+Data!C38) -> 1.1349096 | L38: =K38/MAX($K$2:K38) - 1 -> 0 | M38: =M37*(1+Data!D38) -> 2.7607022 | N38: =M38/MAX($M$2:M38) - 1 -> -0.066429255 | O38: =O37*(1+Data!E38) -> 1.2128898 | P38: =O38/MAX($O$2:O38) - 1 -> 0 | Q38: =Q37*(1+Data!F38) -> 1.1248207 | R38: =Q38/MAX($Q$2:Q38) - 1 -> -0.020070228
... H121: =Data!A121 -> 41639 | I121: =I120*(1+Data!B121) -> 1.569607 | J121: =I121/MAX($I$2:I121) - 1 -> -0.018900235 | K121: =K120*(1+Data!C121) -> 1.9414465 | L121: =K121/MAX($K$2:K121) - 1 -> 0 | M121: =M120*(1+Data!D121) -> 1.8522172 | N121: =M121/MAX($M$2:M121) - 1 -> -0.44909233 | O121: =O120*(1+Data!E121) -> 1.5132686 | P121: =O121/MAX($O$2:O121) - 1 -> -0.063327799 | Q121: =Q120*(1+Data!F121) -> 1.6773749 | R121: =Q121/MAX($Q$2:Q121) - 1 -> -0.10802415

Sheet Histograms
A1: A1 Histogram
A2: Bin Upper | B2: Frequency | C2: Normal PDF
A3: -0.025 | B3: {=FREQUENCY(Data!B2:B121, A3:A14)} -> 0 | C3: =_xlfn.NORM.DIST(A3-0.0025, Asset_Stats!$B$2, Asset_Stats!$B$4, FALSE) * 0.005 * 120 -> 0.0073744686
A4: =A3+0.005 -> -0.02 | B4: 0 | C4: =_xlfn.NORM.DIST(A4-0.0025, Asset_Stats!$B$2, Asset_Stats!$B$4, FALSE) * 0.005 * 120 -> 0.08595537
A5: =A4+0.005 -> -0.015 | B5: 2 | C5: =_xlfn.NORM.DIST(A5-0.0025, Asset_Stats!$B$2, Asset_Stats!$B$4, FALSE) * 0.005 * 120 -> 0.65404201
A6: =A5+0.005 -> -0.01 | B6: 2 | C6: =_xlfn.NORM.DIST(A6-0.0025, Asset_Stats!$B$2, Asset_Stats!$B$4, FALSE) * 0.005 * 120 -> 3.2488423
A7: =A6+0.005 -> -0.005 | B7: 10 | C7: =_xlfn.NORM.DIST(A7-0.0025, Asset_Stats!$B$2, Asset_Stats!$B$4, FALSE) * 0.005 * 120 -> 10.53518
A8: =A7+0.005 -> 0 | B8: 17 | C8: =_xlfn.NORM.DIST(A8-0.0025, Asset_Stats!$B$2, Asset_Stats!$B$4, FALSE) * 0.005 * 120 -> 22.302094
A9: =A8+0.005 -> 0.005 | B9: 37 | C9: =_xlfn.NORM.DIST(A9-0.0025, Asset_Stats!$B$2, Asset_Stats!$B$4, FALSE) * 0.005 * 120 -> 30.820499
A10: =A9+0.005 -> 0.01 | B10: 30 | C10: =_xlfn.NORM.DIST(A10-0.0025, Asset_Stats!$B$2, Asset_Stats!$B$4, FALSE) * 0.005 * 120 -> 27.805073
A11: =A10+0.005 -> 0.015 | B11: 17 | C11: =_xlfn.NORM.DIST(A11-0.0025, Asset_Stats!$B$2, Asset_Stats!$B$4, FALSE) * 0.005 * 120 -> 16.375658
A12: =A11+0.005 -> 0.02 | B12: 4 | C12: =_xlfn.NORM.DIST(A12-0.0025, Asset_Stats!$B$2, Asset_Stats!$B$4, FALSE) * 0.005 * 120 -> 6.2959874
A13: =A12+0.005 -> 0.025 | B13: 0 | C13: =_xlfn.NORM.DIST(A13-0.0025, Asset_Stats!$B$2, Asset_Stats!$B$4, FALSE) * 0.005 * 120 -> 1.5802263
A14: =A13+0.005 -> 0.03 | B14: 0 | C14: =_xlfn.NORM.DIST(A14-0.0025, Asset_Stats!$B$2, Asset_Stats!$B$4, FALSE) * 0.005 * 120 -> 0.25891967
B15: 1
A16: A2 Histogram
A17: Bin Upper | B17: Frequency | C17: Normal PDF
A18: -0.22 | B18: {=FREQUENCY(Data!C4:C121, A18:A27)} -> 0 | C18: =_xlfn.NORM.DIST(A18-0.0025, Asset_Stats!$C$2, Asset_Stats!$C$4, FALSE) * 0.04 * 120 -> 0.0039430875
A19: =A18+0.04 -> -0.18 | B19: 0 | C19: =_xlfn.NORM.DIST(A19-0.0025, Asset_Stats!$C$2, Asset_Stats!$C$4, FALSE) * 0.04 * 120 -> 0.071545275
A20: =A19+0.04 -> -0.14 | B20: 1 | C20: =_xlfn.NORM.DIST(A20-0.0025, Asset_Stats!$C$2, Asset_Stats!$C$4, FALSE) * 0.04 * 120 -> 0.74643788
A21: =A20+0.04 -> -0.1 | B21: 3 | C21: =_xlfn.NORM.DIST(A21-0.0025, Asset_Stats!$C$2, Asset_Stats!$C$4, FALSE) * 0.04 * 120 -> 4.4779019
A22: =A21+0.04 -> -0.06 | B22: 11 | C22: =_xlfn.NORM.DIST(A22-0.0025, Asset_Stats!$C$2, Asset_Stats!$C$4, FALSE) * 0.04 * 120 -> 15.446271
A23: =A22+0.04 -> -0.02 | B23: 17 | C23: =_xlfn.NORM.DIST(A23-0.0025, Asset_Stats!$C$2, Asset_Stats!$C$4, FALSE) * 0.04 * 120 -> 30.636624
A24: =A23+0.04 -> 0.02 | B24: 34 | C24: =_xlfn.NORM.DIST(A24-0.0025, Asset_Stats!$C$2, Asset_Stats!$C$4, FALSE) * 0.04 * 120 -> 34.940278
A25: =A24+0.04 -> 0.06 | B25: 37 | C25: =_xlfn.NORM.DIST(A25-0.0025, Asset_Stats!$C$2, Asset_Stats!$C$4, FALSE) * 0.04 * 120 -> 22.912896
A26: =A25+0.04 -> 0.1 | B26: 11 | C26: =_xlfn.NORM.DIST(A26-0.0025, Asset_Stats!$C$2, Asset_Stats!$C$4, FALSE) * 0.04 * 120 -> 8.639762
A27: =A26+0.04 -> 0.14 | B27: 4 | C27: =_xlfn.NORM.DIST(A27-0.0025, Asset_Stats!$C$2, Asset_Stats!$C$4, FALSE) * 0.04 * 120 -> 1.8732328
B28: 0
A29: A3 Histogram
A30: Bin Upper | B30: Frequency | C30: Normal PDF
A31: -0.3 | B31: {=FREQUENCY(Data!D4:D121, A31:A40)} -> 0 | C31: =_xlfn.NORM.DIST(A31-0.0025, Asset_Stats!$D$2, Asset_Stats!$D$4, FALSE) * 0.06 * 120 -> 0.0037524045
A32: =A31+0.06 -> -0.24 | B32: 1 | C32: =_xlfn.NORM.DIST(A32-0.0025, Asset_Stats!$D$2, Asset_Stats!$D$4, FALSE) * 0.06 * 120 -> 0.095703343
A33: =A32+0.06 -> -0.18 | B33: 1 | C33: =_xlfn.NORM.DIST(A33-0.0025, Asset_Stats!$D$2, Asset_Stats!$D$4, FALSE) * 0.06 * 120 -> 1.2201708
A34: =A33+0.06 -> -0.12 | B34: 1 | C34: =_xlfn.NORM.DIST(A34-0.0025, Asset_Stats!$D$2, Asset_Stats!$D$4, FALSE) * 0.06 * 120 -> 7.7766085
A35: =A34+0.06 -> -0.06 | B35: 13 | C35: =_xlfn.NORM.DIST(A35-0.0025, Asset_Stats!$D$2, Asset_Stats!$D$4, FALSE) * 0.06 * 120 -> 24.776269
A36: =A35+0.06 -> 0 | B36: 39 | C36: =_xlfn.NORM.DIST(A36-0.0025, Asset_Stats!$D$2, Asset_Stats!$D$4, FALSE) * 0.06 * 120 -> 39.460051
A37: =A36+0.06 -> 0.06 | B37: 37 | C37: =_xlfn.NORM.DIST(A37-0.0025, Asset_Stats!$D$2, Asset_Stats!$D$4, FALSE) * 0.06 * 120 -> 31.41633
A38: =A37+0.06 -> 0.12 | B38: 21 | C38: =_xlfn.NORM.DIST(A38-0.0025, Asset_Stats!$D$2, Asset_Stats!$D$4, FALSE) * 0.06 * 120 -> 12.503435
A39: =A38+0.06 -> 0.18 | B39: 4 | C39: =_xlfn.NORM.DIST(A39-0.0025, Asset_Stats!$D$2, Asset_Stats!$D$4, FALSE) * 0.06 * 120 -> 2.4875928
A40: =A39+0.06 -> 0.24 | B40: 1 | C40: =_xlfn.NORM.DIST(A40-0.0025, Asset_Stats!$D$2, Asset_Stats!$D$4, FALSE) * 0.06 * 120 -> 0.24740319
B41: 0
A44: A4 Histogram
A45: Bin Upper | B45: Frequency | C45: Normal PDF
A46: -0.03 | B46: {=FREQUENCY(Data!E4:E121, A46:A62)} -> 0 | C46: =_xlfn.NORM.DIST(A46-0.0025, Asset_Stats!$E$2, Asset_Stats!$E$4, FALSE) * 0.005 * 120 -> 0.6257434
A47: =A46+0.005 -> -0.025 | B47: 2 | C47: =_xlfn.NORM.DIST(A47-0.0025, Asset_Stats!$E$2, Asset_Stats!$E$4, FALSE) * 0.005 * 120 -> 1.46902
A48: =A47+0.005 -> -0.02 | B48: 2 | C48: =_xlfn.NORM.DIST(A48-0.0025, Asset_Stats!$E$2, Asset_Stats!$E$4, FALSE) * 0.005 * 120 -> 3.0369105
A49: =A48+0.005 -> -0.015 | B49: 5 | C49: =_xlfn.NORM.DIST(A49-0.0025, Asset_Stats!$E$2, Asset_Stats!$E$4, FALSE) * 0.005 * 120 -> 5.5285227
A50: =A49+0.005 -> -0.01 | B50: 13 | C50: =_xlfn.NORM.DIST(A50-0.0025, Asset_Stats!$E$2, Asset_Stats!$E$4, FALSE) * 0.005 * 120 -> 8.8625567
A51: =A50+0.005 -> -0.005 | B51: 15 | C51: =_xlfn.NORM.DIST(A51-0.0025, Asset_Stats!$E$2, Asset_Stats!$E$4, FALSE) * 0.005 * 120 -> 12.510705
A52: =A51+0.005 -> 0 | B52: 19 | C52: =_xlfn.NORM.DIST(A52-0.0025, Asset_Stats!$E$2, Asset_Stats!$E$4, FALSE) * 0.005 * 120 -> 15.551682
A53: =A52+0.005 -> 0.005 | B53: 10 | C53: =_xlfn.NORM.DIST(A53-0.0025, Asset_Stats!$E$2, Asset_Stats!$E$4, FALSE) * 0.005 * 120 -> 17.023379
A54: =A53+0.005 -> 0.01 | B54: 13 | C54: =_xlfn.NORM.DIST(A54-0.0025, Asset_Stats!$E$2, Asset_Stats!$E$4, FALSE) * 0.005 * 120 -> 16.409185
A55: =A54+0.005 -> 0.015 | B55: 14 | C55: =_xlfn.NORM.DIST(A55-0.0025, Asset_Stats!$E$2, Asset_Stats!$E$4, FALSE) * 0.005 * 120 -> 13.928395
A56: =A55+0.005 -> 0.02 | B56: 10 | C56: =_xlfn.NORM.DIST(A56-0.0025, Asset_Stats!$E$2, Asset_Stats!$E$4, FALSE) * 0.005 * 120 -> 10.410893
A57: =A56+0.005 -> 0.025 | B57: 7 | C57: =_xlfn.NORM.DIST(A57-0.0025, Asset_Stats!$E$2, Asset_Stats!$E$4, FALSE) * 0.005 * 120 -> 6.8524787
A58: =A57+0.005 -> 0.03 | B58: 3 | C58: =_xlfn.NORM.DIST(A58-0.0025, Asset_Stats!$E$2, Asset_Stats!$E$4, FALSE) * 0.005 * 120 -> 3.9717348
... A62: =A61+0.005 -> 0.05 | B62: 0 | C62: =_xlfn.NORM.DIST(A62-0.0025, Asset_Stats!$E$2, Asset_Stats!$E$4, FALSE) * 0.005 * 120 -> 0.12567205
B63: 0
A64: A5 Histogram
A65: Bin Upper | B65: Frequency | C65: Normal PDF
A66: -0.1 | B66: {=FREQUENCY(Data!F4:F121, A66:A75)} -> 0 | C66: =_xlfn.NORM.DIST(A66-0.0025, Asset_Stats!$F$2, Asset_Stats!$F$4, FALSE) * 0.02 * 120 -> 6.3230532e-05
A67: =A66+0.02 -> -0.08 | B67: 1 | C67: =_xlfn.NORM.DIST(A67-0.0025, Asset_Stats!$F$2, Asset_Stats!$F$4, FALSE) * 0.02 * 120 -> 0.0061449477
A68: =A67+0.02 -> -0.06 | B68: 0 | C68: =_xlfn.NORM.DIST(A68-0.0025, Asset_Stats!$F$2, Asset_Stats!$F$4, FALSE) * 0.02 * 120 -> 0.23250438
A69: =A68+0.02 -> -0.04 | B69: 4 | C69: =_xlfn.NORM.DIST(A69-0.0025, Asset_Stats!$F$2, Asset_Stats!$F$4, FALSE) * 0.02 * 120 -> 3.4250402
A70: =A69+0.02 -> -0.02 | B70: 5 | C70: =_xlfn.NORM.DIST(A70-0.0025, Asset_Stats!$F$2, Asset_Stats!$F$4, FALSE) * 0.02 * 120 -> 19.643632
A71: =A70+0.02 -> 0 | B71: 28 | C71: =_xlfn.NORM.DIST(A71-0.0025, Asset_Stats!$F$2, Asset_Stats!$F$4, FALSE) * 0.02 * 120 -> 43.863118
A72: =A71+0.02 -> 0.02 | B72: 63 | C72: =_xlfn.NORM.DIST(A72-0.0025, Asset_Stats!$F$2, Asset_Stats!$F$4, FALSE) * 0.02 * 120 -> 38.132809
A73: =A72+0.02 -> 0.04 | B73: 12 | C73: =_xlfn.NORM.DIST(A73-0.0025, Asset_Stats!$F$2, Asset_Stats!$F$4, FALSE) * 0.02 * 120 -> 12.906833
A74: =A73+0.02 -> 0.06 | B74: 3 | C74: =_xlfn.NORM.DIST(A74-0.0025, Asset_Stats!$F$2, Asset_Stats!$F$4, FALSE) * 0.02 * 120 -> 1.7008349
A75: =A74+0.02 -> 0.08 | B75: 2 | C75: =_xlfn.NORM.DIST(A75-0.0025, Asset_Stats!$F$2, Asset_Stats!$F$4, FALSE) * 0.02 * 120 -> 0.087262214
B76: 0

Sheet Validation_A1
A1: Date | B1: xAsset1 | C1: HY-GAGG | D1: US Muni | E1: US Tbill 1-3yr | F1: Global AGG | G1: EM Bond | H1: TIPs | I1: Gold | J1: RollPred
A2: =Data!A2 -> 38016 | B2: =Data!B2 - Factors!AB4 -> 0.005534337 | C2: =Factors!N4 - Factors!E4 -> 0.012420118 | D2: =Factors!B4 -> 0.0045136227 | E2: =Factors!C4 -> 0.0021072108 | F2: =Factors!E4 -> 0.0037328896 | G2: =Factors!L4 -> 0.0051267546 | H2: =Factors!M4 -> 0.012326082 | I2: =Factors!Z4 -> -0.031291371
A3: =Data!A3 -> 38044 | B3: =Data!B3 - Factors!AB5 -> 0.0076974457 | C3: =Factors!N5 - Factors!E5 -> -0.0062488062 | D3: =Factors!B5 -> 0.014482164 | E3: =Factors!C5 -> 0.0050261565 | F3: =Factors!E5 -> 0.0051522151 | G3: =Factors!L5 -> 0.0034824821 | H3: =Factors!M5 -> 0.024775375 | I3: =Factors!Z5 -> -0.015654119 | K3: SUMMARY OUTPUT
A4: =Data!A4 -> 38077 | B4: =Data!B4 - Factors!AB6 -> 0.00359195 | C4: =Factors!N6 - Factors!E6 -> -0.0044051421 | D4: =Factors!B6 -> -0.0047764906 | E4: =Factors!C6 -> 0.0032149418 | F4: =Factors!E6 -> 0.011076524 | G4: =Factors!L6 -> 0.024958811 | H4: =Factors!M6 -> 0.017390173 | I4: =Factors!Z6 -> 0.076486179
A5: =Data!A5 -> 38107 | B5: =Data!B5 - Factors!AB7 -> -0.018594571 | C5: =Factors!N7 - Factors!E7 -> 0.029962729 | D5: =Factors!B7 -> -0.020876864 | E5: =Factors!C7 -> -0.010071723 | F5: =Factors!E7 -> -0.036564036 | G5: =Factors!L7 -> -0.054311023 | H5: =Factors!M7 -> -0.046496063 | I5: =Factors!Z7 -> -0.093094149 | K5: Regression Statistics
A6: =Data!A6 -> 38138 | B6: =Data!B6 - Factors!AB8 -> -0.0029775632 | C6: =Factors!N8 - Factors!E8 -> -0.02061187 | D6: =Factors!B8 -> -0.0022641617 | E6: =Factors!C8 -> -0.0011304661 | F6: =Factors!E8 -> 0.0049003612 | G6: =Factors!L8 -> -0.014827674 | H6: =Factors!M8 -> 0.016443736 | I6: =Factors!Z8 -> 0.022753717 | K6: Multiple R | L6: 0.8350451
A7: =Data!A7 -> 38168 | B7: =Data!B7 - Factors!AB9 -> 0.0081784614 | C7: =Factors!N9 - Factors!E9 -> 0.011604847 | D7: =Factors!B9 -> 0.0033728521 | E7: =Factors!C9 -> -0.00010288595 | F7: =Factors!E9 -> 0.002922566 | G7: =Factors!L9 -> 0.014683749 | H7: =Factors!M9 -> -0.0026148152 | I7: =Factors!Z9 -> -0.003286563 | K7: R Square | L7: 0.69730032
A8: =Data!A8 -> 38198 | B8: =Data!B8 - Factors!AB10 -> 0.0079909892 | C8: =Factors!N10 - Factors!E10 -> 0.013683916 | D8: =Factors!B10 -> 0.011548622 | E8: =Factors!C10 -> 0.0036528271 | F8: =Factors!E10 -> -0.0002074828 | G8: =Factors!L10 -> 0.029702254 | H8: =Factors!M10 -> 0.016134553 | I8: =Factors!Z10 -> -0.0081166772 | K8: Adjusted R Square | L8: 0.67838159
A9: =Data!A9 -> 38230 | B9: =Data!B9 - Factors!AB11 -> 0.01432793 | C9: =Factors!N11 - Factors!E11 -> -0.0037153097 | D9: =Factors!B11 -> 0.01810155 | E9: =Factors!C11 -> 0.0071252819 | F9: =Factors!E11 -> 0.021887267 | G9: =Factors!L11 -> 0.041283114 | H9: =Factors!M11 -> 0.025976512 | I9: =Factors!Z11 -> 0.048075694 | K9: Standard Error | L9: 0.004354312
A10: =Data!A10 -> 38260 | B10: =Data!B10 - Factors!AB12 -> 0.00031251778 | C10: =Factors!N12 - Factors!E12 -> 0.0021144631 | D10: =Factors!B12 -> 0.0037546187 | E10: =Factors!C12 -> -0.0008143737 | F10: =Factors!E12 -> 0.01181709 | G10: =Factors!L12 -> 0.016634612 | H10: =Factors!M12 -> 0.0015744976 | I10: =Factors!Z12 -> 0.020495303 | K10: Observations | L10: 120
A11: =Data!A11 -> 38289 | B11: =Data!B11 - Factors!AB13 -> 0.006845742 | C11: =Factors!N13 - Factors!E13 -> -0.0046737517 | D11: =Factors!B13 -> 0.0067472552 | E11: =Factors!C13 -> 0.0031582701 | F11: =Factors!E13 -> 0.023953957 | G11: =Factors!L13 -> 0.016096913 | H11: =Factors!M13 -> 0.014200355 | I11: =Factors!Z13 -> 0.02462642
A12: =Data!A12 -> 38321 | B12: =Data!B12 - Factors!AB14 -> -0.0038796692 | C12: =Factors!N14 - Factors!E14 -> -0.016092938 | D12: =Factors!B14 -> -0.0086422779 | E12: =Factors!C14 -> -0.0051287259 | F12: =Factors!E14 -> 0.026496979 | G12: =Factors!L14 -> 0.0069900376 | H12: =Factors!M14 -> -0.0070595322 | I12: =Factors!Z14 -> 0.05226928 | K12: ANOVA
A13: =Data!A13 -> 38352 | B13: =Data!B13 - Factors!AB15 -> 0.0051129046 | C13: =Factors!N15 - Factors!E15 -> -0.00024049779 | D13: =Factors!B15 -> 0.0097161351 | E13: =Factors!C15 -> 0.0021437321 | F13: =Factors!E15 -> 0.015321934 | G13: =Factors!L15 -> 0.025041357 | H13: =Factors!M15 -> 0.013768153 | I13: =Factors!Z15 -> -0.027719259 | L13: df | M13: SS | N13: MS | O13: F | P13: Significance F
A14: =Data!A14 -> 38383 | B14: =Data!B14 - Factors!AB16 -> 0.0036364555 | C14: =Factors!N16 - Factors!E16 -> 0.0095053028 | D14: =Factors!B16 -> 0.0052499575 | E14: =Factors!C16 -> -0.00040745645 | F14: =Factors!E16 -> -0.010524264 | G14: =Factors!L16 -> 0.0062656245 | H14: =Factors!M16 -> 0.0054076539 | I14: =Factors!Z16 -> -0.036150074 | K14: Regression | L14: 7 | M14: 0.0048917586 | N14: 0.00069882265 | O14: 36.857671 | P14: 2.7273079e-26
A15: =Data!A15 -> 38411 | B15: =Data!B15 - Factors!AB17 -> -0.0062576928 | C15: =Factors!N17 - Factors!E17 -> 0.012380416 | D15: =Factors!B17 -> -0.0046337596 | E15: =Factors!C17 -> -0.0024457352 | F15: =Factors!E17 -> 0.0019035659 | G15: =Factors!L17 -> 0.0066668763 | H15: =Factors!M17 -> -0.0071714246 | I15: =Factors!Z17 -> 0.030880265 | K15: Residual | L15: 112 | M15: 0.0021235237 | N15: 1.8960033e-05
A16: =Data!A16 -> 38442 | B16: =Data!B16 - Factors!AB18 -> -0.0041361703 | C16: =Factors!N18 - Factors!E18 -> -0.015214777 | D16: =Factors!B18 -> -0.0070461486 | E16: =Factors!C18 -> -5.107774e-05 | F16: =Factors!E18 -> -0.012098137 | G16: =Factors!L18 -> -0.025459998 | H16: =Factors!M18 -> -0.0044377509 | I16: =Factors!Z18 -> -0.016756571 | K16: Total | L16: 119 | M16: 0.0070152822
A17: =Data!A17 -> 38471 | B17: =Data!B17 - Factors!AB19 -> 0.0088541607 | C17: =Factors!N19 - Factors!E19 -> -0.023814428 | D17: =Factors!B19 -> 0.014397938 | E17: =Factors!C19 -> 0.0058231598 | F17: =Factors!E19 -> 0.013086726 | G17: =Factors!L19 -> 0.015771253 | H17: =Factors!M19 -> 0.025283828 | I17: =Factors!Z19 -> 0.014100619
A18: =Data!A18 -> 38503 | B18: =Data!B18 - Factors!AB20 -> 0.0054878374 | C18: =Factors!N20 - Factors!E20 -> 0.031300321 | D18: =Factors!B20 -> 0.0050434595 | E18: =Factors!C20 -> 0.0038088467 | F18: =Factors!E20 -> -0.013397377 | G18: =Factors!L20 -> 0.029916688 | H18: =Factors!M20 -> 0.0069189282 | I18: =Factors!Z20 -> -0.03945763 | L18: Coefficients | M18: Standard Error | N18: t Stat | O18: P-value | P18: Lower 95% | Q18: Upper 95% | R18: Lower 95.0% | S18: Upper 95.0%
A19: =Data!A19 -> 38533 | B19: =Data!B19 - Factors!AB21 -> 0.0013617324 | C19: =Factors!N21 - Factors!E21 -> 0.023515645 | D19: =Factors!B21 -> 0.0053472183 | E19: =Factors!C21 -> 0.0018719012 | F19: =Factors!E21 -> -0.0044845893 | G19: =Factors!L21 -> 0.017771786 | H19: =Factors!M21 -> 0.0036562031 | I19: =Factors!Z21 -> 0.043738766 | K19: Intercept | L19: 0.00014878997 | M19: 0.00050931758 | N19: 0.29213594 | O19: 0.77072315 | P19: -0.00086035753 | Q19: 0.0011579375 | R19: -0.00086035753 | S19: 0.0011579375
A20: =Data!A20 -> 38562 | B20: =Data!B20 - Factors!AB22 -> -0.0074498679 | C20: =Factors!N22 - Factors!E22 -> 0.023707031 | D20: =Factors!B22 -> -0.0058462084 | E20: =Factors!C22 -> -0.0029793466 | F20: =Factors!E22 -> -0.0080068466 | G20: =Factors!L22 -> -0.0024686898 | H20: =Factors!M22 -> -0.018193158 | I20: =Factors!Z22 -> -0.013088404 | K20: HY-GAGG | L20: -0.092828826 | M20: 0.024534566 | N20: -3.7835936 | O20: 0.00024995833 | P20: -0.14144092 | Q20: -0.044216729 | R20: -0.14144092 | S20: -0.044216729
A21: =Data!A21 -> 38595 | B21: =Data!B21 - Factors!AB23 -> 0.0060719039 | C21: =Factors!N23 - Factors!E23 -> -0.012839365 | D21: =Factors!B23 -> 0.0088760151 | E21: =Factors!C23 -> 0.006280389 | F21: =Factors!E23 -> 0.016459134 | G21: =Factors!L23 -> 0.019406048 | H21: =Factors!M23 -> 0.024976539 | I21: =Factors!Z23 -> 0.012563983 | K21: US Muni | L21: 0.12690855 | M21: 0.048911177 | N21: 2.5946739 | O21: 0.010734358 | P21: 0.029997324 | Q21: 0.22381978 | R21: 0.029997324 | S21: 0.22381978
A22: =Data!A22 -> 38625 | B22: =Data!B22 - Factors!AB24 -> -0.0082182653 | C22: =Factors!N24 - Factors!E24 -> 0.0059054787 | D22: =Factors!B24 -> -0.0053323723 | E22: =Factors!C24 -> -0.0026676062 | F22: =Factors!E24 -> -0.015920275 | G22: =Factors!L24 -> 0.016904995 | H22: =Factors!M24 -> -0.0052538911 | I22: =Factors!Z24 -> 0.078354779 | K22: US Tbill 1-3yr | L22: 0.48595859 | M22: 0.14644118 | N22: 3.3184559 | O22: 0.0012215802 | P22: 0.19580417 | Q22: 0.77611301 | R22: 0.19580417 | S22: 0.77611301
A23: =Data!A23 -> 38656 | B23: =Data!B23 - Factors!AB25 -> -0.0096210421 | C23: =Factors!N25 - Factors!E25 -> 0.0075918327 | D23: =Factors!B25 -> -0.005316902 | E23: =Factors!C25 -> -0.00020186727 | F23: =Factors!E25 -> -0.014886017 | G23: =Factors!L25 -> -0.014789799 | H23: =Factors!M25 -> -0.012573985 | I23: =Factors!Z25 -> -0.0087577243 | K23: Global AGG | L23: -0.076394898 | M23: 0.043089834 | N23: -1.7729216 | O23: 0.078960172 | P23: -0.16177188 | Q23: 0.0089820848 | R23: -0.16177188 | S23: 0.0089820848
A24: =Data!A24 -> 38686 | B24: =Data!B24 - Factors!AB26 -> 0.00019473398 | C24: =Factors!N26 - Factors!E26 -> 0.011922581 | D24: =Factors!B26 -> 0.004390689 | E24: =Factors!C26 -> 0.0032810055 | F24: =Factors!E26 -> -0.0070979041 | G24: =Factors!L26 -> 0.015277778 | H24: =Factors!M26 -> 0.0019717785 | I24: =Factors!Z26 -> 0.059953997 | K24: EM Bond | L24: 0.15283301 | M24: 0.032833378 | N24: 4.6548063 | O24: 8.9622061e-06 | P24: 0.087777884 | Q24: 0.21788814 | R24: 0.087777884 | S24: 0.21788814
A25: =Data!A25 -> 38716 | B25: =Data!B25 - Factors!AB27 -> 0.0065581799 | C25: =Factors!N27 - Factors!E27 -> -0.00071723125 | D25: =Factors!B27 -> 0.0068721605 | E25: =Factors!C27 -> 0.0038740189 | F25: =Factors!E27 -> 0.0098715137 | G25: =Factors!L27 -> 0.018482405 | H25: =Factors!M27 -> 0.0084798523 | I25: =Factors!Z27 -> 0.048511398 | K25: TIPs | L25: 0.10232754 | M25: 0.031273573 | N25: 3.272013 | O25: 0.00142002 | P25: 0.040362962 | Q25: 0.16429211 | R25: 0.040362962 | S25: 0.16429211
A26: =Data!A26 -> 38748 | B26: =Data!B26 - Factors!AB28 -> 4.4318948e-06 | C26: =Factors!N28 - Factors!E28 -> 0.0032352419 | D26: =Factors!B28 -> 0.0028999352 | E26: =Factors!C28 -> 0.0015035333 | F26: =Factors!E28 -> 0.012614298 | G26: =Factors!L28 -> 0.011974166 | H26: =Factors!M28 -> 0.00078054042 | I26: =Factors!Z28 -> 0.10038685 | K26: Gold | L26: -0.0056226851 | M26: 0.0086418469 | N26: -0.65063466 | O26: 0.51661488 | P26: -0.022745397 | Q26: 0.011500027 | R26: -0.022745397 | S26: 0.011500027
A27: =Data!A27 -> 38776 | B27: =Data!B27 - Factors!AB29 -> 0.0014557254 | C27: =Factors!N29 - Factors!E29 -> 0.0098689223 | D27: =Factors!B29 -> 0.0040444707 | E27: =Factors!C29 -> 0.00075063804 | F27: =Factors!E29 -> -0.0035465658 | G27: =Factors!L29 -> 0.022224732 | H27: =Factors!M29 -> -0.0034033381 | I27: =Factors!Z29 -> -0.01291967
A28: =Data!A28 -> 38807 | B28: =Data!B28 - Factors!AB30 -> -0.012312888 | C28: =Factors!N30 - Factors!E30 -> 0.016163657 | D28: =Factors!B30 -> -0.0063508292 | E28: =Factors!C30 -> 0.00120012 | F28: =Factors!E30 -> -0.0099131724 | G28: =Factors!L30 -> -0.018978949 | H28: =Factors!M30 -> -0.020532449 | I28: =Factors!Z30 -> 0.039355356
A29: =Data!A29 -> 38835 | B29: =Data!B29 - Factors!AB31 -> -0.0037051408 | C29: =Factors!N31 - Factors!E31 -> -0.012502969 | D29: =Factors!B31 -> 1.3389487e-05 | E29: =Factors!C31 -> 0.0030965937 | F29: =Factors!E31 -> 0.018928887 | G29: =Factors!L31 -> -0.00084480865 | H29: =Factors!M31 -> 0.00010169098 | I29: =Factors!Z31 -> 0.12125418
A30: =Data!A30 -> 38868 | B30: =Data!B30 - Factors!AB32 -> -0.005874578 | C30: =Factors!N32 - Factors!E32 -> -0.013529189 | D30: =Factors!B32 -> 0.004853624 | E30: =Factors!C32 -> 0.0014439355 | F30: =Factors!E32 -> 0.012897983 | G30: =Factors!L32 -> -0.02048984 | H30: =Factors!M32 -> 0.0021352933 | I30: =Factors!Z32 -> -0.014088811
A31: =Data!A31 -> 38898 | B31: =Data!B31 - Factors!AB33 -> -0.002027934 | C31: =Factors!N33 - Factors!E33 -> 0.0041536738 | D31: =Factors!B33 -> -0.0036248131 | E31: =Factors!C33 -> 0.0017898871 | F31: =Factors!E33 -> -0.0079451696 | G31: =Factors!L33 -> -5.7547333e-05 | H31: =Factors!M33 -> 0.0035947239 | I31: =Factors!Z33 -> -0.045489771
A32: =Data!A32 -> 38929 | B32: =Data!B32 - Factors!AB34 -> 0.010264381 | C32: =Factors!N34 - Factors!E34 -> 0.00070743003 | D32: =Factors!B34 -> 0.010644481 | E32: =Factors!C34 -> 0.0074941684 | F32: =Factors!E34 -> 0.0099619177 | G32: =Factors!L34 -> 0.032717541 | H32: =Factors!M34 -> 0.016696034 | I32: =Factors!Z34 -> 0.033936835
A33: =Data!A33 -> 38960 | B33: =Data!B33 - Factors!AB35 -> 0.010262188 | C33: =Factors!N35 - Factors!E35 -> 0.0046252147 | D33: =Factors!B35 -> 0.013140651 | E33: =Factors!C35 -> 0.0071428571 | F33: =Factors!E35 -> 0.011555066 | G33: =Factors!L35 -> 0.026024687 | H33: =Factors!M35 -> 0.018765804 | I33: =Factors!Z35 -> -0.014840989
A34: =Data!A34 -> 38989 | B34: =Data!B34 - Factors!AB36 -> 0.0026278673 | C34: =Factors!N36 - Factors!E36 -> 0.013228492 | D34: =Factors!B36 -> 0.0063670591 | E34: =Factors!C36 -> 0.00513573 | F34: =Factors!E36 -> -7.4683066e-05 | G34: =Factors!L36 -> 0.0055943296 | H34: =Factors!M36 -> 0.0025169072 | I34: =Factors!Z36 -> -0.046229874
A35: =Data!A35 -> 39021 | B35: =Data!B35 - Factors!AB37 -> 0.0033539067 | C35: =Factors!N37 - Factors!E37 -> 0.0049282704 | D35: =Factors!B37 -> 0.0049471146 | E35: =Factors!C37 -> 0.0038442822 | F35: =Factors!E37 -> 0.0096735856 | G35: =Factors!L37 -> 0.018553026 | H35: =Factors!M37 -> -0.0015995438 | I35: =Factors!Z37 -> 0.013872639
A36: =Data!A36 -> 39051 | B36: =Data!B36 - Factors!AB38 -> 0.0073057981 | C36: =Factors!N38 - Factors!E38 -> -0.0083921078 | D36: =Factors!B38 -> 0.0063279162 | E36: =Factors!C38 -> 0.0051383974 | F36: =Factors!E38 -> 0.024354469 | G36: =Factors!L38 -> 0.012673666 | H36: =Factors!M38 -> 0.012412842 | I36: =Factors!Z38 -> 0.068249258
A37: =Data!A37 -> 39080 | B37: =Data!B37 - Factors!AB39 -> -0.0070648521 | C37: =Factors!N39 - Factors!E39 -> 0.024265253 | D37: =Factors!B39 -> -0.0028721038 | E37: =Factors!C39 -> 4.8227634e-05 | F37: =Factors!E39 -> -0.013256313 | G37: =Factors!L39 -> 0.0066502592 | H37: =Factors!M39 -> -0.024954762 | I37: =Factors!Z39 -> -0.017438272
A38: =Data!A38 -> 39113 | B38: =Data!B38 - Factors!AB40 -> -0.0034834649 | C38: =Factors!N40 - Factors!E40 -> 0.020572221 | D38: =Factors!B40 -> -0.002430921 | E38: =Factors!C40 -> 0.0020736883 | F38: =Factors!E40 -> -0.0098284605 | G38: =Factors!L40 -> -0.0030430712 | H38: =Factors!M40 -> 0.0023074318 | I38: =Factors!Z40 -> 0.025914874 | J38: {=TREND(B2:B37, C2:I37, C38:I38, TRUE)} -> -0.0025678599
A39: =Data!A39 -> 39141 | B39: =Data!B39 - Factors!AB41 -> 0.0085567023 | C39: =Factors!N41 - Factors!E41 -> -0.0066493112 | D39: =Factors!B41 -> 0.011358545 | E39: =Factors!C41 -> 0.0080850859 | F39: =Factors!E41 -> 0.020578466 | G39: =Factors!L41 -> 0.017166262 | H39: =Factors!M41 -> 0.022753673 | I39: =Factors!Z41 -> 0.024724434 | J39: {=TREND(B3:B38, C3:I38, C39:I39, TRUE)} -> 0.0088591439
A40: =Data!A40 -> 39171 | B40: =Data!B40 - Factors!AB42 -> -0.0018456249 | C40: =Factors!N42 - Factors!E42 -> -4.1273382e-05 | D40: =Factors!B42 -> -0.00046020954 | E40: =Factors!C42 -> 0.0038669022 | F40: =Factors!E42 -> 0.0023638205 | G40: =Factors!L42 -> 0.0097463387 | H40: =Factors!M42 -> 0.0030425056 | I40: =Factors!Z42 -> -0.0083065661 | J40: {=TREND(B4:B39, C4:I39, C40:I40, TRUE)} -> 0.0011536081
A41: =Data!A41 -> 39202 | B41: =Data!B41 - Factors!AB43 -> 0.00063767963 | C41: =Factors!N43 - Factors!E43 -> 0.0019300531 | D41: =Factors!B43 -> 0.0024974672 | E41: =Factors!C43 -> 0.0035191174 | F41: =Factors!E43 -> 0.011302713 | G41: =Factors!L43 -> 0.0086616373 | H41: =Factors!M43 -> 0.0078096584 | I41: =Factors!Z43 -> 0.022085298 | J41: {=TREND(B5:B40, C5:I40, C41:I41, TRUE)} -> 0.0017732287
A42: =Data!A42 -> 39233 | B42: =Data!B42 - Factors!AB44 -> -0.0099683011 | C42: =Factors!N44 - Factors!E44 -> 0.022707655 | D42: =Factors!B44 -> -0.0035767586 | E42: =Factors!C44 -> -0.00099516633 | F42: =Factors!E44 -> -0.01559266 | G42: =Factors!L44 -> -0.0038529338 | H42: =Factors!M44 -> -0.016758027 | I42: =Factors!Z44 -> -0.026457366 | J42: {=TREND(B6:B41, C6:I41, C42:I42, TRUE)} -> -0.0067096363
A43: =Data!A43 -> 39262 | B43: =Data!B43 - Factors!AB45 -> -0.0081880157 | C43: =Factors!N45 - Factors!E45 -> -0.01241912 | D43: =Factors!B45 -> -0.0029891202 | E43: =Factors!C45 -> 0.0043641193 | F43: =Factors!E45 -> -0.0044349056 | G43: =Factors!L45 -> -0.018884142 | H43: =Factors!M45 -> -0.0023823705 | I43: =Factors!Z45 -> -0.016426949 | J43: {=TREND(B7:B42, C7:I42, C43:I43, TRUE)} -> -0.0056100536
A44: =Data!A44 -> 39294 | B44: =Data!B44 - Factors!AB46 -> 0.0029644939 | C44: =Factors!N46 - Factors!E46 -> -0.051708624 | D44: =Factors!B46 -> 0.0080686498 | E44: =Factors!C46 -> 0.0089264629 | F44: =Factors!E46 -> 0.020308133 | G44: =Factors!L46 -> -0.0090182943 | H44: =Factors!M46 -> 0.023700104 | I44: =Factors!Z46 -> 0.022550604 | J44: {=TREND(B8:B43, C8:I43, C44:I44, TRUE)} -> 0.0045006955
A45: =Data!A45 -> 39325 | B45: =Data!B45 - Factors!AB47 -> 0.0068386208 | C45: =Factors!N47 - Factors!E47 -> -0.0011662912 | D45: =Factors!B47 -> 0.0027516275 | E45: =Factors!C47 -> 0.010392285 | F45: =Factors!E47 -> 0.012312678 | G45: =Factors!L47 -> 0.012116485 | H45: =Factors!M47 -> 0.01334563 | I45: =Factors!Z47 -> 0.013548096 | J45: {=TREND(B9:B44, C9:I44, C45:I45, TRUE)} -> 0.0043428547
A46: =Data!A46 -> 39353 | B46: =Data!B46 - Factors!AB48 -> 0.0041751696 | C46: =Factors!N48 - Factors!E48 -> 0.0019959885 | D46: =Factors!B48 -> 0.011351253 | E46: =Factors!C48 -> 0.0069495923 | F46: =Factors!E48 -> 0.022443581 | G46: =Factors!L48 -> 0.022709757 | H46: =Factors!M48 -> 0.0088736014 | I46: =Factors!Z48 -> 0.10441111 | J46: {=TREND(B10:B45, C10:I45, C46:I46, TRUE)} -> 0.006080066
A47: =Data!A47 -> 39386 | B47: =Data!B47 - Factors!AB49 -> 0.0070930246 | C47: =Factors!N49 - Factors!E49 -> -0.010244815 | D47: =Factors!B49 -> 0.0040896828 | E47: =Factors!C49 -> 0.003910923 | F47: =Factors!E49 -> 0.016299287 | G47: =Factors!L49 -> 0.023838232 | H47: =Factors!M49 -> 0.013770414 | I47: =Factors!Z49 -> 0.071543841 | J47: {=TREND(B11:B46, C11:I46, C47:I47, TRUE)} -> 0.0048492379
A48: =Data!A48 -> 39416 | B48: =Data!B48 - Factors!AB50 -> 0.013575159 | C48: =Factors!N50 - Factors!E50 -> -0.039574175 | D48: =Factors!B50 -> 0.0091649074 | E48: =Factors!C50 -> 0.01732435 | F48: =Factors!E50 -> 0.019110525 | G48: =Factors!L50 -> -0.0037047033 | H48: =Factors!M50 -> 0.046900559 | I48: =Factors!Z50 -> -0.016629016 | J48: {=TREND(B12:B47, C12:I47, C48:I48, TRUE)} -> 0.012615331
A49: =Data!A49 -> 39447 | B49: =Data!B49 - Factors!AB51 -> 5.9352799e-05 | C49: =Factors!N51 - Factors!E51 -> 0.0059131074 | D49: =Factors!B51 -> 0.0040355597 | E49: =Factors!C51 -> 0.0024778123 | F49: =Factors!E51 -> -0.002981283 | G49: =Factors!L51 -> 0.0062302994 | H49: =Factors!M51 -> -0.0046936913 | I49: =Factors!Z51 -> 0.064003573 | J49: {=TREND(B13:B48, C13:I48, C49:I49, TRUE)} -> -0.002544609
... A121: =Data!A121 -> 41639 | B121: =Data!B121 - Factors!AB123 -> -0.0047703471 | C121: =Factors!N123 - Factors!E123 -> 0.01145068 | D121: =Factors!B123 -> -0.0015690491 | E121: =Factors!C123 -> -0.0013934785 | F121: =Factors!E123 -> -0.005970907 | G121: =Factors!L123 -> 0.0058312774 | H121: =Factors!M123 -> -0.020891371 | I121: =Factors!Z123 -> -0.04125743 | J121: {=TREND(B85:B120, C85:I120, C121:I121, TRUE)} -> -0.0028953842

Sheet A1
A1: Date | B1: xAsset1 | C1: US AGG | D1: EM Bond | E1: Credit Spread | G1: Predicted | H1: Residual | I1: Resid_ex0809 | J1: xAsset_ex0809 | L1: Factor | M1: R^2 aux | N1: VIF
A2: =Data!A2 -> 38016 | B2: =Data!B2 - Factors!AB4 -> 0.005534337 | C2: =Factors!D4 -> 0.0080453023 | D2: =Factors!L4 -> 0.0051267546 | E2: =Factors!N4 - Factors!D4 -> 0.0081077053 | L2: US AGG | M2: =INDEX(LINEST(C2:C121, D2:E121, TRUE, TRUE), 3, 1) -> 0.69636819 | N2: =1/(1-M2) -> 3.2934626
A3: =Data!A3 -> 38044 | B3: =Data!B3 - Factors!AB5 -> 0.0076974457 | C3: =Factors!D5 -> 0.010824142 | D3: =Factors!L5 -> 0.0034824821 | E3: =Factors!N5 - Factors!D5 -> -0.011920733 | L3: EM Bond | M3: =INDEX(LINEST(D2:D121, CHOOSE({1,2}, C2:C121, E2:E121), TRUE, TRUE), 3, 1) -> 0.79122174 | N3: =1/(1-M3) -> 4.7897707
A4: =Data!A4 -> 38077 | B4: =Data!B4 - Factors!AB6 -> 0.00359195 | C4: =Factors!D6 -> 0.0074889868 | D4: =Factors!L6 -> 0.024958811 | E4: =Factors!N6 - Factors!D6 -> -0.00081760495 | L4: Credit Spread | M4: =INDEX(LINEST(E2:E121, C2:D121, TRUE, TRUE), 3, 1) -> 0.6418213 | N4: =1/(1-M4) -> 2.7919025
A5: =Data!A5 -> 38107 | B5: =Data!B5 - Factors!AB7 -> -0.018594571 | C5: =Factors!D7 -> -0.026016616 | D5: =Factors!L7 -> -0.054311023 | E5: =Factors!N7 - Factors!D7 -> 0.019415308 | G5: SUMMARY OUTPUT | Q5: SUMMARY OUTPUT
A6: =Data!A6 -> 38138 | B6: =Data!B6 - Factors!AB8 -> -0.0029775632 | C6: =Factors!D8 -> -0.0040058707 | D6: =Factors!L8 -> -0.014827674 | E6: =Factors!N8 - Factors!D8 -> -0.011705638
A7: =Data!A7 -> 38168 | B7: =Data!B7 - Factors!AB9 -> 0.0081784614 | C7: =Factors!D9 -> 0.0056515785 | D7: =Factors!L9 -> 0.014683749 | E7: =Factors!N9 - Factors!D9 -> 0.0088758343 | G7: Regression Statistics | Q7: Regression Statistics
A8: =Data!A8 -> 38198 | B8: =Data!B8 - Factors!AB10 -> 0.0079909892 | C8: =Factors!D10 -> 0.009912255 | D8: =Factors!L10 -> 0.029702254 | E8: =Factors!N10 - Factors!D10 -> 0.0035641781 | G8: Multiple R | H8: 0.90414707 | N8: corr(US AGG, US Tbill) = 0.6011 | Q8: Multiple R | R8: 0.90414418
A9: =Data!A9 -> 38230 | B9: =Data!B9 - Factors!AB11 -> 0.01432793 | C9: =Factors!D11 -> 0.019075174 | D9: =Factors!L11 -> 0.041283114 | E9: =Factors!N11 - Factors!D11 -> -0.00090321685 | G9: R Square | H9: 0.81748192 | Q9: R Square | R9: 0.8174767
A10: =Data!A10 -> 38260 | B10: =Data!B10 - Factors!AB12 -> 0.00031251778 | C10: =Factors!D12 -> 0.0027134997 | D10: =Factors!L12 -> 0.016634612 | E10: =Factors!N12 - Factors!D12 -> 0.011218053 | G10: Adjusted R Square | H10: 0.81113346 | Q10: Adjusted R Square | R10: 0.81275627
A11: =Data!A11 -> 38289 | B11: =Data!B11 - Factors!AB13 -> 0.006845742 | C11: =Factors!D13 -> 0.0083857442 | D11: =Factors!L13 -> 0.016096913 | E11: =Factors!N13 - Factors!D13 -> 0.010894461 | G11: Standard Error | H11: 0.0033367725 | Q11: Standard Error | R11: 0.0033224063
A12: =Data!A12 -> 38321 | B12: =Data!B12 - Factors!AB14 -> -0.0038796692 | C12: =Factors!D14 -> -0.0079764104 | D12: =Factors!L14 -> 0.0069900376 | E12: =Factors!N14 - Factors!D14 -> 0.018380451 | G12: Observations | H12: 120 | Q12: Observations | R12: 120
A13: =Data!A13 -> 38352 | B13: =Data!B13 - Factors!AB15 -> 0.0051129046 | C13: =Factors!D15 -> 0.0092011222 | D13: =Factors!L15 -> 0.025041357 | E13: =Factors!N15 - Factors!D15 -> 0.0058803136
A14: =Data!A14 -> 38383 | B14: =Data!B14 - Factors!AB16 -> 0.0036364555 | C14: =Factors!D16 -> 0.0062794738 | D14: =Factors!L16 -> 0.0062656245 | E14: =Factors!N16 - Factors!D16 -> -0.0072984348 | G14: ANOVA | O14: drop tbill | Q14: ANOVA
A15: =Data!A15 -> 38411 | B15: =Data!B15 - Factors!AB17 -> -0.0062576928 | C15: =Factors!D17 -> -0.0059031974 | D15: =Factors!L17 -> 0.0066668763 | E15: =Factors!N17 - Factors!D17 -> 0.020187179 | H15: df | I15: SS | J15: MS | K15: F | L15: Significance F | R15: df | S15: SS | T15: MS | U15: F | V15: Significance F
A16: =Data!A16 -> 38442 | B16: =Data!B16 - Factors!AB18 -> -0.0041361703 | C16: =Factors!D18 -> -0.0051360091 | D16: =Factors!L18 -> -0.025459998 | E16: =Factors!N18 - Factors!D18 -> -0.022176904 | G16: Regression | H16: 4 | I16: 0.0057348664 | J16: 0.0014337166 | K16: 128.76864 | L16: 1.6083377e-41 | Q16: Regression | R16: 3 | S16: 0.0057348298 | T16: 0.0019116099 | U16: 173.17843 | V16: 1.12326e-42
A17: =Data!A17 -> 38471 | B17: =Data!B17 - Factors!AB19 -> 0.0088541607 | C17: =Factors!D19 -> 0.01353396 | D17: =Factors!L19 -> 0.015771253 | E17: =Factors!N19 - Factors!D19 -> -0.024261662 | G17: Residual | H17: 115 | I17: 0.0012804158 | J17: 1.1134051e-05 | Q17: Residual | R17: 116 | S17: 0.0012804525 | T17: 1.1038383e-05
A18: =Data!A18 -> 38503 | B18: =Data!B18 - Factors!AB20 -> 0.0054878374 | C18: =Factors!D20 -> 0.010818747 | D18: =Factors!L20 -> 0.029916688 | E18: =Factors!N20 - Factors!D20 -> 0.0070841965 | G18: Total | H18: 119 | I18: 0.0070152822 | Q18: Total | R18: 119 | S18: 0.0070152822
A19: =Data!A19 -> 38533 | B19: =Data!B19 - Factors!AB21 -> 0.0013617324 | C19: =Factors!D21 -> 0.0054529078 | D19: =Factors!L21 -> 0.017771786 | E19: =Factors!N21 - Factors!D21 -> 0.013578147
A20: =Data!A20 -> 38562 | B20: =Data!B20 - Factors!AB22 -> -0.0074498679 | C20: =Factors!D22 -> -0.0090953845 | D20: =Factors!L22 -> -0.0024686898 | E20: =Factors!N22 - Factors!D22 -> 0.024795569 | H20: Coefficients | I20: Standard Error | J20: t Stat | K20: P-value | L20: Lower 95% | M20: Upper 95% | N20: Lower 95.0% | O20: Upper 95.0% | R20: Coefficients | S20: Standard Error | T20: t Stat | U20: P-value | V20: Lower 95% | W20: Upper 95% | X20: Lower 95.0% | Y20: Upper 95.0%
A21: =Data!A21 -> 38595 | B21: =Data!B21 - Factors!AB23 -> 0.0060719039 | C21: =Factors!D23 -> 0.012811324 | D21: =Factors!L23 -> 0.019406048 | E21: =Factors!N23 - Factors!D23 -> -0.0091915546 | G21: Intercept | H21: 0.0001073372 | I21: 0.00037015553 | J21: 0.28997864 | K21: 0.77235479 | L21: -0.00062586966 | M21: 0.00084054406 | N21: -0.00062586966 | O21: 0.00084054406 | Q21: Intercept | R21: 0.00011659258 | S21: 0.00033168542 | T21: 0.35151554 | U21: 0.72583931 | V21: -0.00054035218 | W21: 0.00077353734 | X21: -0.00054035218 | Y21: 0.00077353734
A22: =Data!A22 -> 38625 | B22: =Data!B22 - Factors!AB24 -> -0.0082182653 | C22: =Factors!D24 -> -0.010301154 | D22: =Factors!L24 -> 0.016904995 | E22: =Factors!N24 - Factors!D24 -> 0.00028635718 | G22: US AGG | H22: 0.59268256 | I22: 0.06612289 | J22: 8.9633493 | K22: 6.7272228e-15 | L22: 0.46170584 | M22: 0.72365928 | N22: 0.46170584 | O22: 0.72365928 | Q22: US AGG | R22: 0.59460301 | S22: 0.056770538 | T22: 10.473796 | U22: 1.800181e-18 | V22: 0.48216181 | W22: 0.70704422 | X22: 0.48216181 | Y22: 0.70704422
A23: =Data!A23 -> 38656 | B23: =Data!B23 - Factors!AB25 -> -0.0096210421 | C23: =Factors!D25 -> -0.007913938 | D23: =Factors!L25 -> -0.014789799 | E23: =Factors!N25 - Factors!D25 -> 0.00061975345 | G23: US Tbill 1-3yr | H23: 0.0065937106 | I23: 0.11497663 | J23: 0.057348268 | K23: 0.9543673 | L23: -0.22115287 | M23: 0.23434029 | N23: -0.22115287 | O23: 0.23434029 | Q23: EM Bond | R23: 0.052414433 | S23: 0.025722588 | T23: 2.0376812 | U23: 0.043856833 | V23: 0.0014676064 | W23: 0.10336126 | X23: 0.0014676064 | Y23: 0.10336126
A24: =Data!A24 -> 38686 | B24: =Data!B24 - Factors!AB26 -> 0.00019473398 | C24: =Factors!D26 -> 0.0044226044 | D24: =Factors!L26 -> 0.015277778 | E24: =Factors!N26 - Factors!D26 -> 0.0004020722 | G24: EM Bond | H24: 0.05259625 | I24: 0.026027627 | J24: 2.0207854 | K24: 0.04562502 | L24: 0.0010405298 | M24: 0.10415197 | N24: 0.0010405298 | O24: 0.10415197 | Q24: Credit Spread | R24: -0.069793958 | S24: 0.017599311 | T24: -3.965721 | U24: 0.00012701342 | V24: -0.10465161 | W24: -0.034936304 | X24: -0.10465161 | Y24: -0.034936304
A25: =Data!A25 -> 38716 | B25: =Data!B25 - Factors!AB27 -> 0.0065581799 | C25: =Factors!D27 -> 0.0095075016 | D25: =Factors!L27 -> 0.018482405 | E25: =Factors!N27 - Factors!D27 -> -0.00035321919 | G25: Credit Spread | H25: -0.069456336 | I25: 0.018630066 | J25: -3.7281852 | K25: 0.00030084912 | L25: -0.10635891 | M25: -0.032553761 | N25: -0.10635891 | O25: -0.032553761
A26: =Data!A26 -> 38748 | B26: =Data!B26 - Factors!AB28 -> 4.4318948e-06 | C26: =Factors!D28 -> 5.6540071e-05 | D26: =Factors!L28 -> 0.011974166 | E26: =Factors!N28 - Factors!D28 -> 0.015793
A27: =Data!A27 -> 38776 | B27: =Data!B27 - Factors!AB29 -> 0.0014557254 | C27: =Factors!D29 -> 0.0033195222 | D27: =Factors!L29 -> 0.022224732 | E27: =Factors!N29 - Factors!D29 -> 0.0030028343
A28: =Data!A28 -> 38807 | B28: =Data!B28 - Factors!AB30 -> -0.012312888 | C28: =Factors!D30 -> -0.0098129186 | D28: =Factors!L30 -> -0.018978949 | E28: =Factors!N30 - Factors!D30 -> 0.016063403
A29: =Data!A29 -> 38835 | B29: =Data!B29 - Factors!AB31 -> -0.0037051408 | C29: =Factors!D31 -> -0.0018129344 | D29: =Factors!L31 -> -0.00084480865 | E29: =Factors!N31 - Factors!D31 -> 0.0082388531
A30: =Data!A30 -> 38868 | B30: =Data!B30 - Factors!AB32 -> -0.005874578 | C30: =Factors!D32 -> -0.0010669316 | D30: =Factors!L32 -> -0.02048984 | E30: =Factors!N32 - Factors!D32 -> 0.00043572579 | H30: OOS R Square | I30: =1 - SUMSQ(H38:H121) / DEVSQ(B38:B121) -> 0.66655024
A31: =Data!A31 -> 38898 | B31: =Data!B31 - Factors!AB33 -> -0.002027934 | C31: =Factors!D33 -> 0.002119836 | D31: =Factors!L33 -> -5.7547333e-05 | E31: =Factors!N33 - Factors!D33 -> -0.0059113317 | H31: OOS RMSE | I31: =SQRT( SUMSQ(H38:H121) / COUNT(H38:H121) ) -> 0.0044717093
A32: =Data!A32 -> 38929 | B32: =Data!B32 - Factors!AB34 -> 0.010264381 | C32: =Factors!D34 -> 0.013521979 | D32: =Factors!L34 -> 0.032717541 | E32: =Factors!N34 - Factors!D34 -> -0.0028526316 | H32: ex0809 OOS R^2 | I32: =1 - SUMSQ(I38:I121) / DEVSQ(J38:J121) -> 0.79957027
A33: =Data!A33 -> 38960 | B33: =Data!B33 - Factors!AB35 -> 0.010262188 | C33: =Factors!D35 -> 0.015308293 | D33: =Factors!L35 -> 0.026024687 | E33: =Factors!N35 - Factors!D35 -> 0.00087198764
A34: =Data!A34 -> 38989 | B34: =Data!B34 - Factors!AB36 -> 0.0026278673 | C34: =Factors!D36 -> 0.0087839975 | D34: =Factors!L36 -> 0.0055943296 | E34: =Factors!N36 - Factors!D36 -> 0.0043698119
A35: =Data!A35 -> 39021 | B35: =Data!B35 - Factors!AB37 -> 0.0033539067 | C35: =Factors!D37 -> 0.0066148866 | D35: =Factors!L37 -> 0.018553026 | E35: =Factors!N37 - Factors!D37 -> 0.0079869694
A36: =Data!A36 -> 39051 | B36: =Data!B36 - Factors!AB38 -> 0.0073057981 | C36: =Factors!D38 -> 0.011601199 | D36: =Factors!L38 -> 0.012673666 | E36: =Factors!N38 - Factors!D38 -> 0.0043611622
A37: =Data!A37 -> 39080 | B37: =Data!B37 - Factors!AB39 -> -0.0070648521 | C37: =Factors!D39 -> -0.0058033481 | D37: =Factors!L39 -> 0.0066502592 | E37: =Factors!N39 - Factors!D39 -> 0.016812288 | G37: 36 Month Rolling
A38: =Data!A38 -> 39113 | B38: =Data!B38 - Factors!AB40 -> -0.0034834649 | C38: =Factors!D40 -> -0.00041030882 | D38: =Factors!L40 -> -0.0030430712 | E38: =Factors!N40 - Factors!D40 -> 0.011154069 | G38: {=TREND(B2:B37, C2:E37, C38:E38, TRUE)} -> -0.0019193824 | H38: =B38 - G38 -> -0.0015640826 | I38: =IF(OR(YEAR(A38)=2008, YEAR(A38)=2009), "", H38) -> -0.0015640826 | J38: =IF(OR(YEAR(A38)=2008, YEAR(A38)=2009), "", B38) -> -0.0034834649
A39: =Data!A39 -> 39141 | B39: =Data!B39 - Factors!AB41 -> 0.0085567023 | C39: =Factors!D41 -> 0.015420003 | D39: =Factors!L41 -> 0.017166262 | E39: =Factors!N41 - Factors!D41 -> -0.0014908489 | G39: {=TREND(B3:B38, C3:E38, C39:E39, TRUE)} -> 0.0095668898 | H39: =B39 - G39 -> -0.0010101875 | I39: =IF(OR(YEAR(A39)=2008, YEAR(A39)=2009), "", H39) -> -0.0010101875 | J39: =IF(OR(YEAR(A39)=2008, YEAR(A39)=2009), "", B39) -> 0.0085567023
A40: =Data!A40 -> 39171 | B40: =Data!B40 - Factors!AB42 -> -0.0018456249 | C40: =Factors!D42 -> 3.0508966e-05 | D40: =Factors!L42 -> 0.0097463387 | E40: =Factors!N42 - Factors!D42 -> 0.0022920381 | G40: {=TREND(B4:B39, C4:E39, C40:E40, TRUE)} -> -0.0010545677 | H40: =B40 - G40 -> -0.00079105717 | I40: =IF(OR(YEAR(A40)=2008, YEAR(A40)=2009), "", H40) -> -0.00079105717 | J40: =IF(OR(YEAR(A40)=2008, YEAR(A40)=2009), "", B40) -> -0.0018456249
A41: =Data!A41 -> 39202 | B41: =Data!B41 - Factors!AB43 -> 0.00063767963 | C41: =Factors!D43 -> 0.0053922952 | D41: =Factors!L43 -> 0.0086616373 | E41: =Factors!N43 - Factors!D43 -> 0.0078404705 | G41: {=TREND(B5:B40, C5:E40, C41:E41, TRUE)} -> 0.0022221494 | H41: =B41 - G41 -> -0.0015844698 | I41: =IF(OR(YEAR(A41)=2008, YEAR(A41)=2009), "", H41) -> -0.0015844698 | J41: =IF(OR(YEAR(A41)=2008, YEAR(A41)=2009), "", B41) -> 0.00063767963
A42: =Data!A42 -> 39233 | B42: =Data!B42 - Factors!AB44 -> -0.0099683011 | C42: =Factors!D44 -> -0.0075785162 | D42: =Factors!L44 -> -0.0038529338 | E42: =Factors!N44 - Factors!D44 -> 0.014693511 | G42: {=TREND(B6:B41, C6:E41, C42:E42, TRUE)} -> -0.0075770056 | H42: =B42 - G42 -> -0.0023912954 | I42: =IF(OR(YEAR(A42)=2008, YEAR(A42)=2009), "", H42) -> -0.0023912954 | J42: =IF(OR(YEAR(A42)=2008, YEAR(A42)=2009), "", B42) -> -0.0099683011
A43: =Data!A43 -> 39262 | B43: =Data!B43 - Factors!AB45 -> -0.0081880157 | C43: =Factors!D45 -> -0.0029582406 | D43: =Factors!L45 -> -0.018884142 | E43: =Factors!N45 - Factors!D45 -> -0.013895785 | G43: {=TREND(B7:B42, C7:E42, C43:E43, TRUE)} -> -0.0055362427 | H43: =B43 - G43 -> -0.002651773 | I43: =IF(OR(YEAR(A43)=2008, YEAR(A43)=2009), "", H43) -> -0.002651773 | J43: =IF(OR(YEAR(A43)=2008, YEAR(A43)=2009), "", B43) -> -0.0081880157
A44: =Data!A44 -> 39294 | B44: =Data!B44 - Factors!AB46 -> 0.0029644939 | C44: =Factors!D46 -> 0.0083413834 | D44: =Factors!L46 -> -0.0090182943 | E44: =Factors!N46 - Factors!D46 -> -0.039741875 | G44: {=TREND(B8:B43, C8:E43, C44:E44, TRUE)} -> 0.0028887435 | H44: =B44 - G44 -> 7.5750457e-05 | I44: =IF(OR(YEAR(A44)=2008, YEAR(A44)=2009), "", H44) -> 7.5750457e-05 | J44: =IF(OR(YEAR(A44)=2008, YEAR(A44)=2009), "", B44) -> 0.0029644939
A45: =Data!A45 -> 39325 | B45: =Data!B45 - Factors!AB47 -> 0.0068386208 | C45: =Factors!D47 -> 0.012256505 | D45: =Factors!L47 -> 0.012116485 | E45: =Factors!N47 - Factors!D47 -> -0.0011101182 | G45: {=TREND(B9:B44, C9:E44, C45:E45, TRUE)} -> 0.0065354975 | H45: =B45 - G45 -> 0.00030312333 | I45: =IF(OR(YEAR(A45)=2008, YEAR(A45)=2009), "", H45) -> 0.00030312333 | J45: =IF(OR(YEAR(A45)=2008, YEAR(A45)=2009), "", B45) -> 0.0068386208
A46: =Data!A46 -> 39353 | B46: =Data!B46 - Factors!AB48 -> 0.0041751696 | C46: =Factors!D48 -> 0.0075863416 | D46: =Factors!L48 -> 0.022709757 | E46: =Factors!N48 - Factors!D48 -> 0.016853228 | G46: {=TREND(B10:B45, C10:E45, C46:E46, TRUE)} -> 0.0041305146 | H46: =B46 - G46 -> 4.4655019e-05 | I46: =IF(OR(YEAR(A46)=2008, YEAR(A46)=2009), "", H46) -> 4.4655019e-05 | J46: =IF(OR(YEAR(A46)=2008, YEAR(A46)=2009), "", B46) -> 0.0041751696
A47: =Data!A47 -> 39386 | B47: =Data!B47 - Factors!AB49 -> 0.0070930246 | C47: =Factors!D49 -> 0.0089828841 | D47: =Factors!L49 -> 0.023838232 | E47: =Factors!N49 - Factors!D49 -> -0.0029284122 | G47: {=TREND(B11:B46, C11:E46, C47:E47, TRUE)} -> 0.0056302717 | H47: =B47 - G47 -> 0.0014627528 | I47: =IF(OR(YEAR(A47)=2008, YEAR(A47)=2009), "", H47) -> 0.0014627528 | J47: =IF(OR(YEAR(A47)=2008, YEAR(A47)=2009), "", B47) -> 0.0070930246
A48: =Data!A48 -> 39416 | B48: =Data!B48 - Factors!AB50 -> 0.013575159 | C48: =Factors!D50 -> 0.01798314 | D48: =Factors!L50 -> -0.0037047033 | E48: =Factors!N50 - Factors!D50 -> -0.03844679 | G48: {=TREND(B12:B47, C12:E47, C48:E48, TRUE)} -> 0.009574771 | H48: =B48 - G48 -> 0.0040003883 | I48: =IF(OR(YEAR(A48)=2008, YEAR(A48)=2009), "", H48) -> 0.0040003883 | J48: =IF(OR(YEAR(A48)=2008, YEAR(A48)=2009), "", B48) -> 0.013575159
A49: =Data!A49 -> 39447 | B49: =Data!B49 - Factors!AB51 -> 5.9352799e-05 | C49: =Factors!D51 -> 0.0028087645 | D49: =Factors!L51 -> 0.0062302994 | E49: =Factors!N51 - Factors!D51 -> 0.00012305996 | G49: {=TREND(B13:B48, C13:E48, C49:E49, TRUE)} -> -0.00012382651 | H49: =B49 - G49 -> 0.00018317931 | I49: =IF(OR(YEAR(A49)=2008, YEAR(A49)=2009), "", H49) -> 0.00018317931 | J49: =IF(OR(YEAR(A49)=2008, YEAR(A49)=2009), "", B49) -> 5.9352799e-05
... A121: =Data!A121 -> 41639 | B121: =Data!B121 - Factors!AB123 -> -0.0047703471 | C121: =Factors!D123 -> -0.0056511476 | D121: =Factors!L123 -> 0.0058312774 | E121: =Factors!N123 - Factors!D123 -> 0.01113092 | G121: {=TREND(B85:B120, C85:E120, C121:E121, TRUE)} -> -0.002475845 | H121: =B121 - G121 -> -0.002294502 | I121: =IF(OR(YEAR(A121)=2008, YEAR(A121)=2009), "", H121) -> -0.002294502 | J121: =IF(OR(YEAR(A121)=2008, YEAR(A121)=2009), "", B121) -> -0.0047703471

Sheet A1 Rolling Betas
A1: Date | B1: Beta US AGG | C1: Beta EM Bond | D1: Beta Credit Spread | E1: Beta Intercept
A38: ='A1'!A38 -> 39113 | B38: =INDEX(LINEST('A1'!B2:B37, 'A1'!C2:E37, TRUE, FALSE), 1, 3) -> 0.68532602 | C38: =INDEX(LINEST('A1'!B2:B37, 'A1'!C2:E37, TRUE, FALSE), 1, 2) -> 0.038243692 | D38: =INDEX(LINEST('A1'!B2:B37, 'A1'!C2:E37, TRUE, FALSE), 1, 1) -> -0.0069555604 | E38: =INDEX(LINEST('A1'!B2:B37, 'A1'!C2:E37, TRUE, FALSE), 1, 4) -> -0.001444226
A39: ='A1'!A39 -> 39141 | B39: =INDEX(LINEST('A1'!B3:B38, 'A1'!C3:E38, TRUE, FALSE), 1, 3) -> 0.66227709 | C39: =INDEX(LINEST('A1'!B3:B38, 'A1'!C3:E38, TRUE, FALSE), 1, 2) -> 0.048587032 | D39: =INDEX(LINEST('A1'!B3:B38, 'A1'!C3:E38, TRUE, FALSE), 1, 1) -> -0.017778507 | E39: =INDEX(LINEST('A1'!B3:B38, 'A1'!C3:E38, TRUE, FALSE), 1, 4) -> -0.0015059881
A40: ='A1'!A40 -> 39171 | B40: =INDEX(LINEST('A1'!B4:B39, 'A1'!C4:E39, TRUE, FALSE), 1, 3) -> 0.6397446 | C40: =INDEX(LINEST('A1'!B4:B39, 'A1'!C4:E39, TRUE, FALSE), 1, 2) -> 0.057800696 | D40: =INDEX(LINEST('A1'!B4:B39, 'A1'!C4:E39, TRUE, FALSE), 1, 1) -> -0.016907032 | E40: =INDEX(LINEST('A1'!B4:B39, 'A1'!C4:E39, TRUE, FALSE), 1, 4) -> -0.0015986793
A41: ='A1'!A41 -> 39202 | B41: =INDEX(LINEST('A1'!B5:B40, 'A1'!C5:E40, TRUE, FALSE), 1, 3) -> 0.6391884 | C41: =INDEX(LINEST('A1'!B5:B40, 'A1'!C5:E40, TRUE, FALSE), 1, 2) -> 0.059304309 | D41: =INDEX(LINEST('A1'!B5:B40, 'A1'!C5:E40, TRUE, FALSE), 1, 1) -> -0.017769362 | E41: =INDEX(LINEST('A1'!B5:B40, 'A1'!C5:E40, TRUE, FALSE), 1, 4) -> -0.0015988954
A42: ='A1'!A42 -> 39233 | B42: =INDEX(LINEST('A1'!B6:B41, 'A1'!C6:E41, TRUE, FALSE), 1, 3) -> 0.62988822 | C42: =INDEX(LINEST('A1'!B6:B41, 'A1'!C6:E41, TRUE, FALSE), 1, 2) -> 0.088573026 | D42: =INDEX(LINEST('A1'!B6:B41, 'A1'!C6:E41, TRUE, FALSE), 1, 1) -> -0.036582578 | E42: =INDEX(LINEST('A1'!B6:B41, 'A1'!C6:E41, TRUE, FALSE), 1, 4) -> -0.0019245951
A43: ='A1'!A43 -> 39262 | B43: =INDEX(LINEST('A1'!B7:B42, 'A1'!C7:E42, TRUE, FALSE), 1, 3) -> 0.64672944 | C43: =INDEX(LINEST('A1'!B7:B42, 'A1'!C7:E42, TRUE, FALSE), 1, 2) -> 0.094060068 | D43: =INDEX(LINEST('A1'!B7:B42, 'A1'!C7:E42, TRUE, FALSE), 1, 1) -> -0.026764633 | E43: =INDEX(LINEST('A1'!B7:B42, 'A1'!C7:E42, TRUE, FALSE), 1, 4) -> -0.0022187333
A44: ='A1'!A44 -> 39294 | B44: =INDEX(LINEST('A1'!B8:B43, 'A1'!C8:E43, TRUE, FALSE), 1, 3) -> 0.63476133 | C44: =INDEX(LINEST('A1'!B8:B43, 'A1'!C8:E43, TRUE, FALSE), 1, 2) -> 0.1039827 | D44: =INDEX(LINEST('A1'!B8:B43, 'A1'!C8:E43, TRUE, FALSE), 1, 1) -> -0.026117429 | E44: =INDEX(LINEST('A1'!B8:B43, 'A1'!C8:E43, TRUE, FALSE), 1, 4) -> -0.0025062532
A45: ='A1'!A45 -> 39325 | B45: =INDEX(LINEST('A1'!B9:B44, 'A1'!C9:E44, TRUE, FALSE), 1, 3) -> 0.63709575 | C45: =INDEX(LINEST('A1'!B9:B44, 'A1'!C9:E44, TRUE, FALSE), 1, 2) -> 0.099955625 | D45: =INDEX(LINEST('A1'!B9:B44, 'A1'!C9:E44, TRUE, FALSE), 1, 1) -> -0.025565891 | E45: =INDEX(LINEST('A1'!B9:B44, 'A1'!C9:E44, TRUE, FALSE), 1, 4) -> -0.0025125614
A46: ='A1'!A46 -> 39353 | B46: =INDEX(LINEST('A1'!B10:B45, 'A1'!C10:E45, TRUE, FALSE), 1, 3) -> 0.63836423 | C46: =INDEX(LINEST('A1'!B10:B45, 'A1'!C10:E45, TRUE, FALSE), 1, 2) -> 0.097155287 | D46: =INDEX(LINEST('A1'!B10:B45, 'A1'!C10:E45, TRUE, FALSE), 1, 1) -> -0.024605143 | E46: =INDEX(LINEST('A1'!B10:B45, 'A1'!C10:E45, TRUE, FALSE), 1, 4) -> -0.0025040314
A47: ='A1'!A47 -> 39386 | B47: =INDEX(LINEST('A1'!B11:B46, 'A1'!C11:E46, TRUE, FALSE), 1, 3) -> 0.63803677 | C47: =INDEX(LINEST('A1'!B11:B46, 'A1'!C11:E46, TRUE, FALSE), 1, 2) -> 0.097599533 | D47: =INDEX(LINEST('A1'!B11:B46, 'A1'!C11:E46, TRUE, FALSE), 1, 1) -> -0.024321618 | E47: =INDEX(LINEST('A1'!B11:B46, 'A1'!C11:E46, TRUE, FALSE), 1, 4) -> -0.0024989626
A48: ='A1'!A48 -> 39416 | B48: =INDEX(LINEST('A1'!B12:B47, 'A1'!C12:E47, TRUE, FALSE), 1, 3) -> 0.61776749 | C48: =INDEX(LINEST('A1'!B12:B47, 'A1'!C12:E47, TRUE, FALSE), 1, 2) -> 0.10641114 | D48: =INDEX(LINEST('A1'!B12:B47, 'A1'!C12:E47, TRUE, FALSE), 1, 1) -> -0.035640518 | E48: =INDEX(LINEST('A1'!B12:B47, 'A1'!C12:E47, TRUE, FALSE), 1, 4) -> -0.00251067
A49: ='A1'!A49 -> 39447 | B49: =INDEX(LINEST('A1'!B13:B48, 'A1'!C13:E48, TRUE, FALSE), 1, 3) -> 0.67459244 | C49: =INDEX(LINEST('A1'!B13:B48, 'A1'!C13:E48, TRUE, FALSE), 1, 2) -> 0.085149789 | D49: =INDEX(LINEST('A1'!B13:B48, 'A1'!C13:E48, TRUE, FALSE), 1, 1) -> -0.046560437 | E49: =INDEX(LINEST('A1'!B13:B48, 'A1'!C13:E48, TRUE, FALSE), 1, 4) -> -0.0025433768
... A121: ='A1'!A121 -> 41639 | B121: =INDEX(LINEST('A1'!B85:B120, 'A1'!C85:E120, TRUE, FALSE), 1, 3) -> 0.48889754 | C121: =INDEX(LINEST('A1'!B85:B120, 'A1'!C85:E120, TRUE, FALSE), 1, 2) -> 0.092763772 | D121: =INDEX(LINEST('A1'!B85:B120, 'A1'!C85:E120, TRUE, FALSE), 1, 1) -> -0.077208358 | E121: =INDEX(LINEST('A1'!B85:B120, 'A1'!C85:E120, TRUE, FALSE), 1, 4) -> 0.00060545591

Sheet A2
A1: Date | B1: xAsset2 | C1: US Growth | D1: Growth - Value | E1: Small - S&P500 | G1: Predicted | H1: Residual | I1: Resid_ex0809 | J1: xAsset_ex0809 | L1: Factor | M1: R^2 aux | N1: VIF
A2: =Data!A2 -> 38016 | B2: =Data!C2 - Factors!AB4 -> 0.034039209 | C2: =Factors!V4 -> 0.020422332 | D2: =Factors!V4 - Factors!W4 -> 0.002838608 | E2: =Factors!X4 - Factors!AA4 -> 0.025090927 | L2: US Growth | M2: =INDEX(LINEST(C2:C121, D2:E121, TRUE, TRUE), 3, 1) -> 0.22127521 | N2: =1/(1-M2) -> 1.2841507
A3: =Data!A3 -> 38044 | B3: =Data!C3 - Factors!AB5 -> -0.033257653 | C3: =Factors!V5 -> 0.0063532895 | D3: =Factors!V5 - Factors!W5 -> -0.01507851 | E3: =Factors!X5 - Factors!AA5 -> -0.0049351123 | L3: Growth-Value | M3: =INDEX(LINEST(D2:D121, CHOOSE({1,2}, C2:C121, E2:E121), TRUE, TRUE), 3, 1) -> 0.024522283 | N3: =1/(1-M3) -> 1.0251387
A4: =Data!A4 -> 38077 | B4: =Data!C4 - Factors!AB6 -> -0.027465167 | C4: =Factors!V6 -> -0.01855019 | D4: =Factors!V6 - Factors!W6 -> -0.0097981116 | E4: =Factors!X6 - Factors!AA6 -> 0.024405898 | L4: Small-S&P500 | M4: =INDEX(LINEST(E2:E121, C2:D121, TRUE, TRUE), 3, 1) -> 0.21107913 | N4: =1/(1-M4) -> 1.2675542
A5: =Data!A5 -> 38107 | B5: =Data!C5 - Factors!AB7 -> -0.047464745 | C5: =Factors!V7 -> -0.011625293 | D5: =Factors!V7 - Factors!W7 -> 0.012814313 | E5: =Factors!X7 - Factors!AA7 -> -0.035285976 | G5: SUMMARY OUTPUT
A6: =Data!A6 -> 38138 | B6: =Data!C6 - Factors!AB8 -> 0.048768476 | C6: =Factors!V8 -> 0.018638848 | D6: =Factors!V8 - Factors!W8 -> 0.008440504 | E6: =Factors!X8 - Factors!AA8 -> 0.002193387
A7: =Data!A7 -> 38168 | B7: =Data!C7 - Factors!AB9 -> 0.02700695 | C7: =Factors!V9 -> 0.012495751 | D7: =Factors!V9 - Factors!W9 -> -0.011132447 | E7: =Factors!X9 - Factors!AA9 -> 0.022668462 | G7: Regression Statistics
A8: =Data!A8 -> 38198 | B8: =Data!C8 - Factors!AB10 -> -0.076484301 | C8: =Factors!V10 -> -0.056532161 | D8: =Factors!V10 - Factors!W10 -> -0.042445489 | E8: =Factors!X10 - Factors!AA10 -> -0.034236249 | G8: Multiple R | H8: 0.94872255
A9: =Data!A9 -> 38230 | B9: =Data!C9 - Factors!AB11 -> -0.054394279 | C9: =Factors!V11 -> -0.0049383484 | D9: =Factors!V11 - Factors!W11 -> -0.019159729 | E9: =Factors!X11 - Factors!AA11 -> -0.0091842866 | G9: R Square | H9: 0.90007447
A10: =Data!A10 -> 38260 | B10: =Data!C10 - Factors!AB12 -> 0.027972314 | C10: =Factors!V12 -> 0.0095108983 | D10: =Factors!V12 - Factors!W12 -> -0.0059905212 | E10: =Factors!X12 - Factors!AA12 -> 0.036114968 | G10: Adjusted R Square | H10: 0.89749019
A11: =Data!A11 -> 38289 | B11: =Data!C11 - Factors!AB13 -> 0.051186954 | C11: =Factors!V13 -> 0.015596337 | D11: =Factors!V13 - Factors!W13 -> -0.0010274608 | E11: =Factors!X13 - Factors!AA13 -> 0.0044067204 | G11: Standard Error | H11: 0.017268149
A12: =Data!A12 -> 38321 | B12: =Data!C12 - Factors!AB14 -> 0.047227055 | C12: =Factors!V14 -> 0.034398424 | D12: =Factors!V14 - Factors!W14 -> -0.016159537 | E12: =Factors!X14 - Factors!AA14 -> 0.046276913 | G12: Observations | H12: 120
A13: =Data!A13 -> 38352 | B13: =Data!C13 - Factors!AB15 -> 0.026557605 | C13: =Factors!V15 -> 0.039208485 | D13: =Factors!V15 - Factors!W15 -> 0.0057219741 | E13: =Factors!X15 - Factors!AA15 -> -0.0044289797
A14: =Data!A14 -> 38383 | B14: =Data!C14 - Factors!AB16 -> -0.054095576 | C14: =Factors!V16 -> -0.033348503 | D14: =Factors!V16 - Factors!W16 -> -0.015597855 | E14: =Factors!X16 - Factors!AA16 -> -0.017348382 | G14: ANOVA
A15: =Data!A15 -> 38411 | B15: =Data!C15 - Factors!AB17 -> -0.0011927351 | C15: =Factors!V17 -> 0.010642505 | D15: =Factors!V17 - Factors!W17 -> -0.022499515 | E15: =Factors!X17 - Factors!AA17 -> -0.0041057787 | H15: df | I15: SS | J15: MS | K15: F | L15: Significance F
A16: =Data!A16 -> 38442 | B16: =Data!C16 - Factors!AB18 -> -0.025196024 | C16: =Factors!V18 -> -0.018219344 | D16: =Factors!V18 - Factors!W18 -> -0.0044976356 | E16: =Factors!X18 - Factors!AA18 -> -0.010918705 | G16: Regression | H16: 3 | I16: 0.31156706 | J16: 0.10385569 | K16: 348.28816 | L16: 7.8658089e-58
A17: =Data!A17 -> 38471 | B17: =Data!C17 - Factors!AB19 -> -0.041792742 | C17: =Factors!V19 -> -0.019043377 | D17: =Factors!V19 - Factors!W19 -> -0.0011328093 | E17: =Factors!X19 - Factors!AA19 -> -0.038302915 | G17: Residual | H17: 116 | I17: 0.03458992 | J17: 0.00029818897
A18: =Data!A18 -> 38503 | B18: =Data!C18 - Factors!AB20 -> 0.075449627 | C18: =Factors!V20 -> 0.048382484 | D18: =Factors!V20 - Factors!W20 -> 0.024309576 | E18: =Factors!X20 - Factors!AA20 -> 0.03363222 | G18: Total | H18: 119 | I18: 0.34615698
A19: =Data!A19 -> 38533 | B19: =Data!C19 - Factors!AB21 -> -0.019681493 | C19: =Factors!V21 -> -0.0036864905 | D19: =Factors!V21 - Factors!W21 -> -0.014634832 | E19: =Factors!X21 - Factors!AA21 -> 0.037151269
A20: =Data!A20 -> 38562 | B20: =Data!C20 - Factors!AB22 -> 0.056072297 | C20: =Factors!V22 -> 0.048875218 | D20: =Factors!V22 - Factors!W22 -> 0.01994322 | E20: =Factors!X22 - Factors!AA22 -> 0.026166997 | H20: Coefficients | I20: Standard Error | J20: t Stat | K20: P-value | L20: Lower 95% | M20: Upper 95% | N20: Lower 95.0% | O20: Upper 95.0%
A21: =Data!A21 -> 38595 | B21: =Data!C21 - Factors!AB23 -> -0.0051019974 | C21: =Factors!V23 -> -0.012878843 | D21: =Factors!V23 - Factors!W23 -> -0.0085300654 | E21: =Factors!X23 - Factors!AA23 -> -0.0094164056 | G21: Intercept | H21: -0.0027021659 | I21: 0.0015986991 | J21: -1.6902279 | K21: 0.093669972 | L21: -0.0058685909 | M21: 0.00046425914 | N21: -0.0058685909 | O21: 0.00046425914
A22: =Data!A22 -> 38625 | B22: =Data!C22 - Factors!AB24 -> -9.1459509e-05 | C22: =Factors!V24 -> 0.0046048521 | D22: =Factors!V24 - Factors!W24 -> -0.0094355618 | E22: =Factors!X24 - Factors!AA24 -> -0.0049627077 | G22: US Growth | H22: 1.101134 | I22: 0.041448861 | J22: 26.566085 | K22: 3.8429528e-51 | L22: 1.0190393 | M22: 1.1832287 | N22: 1.0190393 | O22: 1.1832287
A23: =Data!A23 -> 38656 | B23: =Data!C23 - Factors!AB25 -> -0.024561357 | C23: =Factors!V25 -> -0.0097199284 | D23: =Factors!V25 - Factors!W25 -> 0.01567761 | E23: =Factors!X25 - Factors!AA25 -> -0.014378494 | G23: Growth - Value | H23: 0.45214917 | I23: 0.091052421 | J23: 4.9658116 | K23: 2.3756777e-06 | L23: 0.27180837 | M23: 0.63248996 | N23: 0.27180837 | O23: 0.63248996
A24: =Data!A24 -> 38686 | B24: =Data!C24 - Factors!AB26 -> 0.060937264 | C24: =Factors!V26 -> 0.043145157 | D24: =Factors!V26 - Factors!W26 -> 0.010445097 | E24: =Factors!X26 - Factors!AA26 -> 0.010723679 | G24: Small - S&P500 | H24: 0.17417433 | I24: 0.07465696 | J24: 2.3329952 | K24: 0.021371478 | L24: 0.026306811 | M24: 0.32204184 | N24: 0.026306811 | O24: 0.32204184
A25: =Data!A25 -> 38716 | B25: =Data!C25 - Factors!AB27 -> -0.032513564 | C25: =Factors!V27 -> -0.0031349222 | D25: =Factors!V27 - Factors!W27 -> -0.0092760357 | E25: =Factors!X27 - Factors!AA27 -> -0.0049183165
A26: =Data!A26 -> 38748 | B26: =Data!C26 - Factors!AB28 -> 0.028843695 | C26: =Factors!V28 -> 0.017555912 | D26: =Factors!V28 - Factors!W28 -> -0.021283242 | E26: =Factors!X28 - Factors!AA28 -> 0.063194492
A27: =Data!A27 -> 38776 | B27: =Data!C27 - Factors!AB29 -> -0.01234019 | C27: =Factors!V29 -> -0.0015890374 | D27: =Factors!V29 - Factors!W29 -> -0.0076931105 | E27: =Factors!X29 - Factors!AA29 -> -0.0054668284
A28: =Data!A28 -> 38807 | B28: =Data!C28 - Factors!AB30 -> 0.014344276 | C28: =Factors!V30 -> 0.014765656 | D28: =Factors!V30 - Factors!W30 -> 0.0012187249 | E28: =Factors!X30 - Factors!AA30 -> 0.036069977
A29: =Data!A29 -> 38835 | B29: =Data!C29 - Factors!AB31 -> -0.015144486 | C29: =Factors!V31 -> -0.0013600246 | D29: =Factors!V31 - Factors!W31 -> -0.02677154 | E29: =Factors!X31 - Factors!AA31 -> -0.013590947 | H29: OOS R Square | I29: =1 - SUMSQ(H38:H121) / DEVSQ(B38:B121) -> 0.90060514
A30: =Data!A30 -> 38868 | B30: =Data!C30 - Factors!AB32 -> -0.074900558 | C30: =Factors!V32 -> -0.033895548 | D30: =Factors!V32 - Factors!W32 -> -0.0086361784 | E30: =Factors!X32 - Factors!AA32 -> -0.027378887 | H30: OOS RMSE | I30: =SQRT( SUMSQ(H38:H121) / COUNT(H38:H121) ) -> 0.018285298
A31: =Data!A31 -> 38898 | B31: =Data!C31 - Factors!AB33 -> -0.020439838 | C31: =Factors!V33 -> -0.0039456266 | D31: =Factors!V33 - Factors!W33 -> -0.010341834 | E31: =Factors!X33 - Factors!AA33 -> 0.0050737945 | H31: ex0809 OOS R^2 | I31: =1 - SUMSQ(I38:I121) / DEVSQ(J38:J121) -> 0.86445661
A32: =Data!A32 -> 38929 | B32: =Data!C32 - Factors!AB34 -> -0.041865795 | C32: =Factors!V34 -> -0.019046226 | D32: =Factors!V34 - Factors!W34 -> -0.043349556 | E32: =Factors!X34 - Factors!AA34 -> -0.038707189
A33: =Data!A33 -> 38960 | B33: =Data!C33 - Factors!AB35 -> 0.07952116 | C33: =Factors!V35 -> 0.031199326 | D33: =Factors!V35 - Factors!W35 -> 0.014460505 | E33: =Factors!X35 - Factors!AA35 -> 0.0058143468
A34: =Data!A34 -> 38989 | B34: =Data!C34 - Factors!AB36 -> 0.035732557 | C34: =Factors!V36 -> 0.027478554 | D34: =Factors!V36 - Factors!W36 -> 0.0075458035 | E34: =Factors!X36 - Factors!AA36 -> -0.01744476
A35: =Data!A35 -> 39021 | B35: =Data!C35 - Factors!AB37 -> 0.037297893 | C35: =Factors!V37 -> 0.035153351 | D35: =Factors!V37 - Factors!W37 -> 0.002420285 | E35: =Factors!X37 - Factors!AA37 -> 0.024991521
A36: =Data!A36 -> 39051 | B36: =Data!C36 - Factors!AB38 -> 0.028300846 | C36: =Factors!V38 -> 0.019844378 | D36: =Factors!V38 - Factors!W38 -> -0.0029841881 | E36: =Factors!X38 - Factors!AA38 -> 0.0072892807
A37: =Data!A37 -> 39080 | B37: =Data!C37 - Factors!AB39 -> -0.017699892 | C37: =Factors!V39 -> 0.0033862167 | D37: =Factors!V39 - Factors!W39 -> -0.019062227 | E37: =Factors!X39 - Factors!AA39 -> -0.010679034 | G37: 36 Month Rolling
A38: =Data!A38 -> 39113 | B38: =Data!C38 - Factors!AB40 -> 0.011683084 | C38: =Factors!V40 -> 0.025705948 | D38: =Factors!V40 - Factors!W40 -> 0.01291813 | E38: =Factors!X40 - Factors!AA40 -> 0.0016108122 | G38: {=TREND(B2:B37, C2:E37, C38:E38, TRUE)} -> 0.032359965 | H38: =B38 - G38 -> -0.020676881 | I38: =IF(OR(YEAR(A38)=2008, YEAR(A38)=2009), "", H38) -> -0.020676881 | J38: =IF(OR(YEAR(A38)=2008, YEAR(A38)=2009), "", B38) -> 0.011683084
A39: =Data!A39 -> 39141 | B39: =Data!C39 - Factors!AB41 -> -0.034536323 | C39: =Factors!V41 -> -0.018796556 | D39: =Factors!V41 - Factors!W41 -> -0.0032067183 | E39: =Factors!X41 - Factors!AA41 -> 0.011623902 | G39: {=TREND(B3:B38, C3:E38, C39:E39, TRUE)} -> -0.028106622 | H39: =B39 - G39 -> -0.0064297011 | I39: =IF(OR(YEAR(A39)=2008, YEAR(A39)=2009), "", H39) -> -0.0064297011 | J39: =IF(OR(YEAR(A39)=2008, YEAR(A39)=2009), "", B39) -> -0.034536323
A40: =Data!A40 -> 39171 | B40: =Data!C40 - Factors!AB42 -> 0.0012081448 | C40: =Factors!V42 -> 0.005423696 | D40: =Factors!V42 - Factors!W42 -> -0.010037373 | E40: =Factors!X42 - Factors!AA42 -> -0.00047954754 | G40: {=TREND(B4:B39, C4:E39, C40:E40, TRUE)} -> -0.00043093058 | H40: =B40 - G40 -> 0.0016390754 | I40: =IF(OR(YEAR(A40)=2008, YEAR(A40)=2009), "", H40) -> 0.0016390754 | J40: =IF(OR(YEAR(A40)=2008, YEAR(A40)=2009), "", B40) -> 0.0012081448
A41: =Data!A41 -> 39202 | B41: =Data!C41 - Factors!AB43 -> 0.049764513 | C41: =Factors!V43 -> 0.047079873 | D41: =Factors!V43 - Factors!W43 -> 0.01012743 | E41: =Factors!X43 - Factors!AA43 -> -0.026332884 | G41: {=TREND(B5:B40, C5:E40, C41:E41, TRUE)} -> 0.053038447 | H41: =B41 - G41 -> -0.0032739345 | I41: =IF(OR(YEAR(A41)=2008, YEAR(A41)=2009), "", H41) -> -0.0032739345 | J41: =IF(OR(YEAR(A41)=2008, YEAR(A41)=2009), "", B41) -> 0.049764513
A42: =Data!A42 -> 39233 | B42: =Data!C42 - Factors!AB44 -> 0.0354954 | C42: =Factors!V44 -> 0.035975205 | D42: =Factors!V44 - Factors!W44 -> -9.388196e-05 | E42: =Factors!X44 - Factors!AA44 -> 0.0060604239 | G42: {=TREND(B6:B41, C6:E41, C42:E42, TRUE)} -> 0.043612393 | H42: =B42 - G42 -> -0.0081169937 | I42: =IF(OR(YEAR(A42)=2008, YEAR(A42)=2009), "", H42) -> -0.0081169937 | J42: =IF(OR(YEAR(A42)=2008, YEAR(A42)=2009), "", B42) -> 0.0354954
A43: =Data!A43 -> 39262 | B43: =Data!C43 - Factors!AB45 -> 0.0025520545 | C43: =Factors!V45 -> -0.014927265 | D43: =Factors!V45 - Factors!W45 -> 0.0084383637 | E43: =Factors!X45 - Factors!AA45 -> 0.001984455 | G43: {=TREND(B7:B42, C7:E42, C43:E43, TRUE)} -> -0.023041334 | H43: =B43 - G43 -> 0.025593389 | I43: =IF(OR(YEAR(A43)=2008, YEAR(A43)=2009), "", H43) -> 0.025593389 | J43: =IF(OR(YEAR(A43)=2008, YEAR(A43)=2009), "", B43) -> 0.0025520545
A44: =Data!A44 -> 39294 | B44: =Data!C44 - Factors!AB46 -> -0.0083667901 | C44: =Factors!V46 -> -0.01550296 | D44: =Factors!V46 - Factors!W46 -> 0.03074108 | E44: =Factors!X46 - Factors!AA46 -> -0.037389864 | G44: {=TREND(B8:B43, C8:E43, C44:E44, TRUE)} -> -0.022168961 | H44: =B44 - G44 -> 0.013802171 | I44: =IF(OR(YEAR(A44)=2008, YEAR(A44)=2009), "", H44) -> 0.013802171 | J44: =IF(OR(YEAR(A44)=2008, YEAR(A44)=2009), "", B44) -> -0.0083667901
A45: =Data!A45 -> 39325 | B45: =Data!C45 - Factors!AB47 -> 0.023463332 | C45: =Factors!V47 -> 0.015934413 | D45: =Factors!V47 - Factors!W47 -> 0.0047294607 | E45: =Factors!X47 - Factors!AA47 -> 0.0076756891 | G45: {=TREND(B9:B44, C9:E44, C45:E45, TRUE)} -> 0.019579357 | H45: =B45 - G45 -> 0.0038839741 | I45: =IF(OR(YEAR(A45)=2008, YEAR(A45)=2009), "", H45) -> 0.0038839741 | J45: =IF(OR(YEAR(A45)=2008, YEAR(A45)=2009), "", B45) -> 0.023463332
A46: =Data!A46 -> 39353 | B46: =Data!C46 - Factors!AB48 -> 0.034348308 | C46: =Factors!V48 -> 0.041890197 | D46: =Factors!V48 - Factors!W48 -> 0.0075423622 | E46: =Factors!X48 - Factors!AA48 -> -0.020233866 | G46: {=TREND(B10:B45, C10:E45, C46:E46, TRUE)} -> 0.046735911 | H46: =B46 - G46 -> -0.012387603 | I46: =IF(OR(YEAR(A46)=2008, YEAR(A46)=2009), "", H46) -> -0.012387603 | J46: =IF(OR(YEAR(A46)=2008, YEAR(A46)=2009), "", B46) -> 0.034348308
A47: =Data!A47 -> 39386 | B47: =Data!C47 - Factors!AB49 -> 0.068327326 | C47: =Factors!V49 -> 0.034034179 | D47: =Factors!V49 - Factors!W49 -> 0.033923203 | E47: =Factors!X49 - Factors!AA49 -> 0.012783872 | G47: {=TREND(B11:B46, C11:E46, C47:E47, TRUE)} -> 0.054232199 | H47: =B47 - G47 -> 0.014095127 | I47: =IF(OR(YEAR(A47)=2008, YEAR(A47)=2009), "", H47) -> 0.014095127 | J47: =IF(OR(YEAR(A47)=2008, YEAR(A47)=2009), "", B47) -> 0.068327326
A48: =Data!A48 -> 39416 | B48: =Data!C48 - Factors!AB50 -> -0.084061753 | C48: =Factors!V50 -> -0.036837044 | D48: =Factors!V50 - Factors!W50 -> 0.012036551 | E48: =Factors!X50 - Factors!AA50 -> -0.029999416 | G48: {=TREND(B12:B47, C12:E47, C48:E48, TRUE)} -> -0.049353475 | H48: =B48 - G48 -> -0.034708278 | I48: =IF(OR(YEAR(A48)=2008, YEAR(A48)=2009), "", H48) -> -0.034708278 | J48: =IF(OR(YEAR(A48)=2008, YEAR(A48)=2009), "", B48) -> -0.084061753
A49: =Data!A49 -> 39447 | B49: =Data!C49 - Factors!AB51 -> 0.012356465 | C49: =Factors!V51 -> -0.0036159777 | D49: =Factors!V51 - Factors!W51 -> 0.0060546061 | E49: =Factors!X51 - Factors!AA51 -> 0.0063138124 | G49: {=TREND(B13:B48, C13:E48, C49:E49, TRUE)} -> -0.0069466761 | H49: =B49 - G49 -> 0.019303141 | I49: =IF(OR(YEAR(A49)=2008, YEAR(A49)=2009), "", H49) -> 0.019303141 | J49: =IF(OR(YEAR(A49)=2008, YEAR(A49)=2009), "", B49) -> 0.012356465
... A121: =Data!A121 -> 41639 | B121: =Data!C121 - Factors!AB123 -> 0.041275812 | C121: =Factors!V123 -> 0.028564868 | D121: =Factors!V123 - Factors!W123 -> 0.0032374424 | E121: =Factors!X123 - Factors!AA123 -> -0.0056358384 | G121: {=TREND(B85:B120, C85:E120, C121:E121, TRUE)} -> 0.031605682 | H121: =B121 - G121 -> 0.0096701304 | I121: =IF(OR(YEAR(A121)=2008, YEAR(A121)=2009), "", H121) -> 0.0096701304 | J121: =IF(OR(YEAR(A121)=2008, YEAR(A121)=2009), "", B121) -> 0.041275812

Sheet A3
A1: Date | B1: xAsset3 | C1: Commodities | D1: Event Driven HF | G1: Predicted | H1: Residual | I1: Resid_ex0809 | J1: xAsset_ex0809 | L1: Factors | M1: R^2 aux | N1: VIF
A2: =Data!A2 -> 38016 | B2: =Data!D2 - Factors!AB4 -> 0.031878518 | C2: =Factors!G4 -> 0.018131402 | D2: =Factors!I4 -> 0.027989998 | L2: Commodities | M2: =RSQ(C2:C121, D2:D121) -> 0.34946274 | N2: =1/(1-M2) -> 1.537191
A3: =Data!A3 -> 38044 | B3: =Data!D3 - Factors!AB5 -> 0.083234653 | C3: =Factors!G5 -> 0.06488201 | D3: =Factors!I5 -> 0.012020003 | L3: Event Driven HF | M3: =RSQ(C3:C122, D3:D122) -> 0.35016791 | N3: =1/(1-M3) -> 1.5388591
A4: =Data!A4 -> 38077 | B4: =Data!D4 - Factors!AB6 -> -0.0043764061 | C4: =Factors!G6 -> 0.030877435 | D4: =Factors!I6 -> 0.00057999971
A5: =Data!A5 -> 38107 | B5: =Data!D5 - Factors!AB7 -> -0.086266702 | C5: =Factors!G7 -> -0.017736548 | D5: =Factors!I7 -> -0.005619991
A6: =Data!A6 -> 38138 | B6: =Data!D6 - Factors!AB8 -> 0.042917294 | C6: =Factors!G8 -> 0.016954736 | D6: =Factors!I8 -> -0.0031200008 | F6: SUMMARY OUTPUT
A7: =Data!A7 -> 38168 | B7: =Data!D7 - Factors!AB9 -> -0.0040735819 | C7: =Factors!G9 -> -0.041462267 | D7: =Factors!I9 -> 0.017579991
A8: =Data!A8 -> 38198 | B8: =Data!D8 - Factors!AB10 -> 0.018803388 | C8: =Factors!G10 -> 0.017666821 | D8: =Factors!I10 -> -0.0093100039 | F8: Regression Statistics
A9: =Data!A9 -> 38230 | B9: =Data!D9 - Factors!AB11 -> -0.025322896 | C9: =Factors!G11 -> -0.018225954 | D9: =Factors!I11 -> 0.0049100023 | F9: Multiple R | G9: 0.76428934
A10: =Data!A10 -> 38260 | B10: =Data!D10 - Factors!AB12 -> 0.12039489 | C10: =Factors!G12 -> 0.068466451 | D10: =Factors!I12 -> 0.013649999 | F10: R Square | G10: 0.5841382
A11: =Data!A11 -> 38289 | B11: =Data!D11 - Factors!AB13 -> -0.043277089 | C11: =Factors!G13 -> 0.016922451 | D11: =Factors!I13 -> 0.014890002 | F11: Adjusted R Square | G11: 0.57702945
A12: =Data!A12 -> 38321 | B12: =Data!D12 - Factors!AB14 -> 0.049522834 | C12: =Factors!G14 -> -0.011978445 | D12: =Factors!I14 -> 0.040329999 | F12: Standard Error | G12: 0.046755563
A13: =Data!A13 -> 38352 | B13: =Data!D13 - Factors!AB15 -> 0.048988258 | C13: =Factors!G15 -> -0.049106105 | D13: =Factors!I15 -> 0.027990001 | F13: Observations | G13: 120
A14: =Data!A14 -> 38383 | B14: =Data!D14 - Factors!AB16 -> -0.027927188 | C14: =Factors!G16 -> 0.010434131 | D14: =Factors!I16 -> -0.0014799961
A15: =Data!A15 -> 38411 | B15: =Data!D15 - Factors!AB17 -> 0.058021073 | C15: =Factors!G17 -> 0.07064496 | D15: =Factors!I17 -> 0.013849994 | F15: ANOVA
A16: =Data!A16 -> 38442 | B16: =Data!D16 - Factors!AB18 -> 0.0097695927 | C16: =Factors!G18 -> 0.035651904 | D16: =Factors!I18 -> -0.001979998 | G16: df | H16: SS | I16: MS | J16: F | K16: Significance F
A17: =Data!A17 -> 38471 | B17: =Data!D17 - Factors!AB19 -> -0.046385367 | C17: =Factors!G19 -> -0.058346126 | D17: =Factors!I19 -> -0.017059995 | F17: Regression | G17: 2 | H17: 0.35926839 | I17: 0.1796342 | J17: 82.171731 | K17: 5.1111483e-23
A18: =Data!A18 -> 38503 | B18: =Data!D18 - Factors!AB20 -> -0.014087372 | C18: =Factors!G20 -> -0.0077624598 | D18: =Factors!I20 -> 0.012000004 | F18: Residual | G18: 117 | H18: 0.25577167 | I18: 0.0021860827
A19: =Data!A19 -> 38533 | B19: =Data!D19 - Factors!AB21 -> -0.0064021151 | C19: =Factors!G21 -> 0.016833418 | D19: =Factors!I21 -> 0.013249994 | F19: Total | G19: 119 | H19: 0.61504007
A20: =Data!A20 -> 38562 | B20: =Data!D20 - Factors!AB22 -> 0.060050127 | C20: =Factors!G22 -> 0.044831599 | D20: =Factors!I22 -> 0.023509999
A21: =Data!A21 -> 38595 | B21: =Data!D21 - Factors!AB23 -> 0.018882265 | C21: =Factors!G23 -> 0.075479997 | D21: =Factors!I23 -> 0.0088700061 | G21: Coefficients | H21: Standard Error | I21: t Stat | J21: P-value | K21: Lower 95% | L21: Upper 95% | M21: Lower 95.0% | N21: Upper 95.0%
A22: =Data!A22 -> 38625 | B22: =Data!D22 - Factors!AB24 -> 0.015243661 | C22: =Factors!G24 -> 0.046525664 | D22: =Factors!I24 -> 0.0099799919 | F22: Intercept | G22: -0.0028003893 | H22: 0.0045259493 | I22: -0.61874077 | J22: 0.53728995 | K22: -0.011763795 | L22: 0.006163016 | M22: -0.011763795 | N22: 0.006163016
A23: =Data!A23 -> 38656 | B23: =Data!D23 - Factors!AB25 -> 0.04508219 | C23: =Factors!G25 -> -0.062839567 | D23: =Factors!I25 -> -0.017979998 | F23: Commodoties | G23: 0.68741539 | H23: 0.10203797 | I23: 6.7368588 | J23: 6.4073241e-10 | K23: 0.48533454 | L23: 0.88949624 | M23: 0.48533454 | N23: 0.88949624
A24: =Data!A24 -> 38686 | B24: =Data!D24 - Factors!AB26 -> 0.089889096 | C24: =Factors!G26 -> 0.002582589 | D24: =Factors!I26 -> 0.012900005 | F24: Event Driven HF | G24: 1.3398941 | H24: 0.27830654 | I24: 4.8144541 | J24: 4.4548039e-06 | K24: 0.78872255 | L24: 1.8910656 | M24: 0.78872255 | N24: 1.8910656
A25: =Data!A25 -> 38716 | B25: =Data!D25 - Factors!AB27 -> 0.070228118 | C25: =Factors!G27 -> 0.031883922 | D25: =Factors!I27 -> 0.015669996
A26: =Data!A26 -> 38748 | B26: =Data!D26 - Factors!AB28 -> 0.11377117 | C26: =Factors!G28 -> 0.018495043 | D26: =Factors!I28 -> 0.033220003
A27: =Data!A27 -> 38776 | B27: =Data!D27 - Factors!AB29 -> -0.021024686 | C27: =Factors!G29 -> -0.062602923 | D27: =Factors!I29 -> 0.009650003
A28: =Data!A28 -> 38807 | B28: =Data!D28 - Factors!AB30 -> 0.072205331 | C28: =Factors!G30 -> 0.022241969 | D28: =Factors!I30 -> 0.024759997
A29: =Data!A29 -> 38835 | B29: =Data!D29 - Factors!AB31 -> 0.21806388 | C29: =Factors!G31 -> 0.067798586 | D29: =Factors!I31 -> 0.016289996
A30: =Data!A30 -> 38868 | B30: =Data!D30 - Factors!AB32 -> 0.084328787 | C30: =Factors!G32 -> 0.0095660202 | D30: =Factors!I32 -> -0.0054199986 | H30: OOS R Square | I30: =1 - SUMSQ(H38:H121) / DEVSQ(B38:B121) -> 0.59782265
A31: =Data!A31 -> 38898 | B31: =Data!D31 - Factors!AB33 -> -0.05574601 | C31: =Factors!G33 -> -0.015536902 | D31: =Factors!I33 -> -0.0011599962 | H31: OOS RMSE | I31: =SQRT( SUMSQ(H38:H121) / COUNT(H38:H121) ) -> 0.047287276
A32: =Data!A32 -> 38929 | B32: =Data!D32 - Factors!AB34 -> 0.060117688 | C32: =Factors!G34 -> 0.03210085 | D32: =Factors!I34 -> -0.0043700025 | H32: ex0809 OOS R^2 | I32: =1 - SUMSQ(I38:I121) / DEVSQ(J38:J121) -> 0.55746975
A33: =Data!A33 -> 38960 | B33: =Data!D33 - Factors!AB35 -> 0.010469314 | C33: =Factors!G35 -> -0.036037351 | D33: =Factors!I35 -> 0.010550004
A34: =Data!A34 -> 38989 | B34: =Data!D34 - Factors!AB36 -> 0.0078607685 | C34: =Factors!G36 -> -0.060212157 | D34: =Factors!I36 -> 0.0023299989
A35: =Data!A35 -> 39021 | B35: =Data!D35 - Factors!AB37 -> 0.07577642 | C35: =Factors!G37 -> 0.047435725 | D35: =Factors!I37 -> 0.023289997
A36: =Data!A36 -> 39051 | B36: =Data!D36 - Factors!AB38 -> 0.0027056095 | C36: =Factors!G38 -> 0.054689127 | D36: =Factors!I38 -> 0.018690004
A37: =Data!A37 -> 39080 | B37: =Data!D37 - Factors!AB39 -> -0.029856111 | C37: =Factors!G39 -> -0.045928784 | D37: =Factors!I39 -> 0.0165 | G37: 36 Month Rolling
A38: =Data!A38 -> 39113 | B38: =Data!D38 - Factors!AB40 -> -0.046084105 | C38: =Factors!G40 -> 0.0021049414 | D38: =Factors!I40 -> 0.015743451 | G38: {=TREND(B2:B37, C2:D37, C38:D38, TRUE)} -> 0.031238569 | H38: =B38 - G38 -> -0.077322674 | I38: =IF(OR(YEAR(A38)=2008, YEAR(A38)=2009), "", H38) -> -0.077322674 | J38: =IF(OR(YEAR(A38)=2008, YEAR(A38)=2009), "", B38) -> -0.046084105
A39: =Data!A39 -> 39141 | B39: =Data!D39 - Factors!AB41 -> 0.052680187 | C39: =Factors!G41 -> 0.033675052 | D39: =Factors!I41 -> 0.010238926 | G39: {=TREND(B3:B38, C3:D38, C39:D39, TRUE)} -> 0.04325408 | H39: =B39 - G39 -> 0.0094261073 | I39: =IF(OR(YEAR(A39)=2008, YEAR(A39)=2009), "", H39) -> 0.0094261073 | J39: =IF(OR(YEAR(A39)=2008, YEAR(A39)=2009), "", B39) -> 0.052680187
A40: =Data!A40 -> 39171 | B40: =Data!D40 - Factors!AB42 -> 0.052787084 | C40: =Factors!G42 -> 0.0097484944 | D40: =Factors!I42 -> 0.013578599 | G40: {=TREND(B4:B39, C4:D39, C40:D40, TRUE)} -> 0.031664363 | H40: =B40 - G40 -> 0.021122721 | I40: =IF(OR(YEAR(A40)=2008, YEAR(A40)=2009), "", H40) -> 0.021122721 | J40: =IF(OR(YEAR(A40)=2008, YEAR(A40)=2009), "", B40) -> 0.052787084
A41: =Data!A41 -> 39202 | B41: =Data!D41 - Factors!AB43 -> 0.086029964 | C41: =Factors!G43 -> 0.011551155 | D41: =Factors!I43 -> 0.019871205 | G41: {=TREND(B5:B40, C5:D40, C41:D41, TRUE)} -> 0.041000523 | H41: =B41 - G41 -> 0.045029441 | I41: =IF(OR(YEAR(A41)=2008, YEAR(A41)=2009), "", H41) -> 0.045029441 | J41: =IF(OR(YEAR(A41)=2008, YEAR(A41)=2009), "", B41) -> 0.086029964
A42: =Data!A42 -> 39233 | B42: =Data!D42 - Factors!AB44 -> -0.033641716 | C42: =Factors!G44 -> 0.0012942218 | D42: =Factors!I44 -> 0.021749319 | G42: {=TREND(B6:B41, C6:D41, C42:D42, TRUE)} -> 0.03863128 | H42: =B42 - G42 -> -0.072272996 | I42: =IF(OR(YEAR(A42)=2008, YEAR(A42)=2009), "", H42) -> -0.072272996 | J42: =IF(OR(YEAR(A42)=2008, YEAR(A42)=2009), "", B42) -> -0.033641716
A43: =Data!A43 -> 39262 | B43: =Data!D43 - Factors!AB45 -> -0.053664388 | C43: =Factors!G45 -> -0.013968546 | D43: =Factors!I45 -> 3.5466972e-05 | G43: {=TREND(B7:B42, C7:D42, C43:D43, TRUE)} -> 0.0070863447 | H43: =B43 - G43 -> -0.060750733 | I43: =IF(OR(YEAR(A43)=2008, YEAR(A43)=2009), "", H43) -> -0.060750733 | J43: =IF(OR(YEAR(A43)=2008, YEAR(A43)=2009), "", B43) -> -0.053664388
A44: =Data!A44 -> 39294 | B44: =Data!D44 - Factors!AB46 -> 0.011986669 | C44: =Factors!G46 -> 0.020751214 | D44: =Factors!I46 -> -0.008822996 | G44: {=TREND(B8:B43, C8:D43, C44:D44, TRUE)} -> 0.017595087 | H44: =B44 - G44 -> -0.0056084184 | I44: =IF(OR(YEAR(A44)=2008, YEAR(A44)=2009), "", H44) -> -0.0056084184 | J44: =IF(OR(YEAR(A44)=2008, YEAR(A44)=2009), "", B44) -> 0.011986669
A45: =Data!A45 -> 39325 | B45: =Data!D45 - Factors!AB47 -> -0.079842709 | C45: =Factors!G47 -> -0.036310313 | D45: =Factors!I47 -> -0.016983801 | G45: {=TREND(B9:B44, C9:D44, C45:D45, TRUE)} -> -0.027363566 | H45: =B45 - G45 -> -0.052479143 | I45: =IF(OR(YEAR(A45)=2008, YEAR(A45)=2009), "", H45) -> -0.052479143 | J45: =IF(OR(YEAR(A45)=2008, YEAR(A45)=2009), "", B45) -> -0.079842709
A46: =Data!A46 -> 39353 | B46: =Data!D46 - Factors!AB48 -> 0.025286253 | C46: =Factors!G48 -> 0.080045742 | D46: =Factors!I48 -> 0.015478596 | G46: {=TREND(B10:B45, C10:D45, C46:D46, TRUE)} -> 0.079033867 | H46: =B46 - G46 -> -0.053747614 | I46: =IF(OR(YEAR(A46)=2008, YEAR(A46)=2009), "", H46) -> -0.053747614 | J46: =IF(OR(YEAR(A46)=2008, YEAR(A46)=2009), "", B46) -> 0.025286253
A47: =Data!A47 -> 39386 | B47: =Data!D47 - Factors!AB49 -> -0.021165602 | C47: =Factors!G49 -> 0.03333649 | D47: =Factors!I49 -> 0.022589973 | G47: {=TREND(B11:B46, C11:D46, C47:D47, TRUE)} -> 0.052404797 | H47: =B47 - G47 -> -0.073570399 | I47: =IF(OR(YEAR(A47)=2008, YEAR(A47)=2009), "", H47) -> -0.073570399 | J47: =IF(OR(YEAR(A47)=2008, YEAR(A47)=2009), "", B47) -> -0.021165602
A48: =Data!A48 -> 39416 | B48: =Data!D48 - Factors!AB50 -> -0.079259555 | C48: =Factors!G50 -> -0.031361333 | D48: =Factors!I50 -> -0.025234799 | G48: {=TREND(B12:B47, C12:D47, C48:D48, TRUE)} -> -0.036438112 | H48: =B48 - G48 -> -0.042821443 | I48: =IF(OR(YEAR(A48)=2008, YEAR(A48)=2009), "", H48) -> -0.042821443 | J48: =IF(OR(YEAR(A48)=2008, YEAR(A48)=2009), "", B48) -> -0.079259555
A49: =Data!A49 -> 39447 | B49: =Data!D49 - Factors!AB51 -> -0.048411691 | C49: =Factors!G51 -> 0.046323291 | D49: =Factors!I51 -> -0.0026816448 | G49: {=TREND(B13:B48, C13:D48, C49:D49, TRUE)} -> 0.024882393 | H49: =B49 - G49 -> -0.073294085 | I49: =IF(OR(YEAR(A49)=2008, YEAR(A49)=2009), "", H49) -> -0.073294085 | J49: =IF(OR(YEAR(A49)=2008, YEAR(A49)=2009), "", B49) -> -0.048411691
... A121: =Data!A121 -> 41639 | B121: =Data!D121 - Factors!AB123 -> 0.048886454 | C121: =Factors!G123 -> 0.01239895 | D121: =Factors!I123 -> 0.011934679 | G121: {=TREND(B85:B120, C85:D120, C121:D121, TRUE)} -> 0.014733294 | H121: =B121 - G121 -> 0.034153159 | I121: =IF(OR(YEAR(A121)=2008, YEAR(A121)=2009), "", H121) -> 0.034153159 | J121: =IF(OR(YEAR(A121)=2008, YEAR(A121)=2009), "", B121) -> 0.048886454

Sheet A4_1
A1: Date | B1: xAsset4 | C1: Gold | D1: HF FOF Div | E1: HF FOF Div - Relative Value HF | F1: US Tbill 1-3yr | H1: Predicted | I1: Residual | J1: Resid_ex0809 | K1: xAsset_ex0809
A2: =Data!A2 -> 38016 | B2: =Data!E2 - Factors!AB4 -> 0.0057286923 | C2: =Factors!Z4 -> -0.031291371 | D2: =Factors!J4 -> 0.01538002 | E2: =Factors!J4 - Factors!K4 -> 0.0032700206 | F2: =Factors!C4 -> 0.0021072108
A3: =Data!A3 -> 38044 | B3: =Data!E3 - Factors!AB5 -> 0.019259224 | C3: =Factors!Z5 -> -0.015654119 | D3: =Factors!J5 -> 0.010909983 | E3: =Factors!J5 - Factors!K5 -> 0.0054099752 | F3: =Factors!C5 -> 0.0050261565
A4: =Data!A4 -> 38077 | B4: =Data!E4 - Factors!AB6 -> 0.010438909 | C4: =Factors!Z6 -> 0.076486179 | D4: =Factors!J6 -> 0.0044400219 | E4: =Factors!J6 - Factors!K6 -> 0.00011003248 | F4: =Factors!C6 -> 0.0032149418
A5: =Data!A5 -> 38107 | B5: =Data!E5 - Factors!AB7 -> -0.029190464 | C5: =Factors!Z7 -> -0.093094149 | D5: =Factors!J7 -> -0.0070900013 | E5: =Factors!J7 - Factors!K7 -> -0.0020300026 | F5: =Factors!C7 -> -0.010071723 | H5: SUMMARY OUTPUT
A6: =Data!A6 -> 38138 | B6: =Data!E6 - Factors!AB8 -> -0.0077398376 | C6: =Factors!Z8 -> 0.022753717 | D6: =Factors!J8 -> -0.008780017 | E6: =Factors!J8 - Factors!K8 -> -0.0053300232 | F6: =Factors!C8 -> -0.0011304661
A7: =Data!A7 -> 38168 | B7: =Data!E7 - Factors!AB9 -> -0.001767805 | C7: =Factors!Z9 -> -0.003286563 | D7: =Factors!J9 -> 0.0036000126 | E7: =Factors!J9 - Factors!K9 -> 0.0019900115 | F7: =Factors!C9 -> -0.00010288595 | H7: Regression Statistics
A8: =Data!A8 -> 38198 | B8: =Data!E8 - Factors!AB10 -> -0.0042606936 | C8: =Factors!Z10 -> -0.0081166772 | D8: =Factors!J10 -> -0.0056499986 | E8: =Factors!J10 - Factors!K10 -> -0.012169985 | F8: =Factors!C10 -> 0.0036528271 | H8: Multiple R | I8: 0.79980604
A9: =Data!A9 -> 38230 | B9: =Data!E9 - Factors!AB11 -> -0.0034209799 | C9: =Factors!Z11 -> 0.048075694 | D9: =Factors!J11 -> -9.0006463e-05 | E9: =Factors!J11 - Factors!K11 -> -0.0083400215 | F9: =Factors!C11 -> 0.0071252819 | H9: R Square | I9: 0.6396897
A10: =Data!A10 -> 38260 | B10: =Data!E10 - Factors!AB12 -> 0.0071391284 | C10: =Factors!Z12 -> 0.020495303 | D10: =Factors!J12 -> 0.0082399999 | E10: =Factors!J12 - Factors!K12 -> 0.0046800139 | F10: =Factors!C12 -> -0.0008143737 | H10: Adjusted R Square | I10: 0.62715717
A11: =Data!A11 -> 38289 | B11: =Data!E11 - Factors!AB13 -> 0.0071705913 | C11: =Factors!Z13 -> 0.02462642 | D11: =Factors!J13 -> 0.0077799954 | E11: =Factors!J13 - Factors!K13 -> 0.0046699963 | F11: =Factors!C13 -> 0.0031582701 | H11: Standard Error | I11: 0.0084699221
A12: =Data!A12 -> 38321 | B12: =Data!E12 - Factors!AB14 -> 0.026660861 | C12: =Factors!Z14 -> 0.05226928 | D12: =Factors!J14 -> 0.026389991 | E12: =Factors!J14 - Factors!K14 -> 0.015719984 | F12: =Factors!C14 -> -0.0051287259 | H12: Observations | I12: 120
A13: =Data!A13 -> 38352 | B13: =Data!E13 - Factors!AB15 -> 0.0041299613 | C13: =Factors!Z15 -> -0.027719259 | D13: =Factors!J15 -> 0.01505 | E13: =Factors!J15 - Factors!K15 -> 0.0075899936 | F13: =Factors!C15 -> 0.0021437321
A14: =Data!A14 -> 38383 | B14: =Data!E14 - Factors!AB16 -> -0.0074455305 | C14: =Factors!Z16 -> -0.036150074 | D14: =Factors!J16 -> 0.00017001186 | E14: =Factors!J16 - Factors!K16 -> -0.0028399794 | F14: =Factors!C16 -> -0.00040745645 | H14: ANOVA
A15: =Data!A15 -> 38411 | B15: =Data!E15 - Factors!AB17 -> 0.016437411 | C15: =Factors!Z17 -> 0.030880265 | D15: =Factors!J17 -> 0.014190009 | E15: =Factors!J17 - Factors!K17 -> 0.0063600111 | F15: =Factors!C17 -> -0.0024457352 | I15: df | J15: SS | K15: MS | L15: F | M15: Significance F
A16: =Data!A16 -> 38442 | B16: =Data!E16 - Factors!AB18 -> -0.0082899575 | C16: =Factors!Z18 -> -0.016756571 | D16: =Factors!J18 -> -0.0051600137 | E16: =Factors!J18 - Factors!K18 -> -0.001660021 | F16: =Factors!C18 -> -5.107774e-05 | H16: Regression | I16: 4 | J16: 0.014647023 | K16: 0.0036617557 | L16: 51.042336 | M16: 1.2195381e-24
A17: =Data!A17 -> 38471 | B17: =Data!E17 - Factors!AB19 -> -0.012824908 | C17: =Factors!Z19 -> 0.014100619 | D17: =Factors!J19 -> -0.015129993 | E17: =Factors!J19 - Factors!K19 -> -0.0066899933 | F17: =Factors!C19 -> 0.0058231598 | H17: Residual | I17: 115 | J17: 0.0082500518 | K17: 7.1739581e-05
A18: =Data!A18 -> 38503 | B18: =Data!E18 - Factors!AB20 -> 0.0010608022 | C18: =Factors!Z20 -> -0.03945763 | D18: =Factors!J20 -> 0.0021699912 | E18: =Factors!J20 - Factors!K20 -> 0.0032099952 | F18: =Factors!C20 -> 0.0038088467 | H18: Total | I18: 119 | J18: 0.022897075
A19: =Data!A19 -> 38533 | B19: =Data!E19 - Factors!AB21 -> 0.0082856709 | C19: =Factors!Z21 -> 0.043738766 | D19: =Factors!J21 -> 0.013040001 | E19: =Factors!J21 - Factors!K21 -> 0.003449991 | F19: =Factors!C21 -> 0.0018719012
A20: =Data!A20 -> 38562 | B20: =Data!E20 - Factors!AB22 -> 0.0049724202 | C20: =Factors!Z22 -> -0.013088404 | D20: =Factors!J22 -> 0.018030012 | E20: =Factors!J22 - Factors!K22 -> 0.0046300243 | F20: =Factors!C22 -> -0.0029793466 | I20: Coefficients | J20: Standard Error | K20: t Stat | L20: P-value | M20: Lower 95% | N20: Upper 95% | O20: Lower 95.0% | P20: Upper 95.0%
A21: =Data!A21 -> 38595 | B21: =Data!E21 - Factors!AB23 -> 0.0044625005 | C21: =Factors!Z23 -> 0.012563983 | D21: =Factors!J23 -> 0.0084599894 | E21: =Factors!J23 - Factors!K23 -> 0.0015499908 | F21: =Factors!C23 -> 0.006280389 | H21: Intercept | I21: 0.001082109 | J21: 0.0010025582 | K21: 1.0793479 | L21: 0.28269125 | M21: -0.00090376571 | N21: 0.0030679838 | O21: -0.00090376571 | P21: 0.0030679838
A22: =Data!A22 -> 38625 | B22: =Data!E22 - Factors!AB24 -> 0.018122826 | C22: =Factors!Z24 -> 0.078354779 | D22: =Factors!J24 -> 0.015259997 | E22: =Factors!J24 - Factors!K24 -> 0.0035099833 | F22: =Factors!C24 -> -0.0026676062 | H22: Gold | I22: 0.077160974 | J22: 0.015705229 | K22: 4.9130753 | L22: 2.9975422e-06 | M22: 0.046051937 | N22: 0.10827001 | O22: 0.046051937 | P22: 0.10827001
A23: =Data!A23 -> 38656 | B23: =Data!E23 - Factors!AB25 -> -0.0089936197 | C23: =Factors!Z25 -> -0.0087577243 | D23: =Factors!J25 -> -0.015100003 | E23: =Factors!J25 - Factors!K25 -> -0.011550001 | F23: =Factors!C25 -> -0.00020186727 | H23: HF FOF Div | I23: 0.35815159 | J23: 0.063026208 | K23: 5.6825819 | L23: 1.0179038e-07 | M23: 0.2333088 | N23: 0.48299438 | O23: 0.2333088 | P23: 0.48299438
A24: =Data!A24 -> 38686 | B24: =Data!E24 - Factors!AB26 -> 0.011561723 | C24: =Factors!Z26 -> 0.059953997 | D24: =Factors!J26 -> 0.017020022 | E24: =Factors!J26 - Factors!K26 -> 0.0087800296 | F24: =Factors!C26 -> 0.0032810055 | H24: HF FOF Div - Relative Value HF | I24: 0.75409716 | J24: 0.1100828 | K24: 6.8502725 | L24: 3.8486921e-10 | M24: 0.53604432 | N24: 0.97214999 | O24: 0.53604432 | P24: 0.97214999
A25: =Data!A25 -> 38716 | B25: =Data!E25 - Factors!AB27 -> 0.0095251369 | C25: =Factors!Z27 -> 0.048511398 | D25: =Factors!J27 -> 0.020079989 | E25: =Factors!J27 - Factors!K27 -> 0.0053299862 | F25: =Factors!C27 -> 0.0038740189 | H25: US Tbill 1-3yr | I25: 0.50089528 | J25: 0.21977849 | K25: 2.2790915 | L25: 0.02450671 | M25: 0.065556397 | N25: 0.93623416 | O25: 0.065556397 | P25: 0.93623416
A26: =Data!A26 -> 38748 | B26: =Data!E26 - Factors!AB28 -> 0.020795499 | C26: =Factors!Z28 -> 0.10038685 | D26: =Factors!J28 -> 0.028360008 | E26: =Factors!J28 - Factors!K28 -> 0.0063700025 | F26: =Factors!C28 -> 0.0015035333
A27: =Data!A27 -> 38776 | B27: =Data!E27 - Factors!AB29 -> -0.007924186 | C27: =Factors!Z29 -> -0.01291967 | D27: =Factors!J29 -> 0.003469983 | E27: =Factors!J29 - Factors!K29 -> -0.0027600065 | F27: =Factors!C29 -> 0.00075063804
A28: =Data!A28 -> 38807 | B28: =Data!E28 - Factors!AB30 -> 0.0076372396 | C28: =Factors!Z30 -> 0.039355356 | D28: =Factors!J30 -> 0.016610014 | E28: =Factors!J30 - Factors!K30 -> 0.0032700063 | F28: =Factors!C30 -> 0.00120012
A29: =Data!A29 -> 38835 | B29: =Data!E29 - Factors!AB31 -> 0.023879732 | C29: =Factors!Z31 -> 0.12125418 | D29: =Factors!J31 -> 0.017169992 | E29: =Factors!J31 - Factors!K31 -> 0.0060199914 | F29: =Factors!C31 -> 0.0030965937
A30: =Data!A30 -> 38868 | B30: =Data!E30 - Factors!AB32 -> -0.017616717 | C30: =Factors!Z32 -> -0.014088811 | D30: =Factors!J32 -> -0.019659986 | E30: =Factors!J32 - Factors!K32 -> -0.021699977 | F30: =Factors!C32 -> 0.0014439355 | I30: OOS R Square | J30: =1 - SUMSQ(I38:I121) / DEVSQ(B38:B121) -> 0.47151813
A31: =Data!A31 -> 38898 | B31: =Data!E31 - Factors!AB33 -> -0.0088009587 | C31: =Factors!Z33 -> -0.045489771 | D31: =Factors!J33 -> -0.0062600113 | E31: =Factors!J33 - Factors!K33 -> -0.01178002 | F31: =Factors!C33 -> 0.0017898871 | I31: OOS RMSE | J31: =SQRT( SUMSQ(I38:I121) / COUNT(I38:I121) ) -> 0.010454963
A32: =Data!A32 -> 38929 | B32: =Data!E32 - Factors!AB34 -> -0.0066596944 | C32: =Factors!Z34 -> 0.033936835 | D32: =Factors!J34 -> -0.0022099993 | E32: =Factors!J34 - Factors!K34 -> -0.0063899907 | F32: =Factors!C34 -> 0.0074941684 | I32: ex0809 OOS R^2 | J32: =1 - SUMSQ(J38:J121) / DEVSQ(K38:K121) -> 0.55590003
A33: =Data!A33 -> 38960 | B33: =Data!E33 - Factors!AB35 -> -0.0019510745 | C33: =Factors!Z35 -> -0.014840989 | D33: =Factors!J35 -> 0.0081299984 | E33: =Factors!J35 - Factors!K35 -> 0.0010199931 | F33: =Factors!C35 -> 0.0071428571
A34: =Data!A34 -> 38989 | B34: =Data!E34 - Factors!AB36 -> -0.01196632 | C34: =Factors!Z36 -> -0.046229874 | D34: =Factors!J36 -> 0.00074999312 | E34: =Factors!J36 - Factors!K36 -> -0.0029499988 | F34: =Factors!C36 -> 0.00513573
A35: =Data!A35 -> 39021 | B35: =Data!E35 - Factors!AB37 -> 0.007474341 | C35: =Factors!Z37 -> 0.013872639 | D35: =Factors!J37 -> 0.016250019 | E35: =Factors!J37 - Factors!K37 -> 0.0039800123 | F35: =Factors!C37 -> 0.0038442822
A36: =Data!A36 -> 39051 | B36: =Data!E36 - Factors!AB38 -> 0.019408258 | C36: =Factors!Z38 -> 0.068249258 | D36: =Factors!J38 -> 0.017829984 | E36: =Factors!J38 - Factors!K38 -> 0.0040999812 | F36: =Factors!C38 -> 0.0051383974
A37: =Data!A37 -> 39080 | B37: =Data!E37 - Factors!AB39 -> 0.0083874782 | C37: =Factors!Z39 -> -0.017438272 | D37: =Factors!J39 -> 0.01786001 | E37: =Factors!J39 - Factors!K39 -> 0.001750013 | F37: =Factors!C39 -> 4.8227634e-05 | H37: 36 Month Rolling
A38: =Data!A38 -> 39113 | B38: =Data!E38 - Factors!AB40 -> -0.00040867298 | C38: =Factors!Z40 -> 0.025914874 | D38: =Factors!J40 -> 0.012942254 | E38: =Factors!J40 - Factors!K40 -> -0.00072645543 | F38: =Factors!C40 -> 0.0020736883 | H38: {=TREND(B2:B37, C2:F37, C38:F38, TRUE)} -> 0.0071813153 | I38: =B38 - H38 -> -0.0075899883 | J38: =IF(OR(YEAR(A38)=2008, YEAR(A38)=2009), "", I38) -> -0.0075899883 | K38: =IF(OR(YEAR(A38)=2008, YEAR(A38)=2009), "", B38) -> -0.00040867298
A39: =Data!A39 -> 39141 | B39: =Data!E39 - Factors!AB41 -> -0.0015428829 | C39: =Factors!Z41 -> 0.024724434 | D39: =Factors!J41 -> 0.0081972119 | E39: =Factors!J41 - Factors!K41 -> 0.00063454805 | F39: =Factors!C41 -> 0.0080850859 | H39: {=TREND(B3:B38, C3:F38, C39:F39, TRUE)} -> 0.0058641103 | I39: =B39 - H39 -> -0.0074069932 | J39: =IF(OR(YEAR(A39)=2008, YEAR(A39)=2009), "", I39) -> -0.0074069932 | K39: =IF(OR(YEAR(A39)=2008, YEAR(A39)=2009), "", B39) -> -0.0015428829
A40: =Data!A40 -> 39171 | B40: =Data!E40 - Factors!AB42 -> -0.0053784364 | C40: =Factors!Z42 -> -0.0083065661 | D40: =Factors!J42 -> 0.011549314 | E40: =Factors!J42 - Factors!K42 -> 0.0040145878 | F40: =Factors!C42 -> 0.0038669022 | H40: {=TREND(B4:B39, C4:F39, C40:F40, TRUE)} -> 0.0022150466 | I40: =B40 - H40 -> -0.007593483 | J40: =IF(OR(YEAR(A40)=2008, YEAR(A40)=2009), "", I40) -> -0.007593483 | K40: =IF(OR(YEAR(A40)=2008, YEAR(A40)=2009), "", B40) -> -0.0053784364
A41: =Data!A41 -> 39202 | B41: =Data!E41 - Factors!AB43 -> 0.011976878 | C41: =Factors!Z43 -> 0.022085298 | D41: =Factors!J43 -> 0.016760762 | E41: =Factors!J43 - Factors!K43 -> 0.0025702188 | F41: =Factors!C43 -> 0.0035191174 | H41: {=TREND(B5:B40, C5:F40, C41:F41, TRUE)} -> 0.0079140129 | I41: =B41 - H41 -> 0.0040628656 | J41: =IF(OR(YEAR(A41)=2008, YEAR(A41)=2009), "", I41) -> 0.0040628656 | K41: =IF(OR(YEAR(A41)=2008, YEAR(A41)=2009), "", B41) -> 0.011976878
A42: =Data!A42 -> 39233 | B42: =Data!E42 - Factors!AB44 -> 0.013884227 | C42: =Factors!Z44 -> -0.026457366 | D42: =Factors!J44 -> 0.021465348 | E42: =Factors!J44 - Factors!K44 -> 0.0065919347 | F42: =Factors!C44 -> -0.00099516633 | H42: {=TREND(B6:B41, C6:F41, C42:F42, TRUE)} -> 0.0077778264 | I42: =B42 - H42 -> 0.0061064007 | J42: =IF(OR(YEAR(A42)=2008, YEAR(A42)=2009), "", I42) -> 0.0061064007 | K42: =IF(OR(YEAR(A42)=2008, YEAR(A42)=2009), "", B42) -> 0.013884227
A43: =Data!A43 -> 39262 | B43: =Data!E43 - Factors!AB45 -> 0.011078126 | C43: =Factors!Z45 -> -0.016426949 | D43: =Factors!J45 -> 0.0052586549 | E43: =Factors!J45 - Factors!K45 -> -0.00036297875 | F43: =Factors!C45 -> 0.0043641193 | H43: {=TREND(B7:B42, C7:F42, C43:F43, TRUE)} -> -0.0029899225 | I43: =B43 - H43 -> 0.014068049 | J43: =IF(OR(YEAR(A43)=2008, YEAR(A43)=2009), "", I43) -> 0.014068049 | K43: =IF(OR(YEAR(A43)=2008, YEAR(A43)=2009), "", B43) -> 0.011078126
A44: =Data!A44 -> 39294 | B44: =Data!E44 - Factors!AB46 -> 0.0041229099 | C44: =Factors!Z46 -> 0.022550604 | D44: =Factors!J46 -> 0.0019128344 | E44: =Factors!J46 - Factors!K46 -> 0.0077167155 | F44: =Factors!C46 -> 0.0089264629 | H44: {=TREND(B8:B43, C8:F43, C44:F44, TRUE)} -> 0.00054125292 | I44: =B44 - H44 -> 0.003581657 | J44: =IF(OR(YEAR(A44)=2008, YEAR(A44)=2009), "", I44) -> 0.003581657 | K44: =IF(OR(YEAR(A44)=2008, YEAR(A44)=2009), "", B44) -> 0.0041229099
A45: =Data!A45 -> 39325 | B45: =Data!E45 - Factors!AB47 -> -0.026040932 | C45: =Factors!Z47 -> 0.013548096 | D45: =Factors!J47 -> -0.021834293 | E45: =Factors!J47 - Factors!K47 -> -0.014952908 | F45: =Factors!C47 -> 0.010392285 | H45: {=TREND(B9:B44, C9:F44, C45:F45, TRUE)} -> -0.019013852 | I45: =B45 - H45 -> -0.0070270805 | J45: =IF(OR(YEAR(A45)=2008, YEAR(A45)=2009), "", I45) -> -0.0070270805 | K45: =IF(OR(YEAR(A45)=2008, YEAR(A45)=2009), "", B45) -> -0.026040932
A46: =Data!A46 -> 39353 | B46: =Data!E46 - Factors!AB48 -> 0.028787166 | C46: =Factors!Z48 -> 0.10441111 | D46: =Factors!J48 -> 0.018790038 | E46: =Factors!J48 - Factors!K48 -> 0.0052881996 | F46: =Factors!C48 -> 0.0069495923 | H46: {=TREND(B10:B45, C10:F45, C46:F46, TRUE)} -> 0.015861564 | I46: =B46 - H46 -> 0.012925601 | J46: =IF(OR(YEAR(A46)=2008, YEAR(A46)=2009), "", I46) -> 0.012925601 | K46: =IF(OR(YEAR(A46)=2008, YEAR(A46)=2009), "", B46) -> 0.028787166
A47: =Data!A47 -> 39386 | B47: =Data!E47 - Factors!AB49 -> 0.029567013 | C47: =Factors!Z49 -> 0.071543841 | D47: =Factors!J49 -> 0.030656165 | E47: =Factors!J49 - Factors!K49 -> 0.0096536196 | F47: =Factors!C49 -> 0.003910923 | H47: {=TREND(B11:B46, C11:F46, C47:F47, TRUE)} -> 0.023020104 | I47: =B47 - H47 -> 0.0065469086 | J47: =IF(OR(YEAR(A47)=2008, YEAR(A47)=2009), "", I47) -> 0.0065469086 | K47: =IF(OR(YEAR(A47)=2008, YEAR(A47)=2009), "", B47) -> 0.029567013
A48: =Data!A48 -> 39416 | B48: =Data!E48 - Factors!AB50 -> -0.012781413 | C48: =Factors!Z50 -> -0.016629016 | D48: =Factors!J50 -> -0.014675704 | E48: =Factors!J50 - Factors!K50 -> -0.0093557817 | F48: =Factors!C50 -> 0.01732435 | H48: {=TREND(B12:B47, C12:F47, C48:F48, TRUE)} -> -0.020956972 | I48: =B48 - H48 -> 0.0081755592 | J48: =IF(OR(YEAR(A48)=2008, YEAR(A48)=2009), "", I48) -> 0.0081755592 | K48: =IF(OR(YEAR(A48)=2008, YEAR(A48)=2009), "", B48) -> -0.012781413
A49: =Data!A49 -> 39447 | B49: =Data!E49 - Factors!AB51 -> 0.0070711374 | C49: =Factors!Z51 -> 0.064003573 | D49: =Factors!J51 -> 0.0033379196 | E49: =Factors!J51 - Factors!K51 -> -0.0030985504 | F49: =Factors!C51 -> 0.0024778123 | H49: {=TREND(B13:B48, C13:F48, C49:F49, TRUE)} -> 0.0054134567 | I49: =B49 - H49 -> 0.0016576807 | J49: =IF(OR(YEAR(A49)=2008, YEAR(A49)=2009), "", I49) -> 0.0016576807 | K49: =IF(OR(YEAR(A49)=2008, YEAR(A49)=2009), "", B49) -> 0.0070711374
... A121: =Data!A121 -> 41639 | B121: =Data!E121 - Factors!AB123 -> 0.0046525741 | C121: =Factors!Z123 -> -0.04125743 | D121: =Factors!J123 -> 0.015226749 | E121: =Factors!J123 - Factors!K123 -> 0.0075417591 | F121: =Factors!C123 -> -0.0013934785 | H121: {=TREND(B85:B120, C85:F120, C121:F121, TRUE)} -> 0.012451591 | I121: =B121 - H121 -> -0.0077990168 | J121: =IF(OR(YEAR(A121)=2008, YEAR(A121)=2009), "", I121) -> -0.0077990168 | K121: =IF(OR(YEAR(A121)=2008, YEAR(A121)=2009), "", B121) -> 0.0046525741

Sheet A5_2factor
A1: Date | B1: xAsset5 | C1: TIPs | D1: Relative Value HF | G1: Predicted | H1: Residual | I1: Resid_ex0809 | J1: xAsset_ex0809
A2: =Data!A2 -> 38016 | B2: =Data!F2 - Factors!AB4 -> 0.011096091 | C2: =Factors!M4 -> 0.012326082 | D2: =Factors!K4 -> 0.012109999
A3: =Data!A3 -> 38044 | B3: =Data!F3 - Factors!AB5 -> 0.023027653 | C3: =Factors!M5 -> 0.024775375 | D3: =Factors!K5 -> 0.0055000077
A4: =Data!A4 -> 38077 | B4: =Data!F4 - Factors!AB6 -> 0.015724601 | C4: =Factors!M6 -> 0.017390173 | D4: =Factors!K6 -> 0.0043299894
A5: =Data!A5 -> 38107 | B5: =Data!F5 - Factors!AB7 -> -0.044654521 | C5: =Factors!M7 -> -0.046496063 | D5: =Factors!K7 -> -0.0050599988 | F5: SUMMARY OUTPUT
A6: =Data!A6 -> 38138 | B6: =Data!F6 - Factors!AB8 -> 0.014467795 | C6: =Factors!M8 -> 0.016443736 | D6: =Factors!K8 -> -0.0034499938
A7: =Data!A7 -> 38168 | B7: =Data!F7 - Factors!AB9 -> -0.0020867511 | C7: =Factors!M9 -> -0.0026148152 | D7: =Factors!K9 -> 0.0016100011 | F7: Regression Statistics
A8: =Data!A8 -> 38198 | B8: =Data!F8 - Factors!AB10 -> 0.013772822 | C8: =Factors!M10 -> 0.016134553 | D8: =Factors!K10 -> 0.0065199865 | F8: Multiple R | G8: 0.97476728
A9: =Data!A9 -> 38230 | B9: =Data!F9 - Factors!AB11 -> 0.022482399 | C9: =Factors!M11 -> 0.025976512 | D9: =Factors!K11 -> 0.0082500151 | F9: R Square | G9: 0.95017125
A10: =Data!A10 -> 38260 | B10: =Data!F10 - Factors!AB12 -> 0.0010415318 | C10: =Factors!M12 -> 0.0015744976 | D10: =Factors!K12 -> 0.003559986 | F10: Adjusted R Square | G10: 0.94931947
A11: =Data!A11 -> 38289 | B11: =Data!F11 - Factors!AB13 -> 0.012832717 | C11: =Factors!M13 -> 0.014200355 | D11: =Factors!K13 -> 0.0031099991 | F11: Standard Error | G11: 0.0046484059
A12: =Data!A12 -> 38321 | B12: =Data!F12 - Factors!AB14 -> -0.0059628895 | C12: =Factors!M14 -> -0.0070595322 | D12: =Factors!K14 -> 0.010670007 | F12: Observations | G12: 120
A13: =Data!A13 -> 38352 | B13: =Data!F13 - Factors!AB15 -> 0.010277841 | C13: =Factors!M15 -> 0.013768153 | D13: =Factors!K15 -> 0.0074600062
A14: =Data!A14 -> 38383 | B14: =Data!F14 - Factors!AB16 -> 0.00064688463 | C14: =Factors!M16 -> 0.0054076539 | D14: =Factors!K16 -> 0.0030099913 | F14: ANOVA
A15: =Data!A15 -> 38411 | B15: =Data!F15 - Factors!AB17 -> -0.0074695158 | C15: =Factors!M17 -> -0.0071714246 | D15: =Factors!K17 -> 0.0078299976 | G15: df | H15: SS | I15: MS | J15: F | K15: Significance F
A16: =Data!A16 -> 38442 | B16: =Data!F16 - Factors!AB18 -> -0.0051539433 | C16: =Factors!M18 -> -0.0044377509 | D16: =Factors!K18 -> -0.0034999927 | F16: Regression | G16: 2 | H16: 0.048207634 | I16: 0.024103817 | J16: 1115.521 | K16: 6.3471787e-77
A17: =Data!A17 -> 38471 | B17: =Data!F17 - Factors!AB19 -> 0.019528423 | C17: =Factors!M19 -> 0.025283828 | D17: =Factors!K19 -> -0.0084399998 | F17: Residual | G17: 117 | H17: 0.0025280982 | I17: 2.1607677e-05
A18: =Data!A18 -> 38503 | B18: =Data!F18 - Factors!AB20 -> 0.0032890235 | C18: =Factors!M20 -> 0.0069189282 | D18: =Factors!K20 -> -0.001040004 | F18: Total | G18: 119 | H18: 0.050735732
A19: =Data!A19 -> 38533 | B19: =Data!F19 - Factors!AB21 -> 0.00085154205 | C19: =Factors!M21 -> 0.0036562031 | D19: =Factors!K21 -> 0.00959001
A20: =Data!A20 -> 38562 | B20: =Data!F20 - Factors!AB22 -> -0.019395522 | C20: =Factors!M22 -> -0.018193158 | D20: =Factors!K22 -> 0.013399988 | G20: Coefficients | H20: Standard Error | I20: t Stat | J20: P-value | K20: Lower 95% | L20: Upper 95% | M20: Lower 95.0% | N20: Upper 95.0%
A21: =Data!A21 -> 38595 | B21: =Data!F21 - Factors!AB23 -> 0.019822141 | C21: =Factors!M23 -> 0.024976539 | D21: =Factors!K23 -> 0.0069099986 | F21: Intercept | G21: -0.0017882792 | H21: 0.0004570054 | I21: -3.9130375 | J21: 0.00015349522 | K21: -0.0026933545 | L21: -0.000883204 | M21: -0.0026933545 | N21: -0.000883204
A22: =Data!A22 -> 38625 | B22: =Data!F22 - Factors!AB24 -> -0.0063266938 | C22: =Factors!M24 -> -0.0052538911 | D22: =Factors!K24 -> 0.011750014 | F22: TIPs | G22: 0.93058959 | H22: 0.020662736 | I22: 45.037095 | J22: 9.4457651e-76 | K22: 0.88966812 | L22: 0.97151105 | M22: 0.88966812 | N22: 0.97151105
A23: =Data!A23 -> 38656 | B23: =Data!F23 - Factors!AB25 -> -0.014666621 | C23: =Factors!M25 -> -0.012573985 | D23: =Factors!K25 -> -0.003550002 | F23: Relative Value HF | G23: 0.15185938 | H23: 0.030359997 | I23: 5.0019564 | J23: 2.0173861e-06 | K23: 0.091733 | L23: 0.21198577 | M23: 0.091733 | N23: 0.21198577
A24: =Data!A24 -> 38686 | B24: =Data!F24 - Factors!AB26 -> -0.0015948266 | C24: =Factors!M26 -> 0.0019717785 | D24: =Factors!K26 -> 0.0082399924
A25: =Data!A25 -> 38716 | B25: =Data!F25 - Factors!AB27 -> 0.0045252174 | C25: =Factors!M27 -> 0.0084798523 | D25: =Factors!K27 -> 0.014750003
A26: =Data!A26 -> 38748 | B26: =Data!F26 - Factors!AB28 -> -0.0021828452 | C26: =Factors!M28 -> 0.00078054042 | D26: =Factors!K28 -> 0.021990006
A27: =Data!A27 -> 38776 | B27: =Data!F27 - Factors!AB29 -> -0.0061157804 | C27: =Factors!M29 -> -0.0034033381 | D27: =Factors!K29 -> 0.0062299896
A28: =Data!A28 -> 38807 | B28: =Data!F28 - Factors!AB30 -> -0.02057989 | C28: =Factors!M30 -> -0.020532449 | D28: =Factors!K30 -> 0.013340008
A29: =Data!A29 -> 38835 | B29: =Data!F29 - Factors!AB31 -> -0.0012021032 | C29: =Factors!M31 -> 0.00010169098 | D29: =Factors!K31 -> 0.011150001 | H29: OOS R Square | I29: =1 - SUMSQ(H38:H121) / DEVSQ(B38:B121) -> 0.92902608
A30: =Data!A30 -> 38868 | B30: =Data!F30 - Factors!AB32 -> -0.0017257024 | C30: =Factors!M32 -> 0.0021352933 | D30: =Factors!K32 -> 0.0020399909 | H30: OOS RMSE | I30: =SQRT( SUMSQ(H38:H121) / COUNT(H38:H121) ) -> 0.0060480921
A31: =Data!A31 -> 38898 | B31: =Data!F31 - Factors!AB33 -> 0.00015052875 | C31: =Factors!M33 -> 0.0035947239 | D31: =Factors!K33 -> 0.0055200083 | H31: ex0809 OOS R^2 | I31: =1 - SUMSQ(I38:I121) / DEVSQ(J38:J121) -> 0.98255939
A32: =Data!A32 -> 38929 | B32: =Data!F32 - Factors!AB34 -> 0.010643188 | C32: =Factors!M34 -> 0.016696034 | D32: =Factors!K34 -> 0.0041799914
A33: =Data!A33 -> 38960 | B33: =Data!F33 - Factors!AB35 -> 0.011870238 | C33: =Factors!M35 -> 0.018765804 | D33: =Factors!K35 -> 0.0071100053
A34: =Data!A34 -> 38989 | B34: =Data!F34 - Factors!AB36 -> -0.0012218407 | C34: =Factors!M36 -> 0.0025169072 | D34: =Factors!K36 -> 0.0036999919
A35: =Data!A35 -> 39021 | B35: =Data!F35 - Factors!AB37 -> -0.0060934197 | C35: =Factors!M37 -> -0.0015995438 | D35: =Factors!K37 -> 0.012270006
A36: =Data!A36 -> 39051 | B36: =Data!F36 - Factors!AB38 -> 0.0071053827 | C36: =Factors!M38 -> 0.012412842 | D36: =Factors!K38 -> 0.013730003
A37: =Data!A37 -> 39080 | B37: =Data!F37 - Factors!AB39 -> -0.026965697 | C37: =Factors!M39 -> -0.024954762 | D37: =Factors!K39 -> 0.016109996 | G37: 36 Month Rolling
A38: =Data!A38 -> 39113 | B38: =Data!F38 - Factors!AB40 -> -0.0014838815 | C38: =Factors!M40 -> 0.0023074318 | D38: =Factors!K40 -> 0.01366871 | G38: {=TREND(B2:B37, C2:D37, C38:D38, TRUE)} -> -0.00034382345 | H38: =B38 - G38 -> -0.001140058 | I38: =IF(OR(YEAR(A38)=2008, YEAR(A38)=2009), "", H38) -> -0.001140058 | J38: =IF(OR(YEAR(A38)=2008, YEAR(A38)=2009), "", B38) -> -0.0014838815
A39: =Data!A39 -> 39141 | B39: =Data!F39 - Factors!AB41 -> 0.017089466 | C39: =Factors!M41 -> 0.022753673 | D39: =Factors!K41 -> 0.0075626638 | G39: {=TREND(B3:B38, C3:D38, C39:D39, TRUE)} -> 0.018410325 | H39: =B39 - G39 -> -0.0013208589 | I39: =IF(OR(YEAR(A39)=2008, YEAR(A39)=2009), "", H39) -> -0.0013208589 | J39: =IF(OR(YEAR(A39)=2008, YEAR(A39)=2009), "", B39) -> 0.017089466
A40: =Data!A40 -> 39171 | B40: =Data!F40 - Factors!AB42 -> 0.00034742056 | C40: =Factors!M42 -> 0.0030425056 | D40: =Factors!K42 -> 0.0075347265 | G40: {=TREND(B4:B39, C4:D39, C40:D40, TRUE)} -> 0.00026072937 | H40: =B40 - G40 -> 8.6691195e-05 | I40: =IF(OR(YEAR(A40)=2008, YEAR(A40)=2009), "", H40) -> 8.6691195e-05 | J40: =IF(OR(YEAR(A40)=2008, YEAR(A40)=2009), "", B40) -> 0.00034742056
A41: =Data!A41 -> 39202 | B41: =Data!F41 - Factors!AB43 -> 0.0036137696 | C41: =Factors!M43 -> 0.0078096584 | D41: =Factors!K43 -> 0.014190543 | G41: {=TREND(B5:B40, C5:D40, C41:D41, TRUE)} -> 0.0042441416 | H41: =B41 - G41 -> -0.00063037192 | I41: =IF(OR(YEAR(A41)=2008, YEAR(A41)=2009), "", H41) -> -0.00063037192 | J41: =IF(OR(YEAR(A41)=2008, YEAR(A41)=2009), "", B41) -> 0.0036137696
A42: =Data!A42 -> 39233 | B42: =Data!F42 - Factors!AB44 -> -0.018720259 | C42: =Factors!M44 -> -0.016758027 | D42: =Factors!K44 -> 0.014873413 | G42: {=TREND(B6:B41, C6:D41, C42:D42, TRUE)} -> -0.017823461 | H42: =B42 - G42 -> -0.00089679804 | I42: =IF(OR(YEAR(A42)=2008, YEAR(A42)=2009), "", H42) -> -0.00089679804 | J42: =IF(OR(YEAR(A42)=2008, YEAR(A42)=2009), "", B42) -> -0.018720259
A43: =Data!A43 -> 39262 | B43: =Data!F43 - Factors!AB45 -> -0.0056159441 | C43: =Factors!M45 -> -0.0023823705 | D43: =Factors!K45 -> 0.0056216336 | G43: {=TREND(B7:B42, C7:D42, C43:D43, TRUE)} -> -0.0046274815 | H43: =B43 - G43 -> -0.00098846254 | I43: =IF(OR(YEAR(A43)=2008, YEAR(A43)=2009), "", H43) -> -0.00098846254 | J43: =IF(OR(YEAR(A43)=2008, YEAR(A43)=2009), "", B43) -> -0.0056159441
A44: =Data!A44 -> 39294 | B44: =Data!F44 - Factors!AB46 -> 0.019022065 | C44: =Factors!M46 -> 0.023700104 | D44: =Factors!K46 -> -0.0058038811 | G44: {=TREND(B8:B43, C8:D43, C44:D44, TRUE)} -> 0.018906546 | H44: =B44 - G44 -> 0.00011551881 | I44: =IF(OR(YEAR(A44)=2008, YEAR(A44)=2009), "", H44) -> 0.00011551881 | J44: =IF(OR(YEAR(A44)=2008, YEAR(A44)=2009), "", B44) -> 0.019022065
A45: =Data!A45 -> 39325 | B45: =Data!F45 - Factors!AB47 -> 0.0052633422 | C45: =Factors!M47 -> 0.01334563 | D45: =Factors!K47 -> -0.006881385 | G45: {=TREND(B9:B44, C9:D44, C45:D45, TRUE)} -> 0.0095827854 | H45: =B45 - G45 -> -0.0043194433 | I45: =IF(OR(YEAR(A45)=2008, YEAR(A45)=2009), "", H45) -> -0.0043194433 | J45: =IF(OR(YEAR(A45)=2008, YEAR(A45)=2009), "", B45) -> 0.0052633422
A46: =Data!A46 -> 39353 | B46: =Data!F46 - Factors!AB48 -> 0.0065596174 | C46: =Factors!M48 -> 0.0088736014 | D46: =Factors!K48 -> 0.013501838 | G46: {=TREND(B10:B45, C10:D45, C46:D46, TRUE)} -> 0.0049569508 | H46: =B46 - G46 -> 0.0016026665 | I46: =IF(OR(YEAR(A46)=2008, YEAR(A46)=2009), "", H46) -> 0.0016026665 | J46: =IF(OR(YEAR(A46)=2008, YEAR(A46)=2009), "", B46) -> 0.0065596174
A47: =Data!A47 -> 39386 | B47: =Data!F47 - Factors!AB49 -> 0.011182572 | C47: =Factors!M49 -> 0.013770414 | D47: =Factors!K49 -> 0.021002545 | G47: {=TREND(B11:B46, C11:D46, C47:D47, TRUE)} -> 0.0095176972 | H47: =B47 - G47 -> 0.001664875 | I47: =IF(OR(YEAR(A47)=2008, YEAR(A47)=2009), "", H47) -> 0.001664875 | J47: =IF(OR(YEAR(A47)=2008, YEAR(A47)=2009), "", B47) -> 0.011182572
A48: =Data!A48 -> 39416 | B48: =Data!F48 - Factors!AB50 -> 0.040146906 | C48: =Factors!M50 -> 0.046900559 | D48: =Factors!K50 -> -0.0053199226 | G48: {=TREND(B12:B47, C12:D47, C48:D48, TRUE)} -> 0.038364265 | H48: =B48 - G48 -> 0.0017826409 | I48: =IF(OR(YEAR(A48)=2008, YEAR(A48)=2009), "", H48) -> 0.0017826409 | J48: =IF(OR(YEAR(A48)=2008, YEAR(A48)=2009), "", B48) -> 0.040146906
A49: =Data!A49 -> 39447 | B49: =Data!F49 - Factors!AB51 -> -0.0047841932 | C49: =Factors!M51 -> -0.0046936913 | D49: =Factors!K51 -> 0.00643647 | G49: {=TREND(B13:B48, C13:D48, C49:D49, TRUE)} -> -0.0073494183 | H49: =B49 - G49 -> 0.0025652251 | I49: =IF(OR(YEAR(A49)=2008, YEAR(A49)=2009), "", H49) -> 0.0025652251 | J49: =IF(OR(YEAR(A49)=2008, YEAR(A49)=2009), "", B49) -> -0.0047841932
... A121: =Data!A121 -> 41639 | B121: =Data!F121 - Factors!AB123 -> -0.020900099 | C121: =Factors!M123 -> -0.020891371 | D121: =Factors!K123 -> 0.0076849904 | G121: {=TREND(B85:B120, C85:D120, C121:D121, TRUE)} -> -0.018261872 | H121: =B121 - G121 -> -0.0026382275 | I121: =IF(OR(YEAR(A121)=2008, YEAR(A121)=2009), "", H121) -> -0.0026382275 | J121: =IF(OR(YEAR(A121)=2008, YEAR(A121)=2009), "", B121) -> -0.020900099

Sheet A4_2
A1: Date | B1: xAsset4 | C1: Gold | D1: HF FOF Div | E1: HF FOF Div - Relative Value HF | F1: Long Short HF - S&P500 | H1: Predicted | I1: Residual | J1: Resid_ex0809 | K1: xAsset_ex0809 | M1: Factor | N1: R^2 aux | O1: VIF
A2: =Data!A2 -> 38016 | B2: =Data!E2 - Factors!AB4 -> 0.0057286923 | C2: =Factors!Z4 -> -0.031291371 | D2: =Factors!J4 -> 0.01538002 | E2: =Factors!J4 - Factors!K4 -> 0.0032700206 | F2: =Factors!H4 - Factors!AA4 -> 0.0011450297 | M2: Gold | N2: =INDEX(LINEST(C2:C121, D2:F121, TRUE, TRUE), 3, 1) -> 0.091420223 | O2: =1/(1-N2) -> 1.1006188
A3: =Data!A3 -> 38044 | B3: =Data!E3 - Factors!AB5 -> 0.019259224 | C3: =Factors!Z5 -> -0.015654119 | D3: =Factors!J5 -> 0.010909983 | E3: =Factors!J5 - Factors!K5 -> 0.0054099752 | F3: =Factors!H5 - Factors!AA5 -> -0.002799445 | M3: HF FOF Div | N3: =INDEX(LINEST(D2:D121, CHOOSE({1,2}, C2:C121, E2:F121), TRUE, TRUE), 3, 1) -> 0.12563652 | O3: =1/(1-N3) -> 1.1436891
A4: =Data!A4 -> 38077 | B4: =Data!E4 - Factors!AB6 -> 0.010438909 | C4: =Factors!Z6 -> 0.076486179 | D4: =Factors!J6 -> 0.0044400219 | E4: =Factors!J6 - Factors!K6 -> 0.00011003248 | F4: =Factors!H6 - Factors!AA6 -> 0.01867623 | M4: HF FOF Div - Relative Value HF | N4: =INDEX(LINEST(E2:E121, CHOOSE({1,2}, C2:D121, F2:F121), TRUE, TRUE), 3, 1) -> 0.024900212 | O4: =1/(1-N4) -> 1.0255361
A5: =Data!A5 -> 38107 | B5: =Data!E5 - Factors!AB7 -> -0.029190464 | C5: =Factors!Z7 -> -0.093094149 | D5: =Factors!J7 -> -0.0070900013 | E5: =Factors!J7 - Factors!K7 -> -0.0020300026 | F5: =Factors!H7 - Factors!AA7 -> -0.0050815692 | M5: Long Short HF - S&P500 | N5: =INDEX(LINEST(F2:F121, C2:E121, TRUE, TRUE), 3, 1) -> 0.14358925 | O5: =1/(1-N5) -> 1.167664
A6: =Data!A6 -> 38138 | B6: =Data!E6 - Factors!AB8 -> -0.0077398376 | C6: =Factors!Z8 -> 0.022753717 | D6: =Factors!J8 -> -0.008780017 | E6: =Factors!J8 - Factors!K8 -> -0.0053300232 | F6: =Factors!H8 - Factors!AA8 -> -0.015632896 | H6: SUMMARY OUTPUT
A7: =Data!A7 -> 38168 | B7: =Data!E7 - Factors!AB9 -> -0.001767805 | C7: =Factors!Z9 -> -0.003286563 | D7: =Factors!J9 -> 0.0036000126 | E7: =Factors!J9 - Factors!K9 -> 0.0019900115 | F7: =Factors!H9 - Factors!AA9 -> -0.0087949416
A8: =Data!A8 -> 38198 | B8: =Data!E8 - Factors!AB10 -> -0.0042606936 | C8: =Factors!Z10 -> -0.0081166772 | D8: =Factors!J10 -> -0.0056499986 | E8: =Factors!J10 - Factors!K10 -> -0.012169985 | F8: =Factors!H10 - Factors!AA10 -> 0.014276938 | H8: Regression Statistics
A9: =Data!A9 -> 38230 | B9: =Data!E9 - Factors!AB11 -> -0.0034209799 | C9: =Factors!Z11 -> 0.048075694 | D9: =Factors!J11 -> -9.0006463e-05 | E9: =Factors!J11 - Factors!K11 -> -0.0083400215 | F9: =Factors!H11 - Factors!AA11 -> -0.007714942 | H9: Multiple R | I9: 0.79179941
A10: =Data!A10 -> 38260 | B10: =Data!E10 - Factors!AB12 -> 0.0071391284 | C10: =Factors!Z12 -> 0.020495303 | D10: =Factors!J12 -> 0.0082399999 | E10: =Factors!J12 - Factors!K12 -> 0.0046800139 | F10: =Factors!H12 - Factors!AA12 -> 0.009039415 | H10: R Square | I10: 0.62694631
A11: =Data!A11 -> 38289 | B11: =Data!E11 - Factors!AB13 -> 0.0071705913 | C11: =Factors!Z13 -> 0.02462642 | D11: =Factors!J13 -> 0.0077799954 | E11: =Factors!J13 - Factors!K13 -> 0.0046699963 | F11: =Factors!H13 - Factors!AA13 -> -0.010527279 | H11: Adjusted R Square | I11: 0.61397053
A12: =Data!A12 -> 38321 | B12: =Data!E12 - Factors!AB14 -> 0.026660861 | C12: =Factors!Z14 -> 0.05226928 | D12: =Factors!J14 -> 0.026389991 | E12: =Factors!J14 - Factors!K14 -> 0.015719984 | F12: =Factors!H14 - Factors!AA14 -> -0.006761563 | H12: Standard Error | I12: 0.0086184021
A13: =Data!A13 -> 38352 | B13: =Data!E13 - Factors!AB15 -> 0.0041299613 | C13: =Factors!Z15 -> -0.027719259 | D13: =Factors!J15 -> 0.01505 | E13: =Factors!J15 - Factors!K15 -> 0.0075899936 | F13: =Factors!H15 - Factors!AA15 -> -0.01641866 | H13: Observations | I13: 120
A14: =Data!A14 -> 38383 | B14: =Data!E14 - Factors!AB16 -> -0.0074455305 | C14: =Factors!Z16 -> -0.036150074 | D14: =Factors!J16 -> 0.00017001186 | E14: =Factors!J16 - Factors!K16 -> -0.0028399794 | F14: =Factors!H16 - Factors!AA16 -> 0.018555008
A15: =Data!A15 -> 38411 | B15: =Data!E15 - Factors!AB17 -> 0.016437411 | C15: =Factors!Z17 -> 0.030880265 | D15: =Factors!J17 -> 0.014190009 | E15: =Factors!J17 - Factors!K17 -> 0.0063600111 | F15: =Factors!H17 - Factors!AA17 -> 0.00023578104 | H15: ANOVA
A16: =Data!A16 -> 38442 | B16: =Data!E16 - Factors!AB18 -> -0.0082899575 | C16: =Factors!Z18 -> -0.016756571 | D16: =Factors!J18 -> -0.0051600137 | E16: =Factors!J18 - Factors!K18 -> -0.001660021 | F16: =Factors!H18 - Factors!AA18 -> 0.0071780439 | I16: df | J16: SS | K16: MS | L16: F | M16: Significance F
A17: =Data!A17 -> 38471 | B17: =Data!E17 - Factors!AB19 -> -0.012824908 | C17: =Factors!Z19 -> 0.014100619 | D17: =Factors!J19 -> -0.015129993 | E17: =Factors!J19 - Factors!K19 -> -0.0066899933 | F17: =Factors!H19 - Factors!AA19 -> -0.0033539856 | H17: Regression | I17: 4 | J17: 0.014355237 | K17: 0.0035888091 | L17: 48.316655 | M17: 8.8233461e-24
A18: =Data!A18 -> 38503 | B18: =Data!E18 - Factors!AB20 -> 0.0010608022 | C18: =Factors!Z20 -> -0.03945763 | D18: =Factors!J20 -> 0.0021699912 | E18: =Factors!J20 - Factors!K20 -> 0.0032099952 | F18: =Factors!H20 - Factors!AA20 -> -0.016298995 | H18: Residual | I18: 115 | J18: 0.0085418382 | K18: 7.4276854e-05
A19: =Data!A19 -> 38533 | B19: =Data!E19 - Factors!AB21 -> 0.0082856709 | C19: =Factors!Z21 -> 0.043738766 | D19: =Factors!J21 -> 0.013040001 | E19: =Factors!J21 - Factors!K21 -> 0.003449991 | F19: =Factors!H21 - Factors!AA21 -> 0.018180603 | H19: Total | I19: 119 | J19: 0.022897075
A20: =Data!A20 -> 38562 | B20: =Data!E20 - Factors!AB22 -> 0.0049724202 | C20: =Factors!Z22 -> -0.013088404 | D20: =Factors!J22 -> 0.018030012 | E20: =Factors!J22 - Factors!K22 -> 0.0046300243 | F20: =Factors!H22 - Factors!AA22 -> -0.0076985043
A21: =Data!A21 -> 38595 | B21: =Data!E21 - Factors!AB23 -> 0.0044625005 | C21: =Factors!Z23 -> 0.012563983 | D21: =Factors!J23 -> 0.0084599894 | E21: =Factors!J23 - Factors!K23 -> 0.0015499908 | F21: =Factors!H23 - Factors!AA23 -> 0.016534064 | I21: Coefficients | J21: Standard Error | K21: t Stat | L21: P-value | M21: Lower 95% | N21: Upper 95% | O21: Lower 95.0% | P21: Upper 95.0%
A22: =Data!A22 -> 38625 | B22: =Data!E22 - Factors!AB24 -> 0.018122826 | C22: =Factors!Z24 -> 0.078354779 | D22: =Factors!J24 -> 0.015259997 | E22: =Factors!J24 - Factors!K24 -> 0.0035099833 | F22: =Factors!H24 - Factors!AA24 -> 0.014430686 | H22: Intercept | I22: 0.0022418121 | J22: 0.00087226812 | K22: 2.5700951 | L22: 0.011444742 | M22: 0.00051401679 | N22: 0.0039696073 | O22: 0.00051401679 | P22: 0.0039696073
A23: =Data!A23 -> 38656 | B23: =Data!E23 - Factors!AB25 -> -0.0089936197 | C23: =Factors!Z25 -> -0.0087577243 | D23: =Factors!J25 -> -0.015100003 | E23: =Factors!J25 - Factors!K25 -> -0.011550001 | F23: =Factors!H25 - Factors!AA25 -> -0.0020591314 | H23: Gold | I23: 0.088277653 | J23: 0.014965432 | K23: 5.8987706 | L23: 3.7589545e-08 | M23: 0.058634011 | N23: 0.11792129 | O23: 0.058634011 | P23: 0.11792129
A24: =Data!A24 -> 38686 | B24: =Data!E24 - Factors!AB26 -> 0.011561723 | C24: =Factors!Z26 -> 0.059953997 | D24: =Factors!J26 -> 0.017020022 | E24: =Factors!J26 - Factors!K26 -> 0.0087800296 | F24: =Factors!H26 - Factors!AA26 -> -0.016472298 | H24: HF FOF Div | I24: 0.31472457 | J24: 0.060837686 | K24: 5.1731845 | L24: 9.8495087e-07 | M24: 0.19421683 | N24: 0.43523232 | O24: 0.19421683 | P24: 0.43523232
A25: =Data!A25 -> 38716 | B25: =Data!E25 - Factors!AB27 -> 0.0095251369 | C25: =Factors!Z27 -> 0.048511398 | D25: =Factors!J27 -> 0.020079989 | E25: =Factors!J27 - Factors!K27 -> 0.0053299862 | F25: =Factors!H27 - Factors!AA27 -> 0.022811883 | H25: HF FOF Div - Relative Value HF | I25: 0.75331525 | J25: 0.11522092 | K25: 6.5380076 | L25: 1.7877034e-09 | M25: 0.52508478 | N25: 0.98154571 | O25: 0.52508478 | P25: 0.98154571
A26: =Data!A26 -> 38748 | B26: =Data!E26 - Factors!AB28 -> 0.020795499 | C26: =Factors!Z28 -> 0.10038685 | D26: =Factors!J28 -> 0.028360008 | E26: =Factors!J28 - Factors!K28 -> 0.0063700025 | F26: =Factors!H28 - Factors!AA28 -> 0.013042471 | H26: Long Short HF - S&P500 | I26: 0.036420312 | J26: 0.034908986 | K26: 1.0432933 | L26: 0.29900067 | M26: -0.032727671 | N26: 0.10556829 | O26: -0.032727671 | P26: 0.10556829
A27: =Data!A27 -> 38776 | B27: =Data!E27 - Factors!AB29 -> -0.007924186 | C27: =Factors!Z29 -> -0.01291967 | D27: =Factors!J29 -> 0.003469983 | E27: =Factors!J29 - Factors!K29 -> -0.0027600065 | F27: =Factors!H29 - Factors!AA29 -> -0.0025137165
A28: =Data!A28 -> 38807 | B28: =Data!E28 - Factors!AB30 -> 0.0076372396 | C28: =Factors!Z30 -> 0.039355356 | D28: =Factors!J30 -> 0.016610014 | E28: =Factors!J30 - Factors!K30 -> 0.0032700063 | F28: =Factors!H30 - Factors!AA30 -> 0.013012925
A29: =Data!A29 -> 38835 | B29: =Data!E29 - Factors!AB31 -> 0.023879732 | C29: =Factors!Z31 -> 0.12125418 | D29: =Factors!J31 -> 0.017169992 | E29: =Factors!J31 - Factors!K31 -> 0.0060199914 | F29: =Factors!H31 - Factors!AA31 -> 0.0041719548
A30: =Data!A30 -> 38868 | B30: =Data!E30 - Factors!AB32 -> -0.017616717 | C30: =Factors!Z32 -> -0.014088811 | D30: =Factors!J32 -> -0.019659986 | E30: =Factors!J32 - Factors!K32 -> -0.021699977 | F30: =Factors!H32 - Factors!AA32 -> 0.0055513251 | I30: OOS R Square | J30: =1 - SUMSQ(I38:I121) / DEVSQ(B38:B121) -> 0.47792683
A31: =Data!A31 -> 38898 | B31: =Data!E31 - Factors!AB33 -> -0.0088009587 | C31: =Factors!Z33 -> -0.045489771 | D31: =Factors!J33 -> -0.0062600113 | E31: =Factors!J33 - Factors!K33 -> -0.01178002 | F31: =Factors!H33 - Factors!AA33 -> -0.0067056015 | I31: OOS RMSE | J31: =SQRT( SUMSQ(I38:I121) / COUNT(I38:I121) ) -> 0.010391378
A32: =Data!A32 -> 38929 | B32: =Data!E32 - Factors!AB34 -> -0.0066596944 | C32: =Factors!Z34 -> 0.033936835 | D32: =Factors!J34 -> -0.0022099993 | E32: =Factors!J34 - Factors!K34 -> -0.0063899907 | F32: =Factors!H34 - Factors!AA34 -> -0.011588535 | I32: ex0809 OOS R^2 | J32: =1 - SUMSQ(J38:J121) / DEVSQ(K38:K121) -> 0.53830236
A33: =Data!A33 -> 38960 | B33: =Data!E33 - Factors!AB35 -> -0.0019510745 | C33: =Factors!Z35 -> -0.014840989 | D33: =Factors!J35 -> 0.0081299984 | E33: =Factors!J35 - Factors!K35 -> 0.0010199931 | F33: =Factors!H35 - Factors!AA35 -> -0.013492988
A34: =Data!A34 -> 38989 | B34: =Data!E34 - Factors!AB36 -> -0.01196632 | C34: =Factors!Z36 -> -0.046229874 | D34: =Factors!J36 -> 0.00074999312 | E34: =Factors!J36 - Factors!K36 -> -0.0029499988 | F34: =Factors!H36 - Factors!AA36 -> -0.02419031
A35: =Data!A35 -> 39021 | B35: =Data!E35 - Factors!AB37 -> 0.007474341 | C35: =Factors!Z37 -> 0.013872639 | D35: =Factors!J37 -> 0.016250019 | E35: =Factors!J37 - Factors!K37 -> 0.0039800123 | F35: =Factors!H37 - Factors!AA37 -> -0.013955951
A36: =Data!A36 -> 39051 | B36: =Data!E36 - Factors!AB38 -> 0.019408258 | C36: =Factors!Z38 -> 0.068249258 | D36: =Factors!J38 -> 0.017829984 | E36: =Factors!J38 - Factors!K38 -> 0.0040999812 | F36: =Factors!H38 - Factors!AA38 -> 0.00098412906
A37: =Data!A37 -> 39080 | B37: =Data!E37 - Factors!AB39 -> 0.0083874782 | C37: =Factors!Z39 -> -0.017438272 | D37: =Factors!J39 -> 0.01786001 | E37: =Factors!J39 - Factors!K39 -> 0.001750013 | F37: =Factors!H39 - Factors!AA39 -> -0.00056765242 | H37: 36 Month Rolling
A38: =Data!A38 -> 39113 | B38: =Data!E38 - Factors!AB40 -> -0.00040867298 | C38: =Factors!Z40 -> 0.025914874 | D38: =Factors!J40 -> 0.012942254 | E38: =Factors!J40 - Factors!K40 -> -0.00072645543 | F38: =Factors!H40 - Factors!AA40 -> -0.0035490454 | H38: {=TREND(B2:B37, C2:F37, C38:F38, TRUE)} -> 0.0070425291 | I38: =B38 - H38 -> -0.0074512021 | J38: =IF(OR(YEAR(A38)=2008, YEAR(A38)=2009), "", I38) -> -0.0074512021 | K38: =IF(OR(YEAR(A38)=2008, YEAR(A38)=2009), "", B38) -> -0.00040867298
A39: =Data!A39 -> 39141 | B39: =Data!E39 - Factors!AB41 -> -0.0015428829 | C39: =Factors!Z41 -> 0.024724434 | D39: =Factors!J41 -> 0.0081972119 | E39: =Factors!J41 - Factors!K41 -> 0.00063454805 | F39: =Factors!H41 - Factors!AA41 -> 0.025829047 | H39: {=TREND(B3:B38, C3:F38, C39:F39, TRUE)} -> 0.0058235915 | I39: =B39 - H39 -> -0.0073664744 | J39: =IF(OR(YEAR(A39)=2008, YEAR(A39)=2009), "", I39) -> -0.0073664744 | K39: =IF(OR(YEAR(A39)=2008, YEAR(A39)=2009), "", B39) -> -0.0015428829
A40: =Data!A40 -> 39171 | B40: =Data!E40 - Factors!AB42 -> -0.0053784364 | C40: =Factors!Z42 -> -0.0083065661 | D40: =Factors!J42 -> 0.011549314 | E40: =Factors!J42 - Factors!K42 -> 0.0040145878 | F40: =Factors!H42 - Factors!AA42 -> -0.0010966704 | H40: {=TREND(B4:B39, C4:F39, C40:F40, TRUE)} -> 0.0025902838 | I40: =B40 - H40 -> -0.0079687201 | J40: =IF(OR(YEAR(A40)=2008, YEAR(A40)=2009), "", I40) -> -0.0079687201 | K40: =IF(OR(YEAR(A40)=2008, YEAR(A40)=2009), "", B40) -> -0.0053784364
A41: =Data!A41 -> 39202 | B41: =Data!E41 - Factors!AB43 -> 0.011976878 | C41: =Factors!Z43 -> 0.022085298 | D41: =Factors!J43 -> 0.016760762 | E41: =Factors!J43 - Factors!K43 -> 0.0025702188 | F41: =Factors!H43 - Factors!AA43 -> -0.025716112 | H41: {=TREND(B5:B40, C5:F40, C41:F41, TRUE)} -> 0.0084934843 | I41: =B41 - H41 -> 0.0034833942 | J41: =IF(OR(YEAR(A41)=2008, YEAR(A41)=2009), "", I41) -> 0.0034833942 | K41: =IF(OR(YEAR(A41)=2008, YEAR(A41)=2009), "", B41) -> 0.011976878
A42: =Data!A42 -> 39233 | B42: =Data!E42 - Factors!AB44 -> 0.013884227 | C42: =Factors!Z44 -> -0.026457366 | D42: =Factors!J44 -> 0.021465348 | E42: =Factors!J44 - Factors!K44 -> 0.0065919347 | F42: =Factors!H44 - Factors!AA44 -> -0.012519771 | H42: {=TREND(B6:B41, C6:F41, C42:F42, TRUE)} -> 0.0066107637 | I42: =B42 - H42 -> 0.0072734633 | J42: =IF(OR(YEAR(A42)=2008, YEAR(A42)=2009), "", I42) -> 0.0072734633 | K42: =IF(OR(YEAR(A42)=2008, YEAR(A42)=2009), "", B42) -> 0.013884227
A43: =Data!A43 -> 39262 | B43: =Data!E43 - Factors!AB45 -> 0.011078126 | C43: =Factors!Z45 -> -0.016426949 | D43: =Factors!J45 -> 0.0052586549 | E43: =Factors!J45 - Factors!K45 -> -0.00036297875 | F43: =Factors!H45 - Factors!AA45 -> 0.02549386 | H43: {=TREND(B7:B42, C7:F42, C43:F43, TRUE)} -> -0.0021893109 | I43: =B43 - H43 -> 0.013267437 | J43: =IF(OR(YEAR(A43)=2008, YEAR(A43)=2009), "", I43) -> 0.013267437 | K43: =IF(OR(YEAR(A43)=2008, YEAR(A43)=2009), "", B43) -> 0.011078126
A44: =Data!A44 -> 39294 | B44: =Data!E44 - Factors!AB46 -> 0.0041229099 | C44: =Factors!Z46 -> 0.022550604 | D44: =Factors!J46 -> 0.0019128344 | E44: =Factors!J46 - Factors!K46 -> 0.0077167155 | F44: =Factors!H46 - Factors!AA46 -> 0.032678176 | H44: {=TREND(B8:B43, C8:F43, C44:F44, TRUE)} -> 0.0056761919 | I44: =B44 - H44 -> -0.001553282 | J44: =IF(OR(YEAR(A44)=2008, YEAR(A44)=2009), "", I44) -> -0.001553282 | K44: =IF(OR(YEAR(A44)=2008, YEAR(A44)=2009), "", B44) -> 0.0041229099
A45: =Data!A45 -> 39325 | B45: =Data!E45 - Factors!AB47 -> -0.026040932 | C45: =Factors!Z47 -> 0.013548096 | D45: =Factors!J47 -> -0.021834293 | E45: =Factors!J47 - Factors!K47 -> -0.014952908 | F45: =Factors!H47 - Factors!AA47 -> -0.031664313 | H45: {=TREND(B9:B44, C9:F44, C45:F45, TRUE)} -> -0.017304006 | I45: =B45 - H45 -> -0.0087369268 | J45: =IF(OR(YEAR(A45)=2008, YEAR(A45)=2009), "", I45) -> -0.0087369268 | K45: =IF(OR(YEAR(A45)=2008, YEAR(A45)=2009), "", B45) -> -0.026040932
A46: =Data!A46 -> 39353 | B46: =Data!E46 - Factors!AB48 -> 0.028787166 | C46: =Factors!Z48 -> 0.10441111 | D46: =Factors!J48 -> 0.018790038 | E46: =Factors!J48 - Factors!K48 -> 0.0052881996 | F46: =Factors!H48 - Factors!AA48 -> -0.0056349191 | H46: {=TREND(B10:B45, C10:F45, C46:F46, TRUE)} -> 0.017675306 | I46: =B46 - H46 -> 0.011111859 | J46: =IF(OR(YEAR(A46)=2008, YEAR(A46)=2009), "", I46) -> 0.011111859 | K46: =IF(OR(YEAR(A46)=2008, YEAR(A46)=2009), "", B46) -> 0.028787166
A47: =Data!A47 -> 39386 | B47: =Data!E47 - Factors!AB49 -> 0.029567013 | C47: =Factors!Z49 -> 0.071543841 | D47: =Factors!J49 -> 0.030656165 | E47: =Factors!J49 - Factors!K49 -> 0.0096536196 | F47: =Factors!H49 - Factors!AA49 -> 0.01502169 | H47: {=TREND(B11:B46, C11:F46, C47:F47, TRUE)} -> 0.024879859 | I47: =B47 - H47 -> 0.0046871537 | J47: =IF(OR(YEAR(A47)=2008, YEAR(A47)=2009), "", I47) -> 0.0046871537 | K47: =IF(OR(YEAR(A47)=2008, YEAR(A47)=2009), "", B47) -> 0.029567013
A48: =Data!A48 -> 39416 | B48: =Data!E48 - Factors!AB50 -> -0.012781413 | C48: =Factors!Z50 -> -0.016629016 | D48: =Factors!J50 -> -0.014675704 | E48: =Factors!J50 - Factors!K50 -> -0.0093557817 | F48: =Factors!H50 - Factors!AA50 -> 0.012904033 | H48: {=TREND(B12:B47, C12:F47, C48:F48, TRUE)} -> -0.014986427 | I48: =B48 - H48 -> 0.0022050141 | J48: =IF(OR(YEAR(A48)=2008, YEAR(A48)=2009), "", I48) -> 0.0022050141 | K48: =IF(OR(YEAR(A48)=2008, YEAR(A48)=2009), "", B48) -> -0.012781413
A49: =Data!A49 -> 39447 | B49: =Data!E49 - Factors!AB51 -> 0.0070711374 | C49: =Factors!Z51 -> 0.064003573 | D49: =Factors!J51 -> 0.0033379196 | E49: =Factors!J51 - Factors!K51 -> -0.0030985504 | F49: =Factors!H51 - Factors!AA51 -> 0.012219171 | H49: {=TREND(B13:B48, C13:F48, C49:F49, TRUE)} -> 0.0052499125 | I49: =B49 - H49 -> 0.0018212249 | J49: =IF(OR(YEAR(A49)=2008, YEAR(A49)=2009), "", I49) -> 0.0018212249 | K49: =IF(OR(YEAR(A49)=2008, YEAR(A49)=2009), "", B49) -> 0.0070711374
... A121: =Data!A121 -> 41639 | B121: =Data!E121 - Factors!AB123 -> 0.0046525741 | C121: =Factors!Z123 -> -0.04125743 | D121: =Factors!J123 -> 0.015226749 | E121: =Factors!J123 - Factors!K123 -> 0.0075417591 | F121: =Factors!H123 - Factors!AA123 -> -0.011172553 | H121: {=TREND(B85:B120, C85:F120, C121:F121, TRUE)} -> 0.014484249 | I121: =B121 - H121 -> -0.0098316747 | J121: =IF(OR(YEAR(A121)=2008, YEAR(A121)=2009), "", I121) -> -0.0098316747 | K121: =IF(OR(YEAR(A121)=2008, YEAR(A121)=2009), "", B121) -> 0.0046525741

Sheet A4_3
A1: Date | B1: xAsset4 | C1: Gold | D1: HF FOF Div | E1: High Yield - US AGG | F1: Global AGG | H1: Predicted | I1: Residual | J1: Resid_ex0809 | K1: xAsset_ex0809
A2: =Data!A2 -> 38016 | B2: =Data!E2 - Factors!AB4 -> 0.0057286923 | C2: =Factors!Z4 -> -0.031291371 | D2: =Factors!J4 -> 0.01538002 | E2: =Factors!N4 - Factors!D4 -> 0.0081077053 | F2: =Factors!E4 -> 0.0037328896
A3: =Data!A3 -> 38044 | B3: =Data!E3 - Factors!AB5 -> 0.019259224 | C3: =Factors!Z5 -> -0.015654119 | D3: =Factors!J5 -> 0.010909983 | E3: =Factors!N5 - Factors!D5 -> -0.011920733 | F3: =Factors!E5 -> 0.0051522151
A4: =Data!A4 -> 38077 | B4: =Data!E4 - Factors!AB6 -> 0.010438909 | C4: =Factors!Z6 -> 0.076486179 | D4: =Factors!J6 -> 0.0044400219 | E4: =Factors!N6 - Factors!D6 -> -0.00081760495 | F4: =Factors!E6 -> 0.011076524
A5: =Data!A5 -> 38107 | B5: =Data!E5 - Factors!AB7 -> -0.029190464 | C5: =Factors!Z7 -> -0.093094149 | D5: =Factors!J7 -> -0.0070900013 | E5: =Factors!N7 - Factors!D7 -> 0.019415308 | F5: =Factors!E7 -> -0.036564036 | H5: SUMMARY OUTPUT
A6: =Data!A6 -> 38138 | B6: =Data!E6 - Factors!AB8 -> -0.0077398376 | C6: =Factors!Z8 -> 0.022753717 | D6: =Factors!J8 -> -0.008780017 | E6: =Factors!N8 - Factors!D8 -> -0.011705638 | F6: =Factors!E8 -> 0.0049003612
A7: =Data!A7 -> 38168 | B7: =Data!E7 - Factors!AB9 -> -0.001767805 | C7: =Factors!Z9 -> -0.003286563 | D7: =Factors!J9 -> 0.0036000126 | E7: =Factors!N9 - Factors!D9 -> 0.0088758343 | F7: =Factors!E9 -> 0.002922566 | H7: Regression Statistics
A8: =Data!A8 -> 38198 | B8: =Data!E8 - Factors!AB10 -> -0.0042606936 | C8: =Factors!Z10 -> -0.0081166772 | D8: =Factors!J10 -> -0.0056499986 | E8: =Factors!N10 - Factors!D10 -> 0.0035641781 | F8: =Factors!E10 -> -0.0002074828 | H8: Multiple R | I8: 0.74904956
A9: =Data!A9 -> 38230 | B9: =Data!E9 - Factors!AB11 -> -0.0034209799 | C9: =Factors!Z11 -> 0.048075694 | D9: =Factors!J11 -> -9.0006463e-05 | E9: =Factors!N11 - Factors!D11 -> -0.00090321685 | F9: =Factors!E11 -> 0.021887267 | H9: R Square | I9: 0.56107525
A10: =Data!A10 -> 38260 | B10: =Data!E10 - Factors!AB12 -> 0.0071391284 | C10: =Factors!Z12 -> 0.020495303 | D10: =Factors!J12 -> 0.0082399999 | E10: =Factors!N12 - Factors!D12 -> 0.011218053 | F10: =Factors!E12 -> 0.01181709 | H10: Adjusted R Square | I10: 0.5458083
A11: =Data!A11 -> 38289 | B11: =Data!E11 - Factors!AB13 -> 0.0071705913 | C11: =Factors!Z13 -> 0.02462642 | D11: =Factors!J13 -> 0.0077799954 | E11: =Factors!N13 - Factors!D13 -> 0.010894461 | F11: =Factors!E13 -> 0.023953957 | H11: Standard Error | I11: 0.0093483748
A12: =Data!A12 -> 38321 | B12: =Data!E12 - Factors!AB14 -> 0.026660861 | C12: =Factors!Z14 -> 0.05226928 | D12: =Factors!J14 -> 0.026389991 | E12: =Factors!N14 - Factors!D14 -> 0.018380451 | F12: =Factors!E14 -> 0.026496979 | H12: Observations | I12: 120
A13: =Data!A13 -> 38352 | B13: =Data!E13 - Factors!AB15 -> 0.0041299613 | C13: =Factors!Z15 -> -0.027719259 | D13: =Factors!J15 -> 0.01505 | E13: =Factors!N15 - Factors!D15 -> 0.0058803136 | F13: =Factors!E15 -> 0.015321934
A14: =Data!A14 -> 38383 | B14: =Data!E14 - Factors!AB16 -> -0.0074455305 | C14: =Factors!Z16 -> -0.036150074 | D14: =Factors!J16 -> 0.00017001186 | E14: =Factors!N16 - Factors!D16 -> -0.0072984348 | F14: =Factors!E16 -> -0.010524264 | H14: ANOVA
A15: =Data!A15 -> 38411 | B15: =Data!E15 - Factors!AB17 -> 0.016437411 | C15: =Factors!Z17 -> 0.030880265 | D15: =Factors!J17 -> 0.014190009 | E15: =Factors!N17 - Factors!D17 -> 0.020187179 | F15: =Factors!E17 -> 0.0019035659 | I15: df | J15: SS | K15: MS | L15: F | M15: Significance F
A16: =Data!A16 -> 38442 | B16: =Data!E16 - Factors!AB18 -> -0.0082899575 | C16: =Factors!Z18 -> -0.016756571 | D16: =Factors!J18 -> -0.0051600137 | E16: =Factors!N18 - Factors!D18 -> -0.022176904 | F16: =Factors!E18 -> -0.012098137 | H16: Regression | I16: 4 | J16: 0.012846982 | K16: 0.0032117455 | L16: 36.750977 | M16: 9.1069978e-20
A17: =Data!A17 -> 38471 | B17: =Data!E17 - Factors!AB19 -> -0.012824908 | C17: =Factors!Z19 -> 0.014100619 | D17: =Factors!J19 -> -0.015129993 | E17: =Factors!N19 - Factors!D19 -> -0.024261662 | F17: =Factors!E19 -> 0.013086726 | H17: Residual | I17: 115 | J17: 0.010050093 | K17: 8.7392112e-05
A18: =Data!A18 -> 38503 | B18: =Data!E18 - Factors!AB20 -> 0.0010608022 | C18: =Factors!Z20 -> -0.03945763 | D18: =Factors!J20 -> 0.0021699912 | E18: =Factors!N20 - Factors!D20 -> 0.0070841965 | F18: =Factors!E20 -> -0.013397377 | H18: Total | I18: 119 | J18: 0.022897075
A19: =Data!A19 -> 38533 | B19: =Data!E19 - Factors!AB21 -> 0.0082856709 | C19: =Factors!Z21 -> 0.043738766 | D19: =Factors!J21 -> 0.013040001 | E19: =Factors!N21 - Factors!D21 -> 0.013578147 | F19: =Factors!E21 -> -0.0044845893
A20: =Data!A20 -> 38562 | B20: =Data!E20 - Factors!AB22 -> 0.0049724202 | C20: =Factors!Z22 -> -0.013088404 | D20: =Factors!J22 -> 0.018030012 | E20: =Factors!N22 - Factors!D22 -> 0.024795569 | F20: =Factors!E22 -> -0.0080068466 | I20: Coefficients | J20: Standard Error | K20: t Stat | L20: P-value | M20: Lower 95% | N20: Upper 95% | O20: Lower 95.0% | P20: Upper 95.0%
A21: =Data!A21 -> 38595 | B21: =Data!E21 - Factors!AB23 -> 0.0044625005 | C21: =Factors!Z23 -> 0.012563983 | D21: =Factors!J23 -> 0.0084599894 | E21: =Factors!N23 - Factors!D23 -> -0.0091915546 | F21: =Factors!E23 -> 0.016459134 | H21: Intercept | I21: -0.00025439594 | J21: 0.00088590983 | K21: -0.28715783 | L21: 0.77450825 | M21: -0.0020092128 | N21: 0.0015004209 | O21: -0.0020092128 | P21: 0.0015004209
A22: =Data!A22 -> 38625 | B22: =Data!E22 - Factors!AB24 -> 0.018122826 | C22: =Factors!Z24 -> 0.078354779 | D22: =Factors!J24 -> 0.015259997 | E22: =Factors!N24 - Factors!D24 -> 0.00028635718 | F22: =Factors!E24 -> -0.015920275 | H22: Gold | I22: 0.057535411 | J22: 0.0184629 | K22: 3.1162716 | L22: 0.0023133291 | M22: 0.02096396 | N22: 0.094106863 | O22: 0.02096396 | P22: 0.094106863
A23: =Data!A23 -> 38656 | B23: =Data!E23 - Factors!AB25 -> -0.0089936197 | C23: =Factors!Z25 -> -0.0087577243 | D23: =Factors!J25 -> -0.015100003 | E23: =Factors!N25 - Factors!D25 -> 0.00061975345 | F23: =Factors!E25 -> -0.014886017 | H23: HF FOF Div | I23: 0.68402886 | J23: 0.07769724 | K23: 8.8037729 | L23: 1.5753642e-14 | M23: 0.53012558 | N23: 0.83793214 | O23: 0.53012558 | P23: 0.83793214
A24: =Data!A24 -> 38686 | B24: =Data!E24 - Factors!AB26 -> 0.011561723 | C24: =Factors!Z26 -> 0.059953997 | D24: =Factors!J26 -> 0.017020022 | E24: =Factors!N26 - Factors!D26 -> 0.0004020722 | F24: =Factors!E26 -> -0.0070979041 | H24: High Yield - US AGG | I24: -0.19166375 | J24: 0.040441838 | K24: -4.7392442 | L24: 6.1892032e-06 | M24: -0.27177124 | N24: -0.11155625 | O24: -0.27177124 | P24: -0.11155625
A25: =Data!A25 -> 38716 | B25: =Data!E25 - Factors!AB27 -> 0.0095251369 | C25: =Factors!Z27 -> 0.048511398 | D25: =Factors!J27 -> 0.020079989 | E25: =Factors!N27 - Factors!D27 -> -0.00035321919 | F25: =Factors!E27 -> 0.0098715137 | H25: Global AGG | I25: 0.1406014 | J25: 0.059288876 | K25: 2.3714635 | L25: 0.019379668 | M25: 0.023161551 | N25: 0.25804126 | O25: 0.023161551 | P25: 0.25804126
A26: =Data!A26 -> 38748 | B26: =Data!E26 - Factors!AB28 -> 0.020795499 | C26: =Factors!Z28 -> 0.10038685 | D26: =Factors!J28 -> 0.028360008 | E26: =Factors!N28 - Factors!D28 -> 0.015793 | F26: =Factors!E28 -> 0.012614298
A27: =Data!A27 -> 38776 | B27: =Data!E27 - Factors!AB29 -> -0.007924186 | C27: =Factors!Z29 -> -0.01291967 | D27: =Factors!J29 -> 0.003469983 | E27: =Factors!N29 - Factors!D29 -> 0.0030028343 | F27: =Factors!E29 -> -0.0035465658
A28: =Data!A28 -> 38807 | B28: =Data!E28 - Factors!AB30 -> 0.0076372396 | C28: =Factors!Z30 -> 0.039355356 | D28: =Factors!J30 -> 0.016610014 | E28: =Factors!N30 - Factors!D30 -> 0.016063403 | F28: =Factors!E30 -> -0.0099131724
A29: =Data!A29 -> 38835 | B29: =Data!E29 - Factors!AB31 -> 0.023879732 | C29: =Factors!Z31 -> 0.12125418 | D29: =Factors!J31 -> 0.017169992 | E29: =Factors!N31 - Factors!D31 -> 0.0082388531 | F29: =Factors!E31 -> 0.018928887
A30: =Data!A30 -> 38868 | B30: =Data!E30 - Factors!AB32 -> -0.017616717 | C30: =Factors!Z32 -> -0.014088811 | D30: =Factors!J32 -> -0.019659986 | E30: =Factors!N32 - Factors!D32 -> 0.00043572579 | F30: =Factors!E32 -> 0.012897983 | I30: OOS R Square | J30: =1 - SUMSQ(I38:I121) / DEVSQ(B38:B121) -> 0.22276199
A31: =Data!A31 -> 38898 | B31: =Data!E31 - Factors!AB33 -> -0.0088009587 | C31: =Factors!Z33 -> -0.045489771 | D31: =Factors!J33 -> -0.0062600113 | E31: =Factors!N33 - Factors!D33 -> -0.0059113317 | F31: =Factors!E33 -> -0.0079451696 | I31: OOS RMSE | J31: =SQRT( SUMSQ(I38:I121) / COUNT(I38:I121) ) -> 0.012678985
A32: =Data!A32 -> 38929 | B32: =Data!E32 - Factors!AB34 -> -0.0066596944 | C32: =Factors!Z34 -> 0.033936835 | D32: =Factors!J34 -> -0.0022099993 | E32: =Factors!N34 - Factors!D34 -> -0.0028526316 | F32: =Factors!E34 -> 0.0099619177 | I32: ex0809 OOS R^2 | J32: =1 - SUMSQ(J38:J121) / DEVSQ(K38:K121) -> 0.5021251
A33: =Data!A33 -> 38960 | B33: =Data!E33 - Factors!AB35 -> -0.0019510745 | C33: =Factors!Z35 -> -0.014840989 | D33: =Factors!J35 -> 0.0081299984 | E33: =Factors!N35 - Factors!D35 -> 0.00087198764 | F33: =Factors!E35 -> 0.011555066
A34: =Data!A34 -> 38989 | B34: =Data!E34 - Factors!AB36 -> -0.01196632 | C34: =Factors!Z36 -> -0.046229874 | D34: =Factors!J36 -> 0.00074999312 | E34: =Factors!N36 - Factors!D36 -> 0.0043698119 | F34: =Factors!E36 -> -7.4683066e-05
A35: =Data!A35 -> 39021 | B35: =Data!E35 - Factors!AB37 -> 0.007474341 | C35: =Factors!Z37 -> 0.013872639 | D35: =Factors!J37 -> 0.016250019 | E35: =Factors!N37 - Factors!D37 -> 0.0079869694 | F35: =Factors!E37 -> 0.0096735856
A36: =Data!A36 -> 39051 | B36: =Data!E36 - Factors!AB38 -> 0.019408258 | C36: =Factors!Z38 -> 0.068249258 | D36: =Factors!J38 -> 0.017829984 | E36: =Factors!N38 - Factors!D38 -> 0.0043611622 | F36: =Factors!E38 -> 0.024354469
A37: =Data!A37 -> 39080 | B37: =Data!E37 - Factors!AB39 -> 0.0083874782 | C37: =Factors!Z39 -> -0.017438272 | D37: =Factors!J39 -> 0.01786001 | E37: =Factors!N39 - Factors!D39 -> 0.016812288 | F37: =Factors!E39 -> -0.013256313 | H37: 36 Month Rolling
A38: =Data!A38 -> 39113 | B38: =Data!E38 - Factors!AB40 -> -0.00040867298 | C38: =Factors!Z40 -> 0.025914874 | D38: =Factors!J40 -> 0.012942254 | E38: =Factors!N40 - Factors!D40 -> 0.011154069 | F38: =Factors!E40 -> -0.0098284605 | H38: {=TREND(B2:B37, C2:F37, C38:F38, TRUE)} -> 0.007247674 | I38: =B38 - H38 -> -0.007656347 | J38: =IF(OR(YEAR(A38)=2008, YEAR(A38)=2009), "", I38) -> -0.007656347 | K38: =IF(OR(YEAR(A38)=2008, YEAR(A38)=2009), "", B38) -> -0.00040867298
A39: =Data!A39 -> 39141 | B39: =Data!E39 - Factors!AB41 -> -0.0015428829 | C39: =Factors!Z41 -> 0.024724434 | D39: =Factors!J41 -> 0.0081972119 | E39: =Factors!N41 - Factors!D41 -> -0.0014908489 | F39: =Factors!E41 -> 0.020578466 | H39: {=TREND(B3:B38, C3:F38, C39:F39, TRUE)} -> 0.0067793647 | I39: =B39 - H39 -> -0.0083222476 | J39: =IF(OR(YEAR(A39)=2008, YEAR(A39)=2009), "", I39) -> -0.0083222476 | K39: =IF(OR(YEAR(A39)=2008, YEAR(A39)=2009), "", B39) -> -0.0015428829
A40: =Data!A40 -> 39171 | B40: =Data!E40 - Factors!AB42 -> -0.0053784364 | C40: =Factors!Z42 -> -0.0083065661 | D40: =Factors!J42 -> 0.011549314 | E40: =Factors!N42 - Factors!D42 -> 0.0022920381 | F40: =Factors!E42 -> 0.0023638205 | H40: {=TREND(B4:B39, C4:F39, C40:F40, TRUE)} -> 0.0022830177 | I40: =B40 - H40 -> -0.007661454 | J40: =IF(OR(YEAR(A40)=2008, YEAR(A40)=2009), "", I40) -> -0.007661454 | K40: =IF(OR(YEAR(A40)=2008, YEAR(A40)=2009), "", B40) -> -0.0053784364
A41: =Data!A41 -> 39202 | B41: =Data!E41 - Factors!AB43 -> 0.011976878 | C41: =Factors!Z43 -> 0.022085298 | D41: =Factors!J43 -> 0.016760762 | E41: =Factors!N43 - Factors!D43 -> 0.0078404705 | F41: =Factors!E43 -> 0.011302713 | H41: {=TREND(B5:B40, C5:F40, C41:F41, TRUE)} -> 0.0092442551 | I41: =B41 - H41 -> 0.0027326234 | J41: =IF(OR(YEAR(A41)=2008, YEAR(A41)=2009), "", I41) -> 0.0027326234 | K41: =IF(OR(YEAR(A41)=2008, YEAR(A41)=2009), "", B41) -> 0.011976878
A42: =Data!A42 -> 39233 | B42: =Data!E42 - Factors!AB44 -> 0.013884227 | C42: =Factors!Z44 -> -0.026457366 | D42: =Factors!J44 -> 0.021465348 | E42: =Factors!N44 - Factors!D44 -> 0.014693511 | F42: =Factors!E44 -> -0.01559266 | H42: {=TREND(B6:B41, C6:F41, C42:F42, TRUE)} -> 0.0069876446 | I42: =B42 - H42 -> 0.0068965825 | J42: =IF(OR(YEAR(A42)=2008, YEAR(A42)=2009), "", I42) -> 0.0068965825 | K42: =IF(OR(YEAR(A42)=2008, YEAR(A42)=2009), "", B42) -> 0.013884227
A43: =Data!A43 -> 39262 | B43: =Data!E43 - Factors!AB45 -> 0.011078126 | C43: =Factors!Z45 -> -0.016426949 | D43: =Factors!J45 -> 0.0052586549 | E43: =Factors!N45 - Factors!D45 -> -0.013895785 | F43: =Factors!E45 -> -0.0044349056 | H43: {=TREND(B7:B42, C7:F42, C43:F43, TRUE)} -> -0.0038058171 | I43: =B43 - H43 -> 0.014883944 | J43: =IF(OR(YEAR(A43)=2008, YEAR(A43)=2009), "", I43) -> 0.014883944 | K43: =IF(OR(YEAR(A43)=2008, YEAR(A43)=2009), "", B43) -> 0.011078126
A44: =Data!A44 -> 39294 | B44: =Data!E44 - Factors!AB46 -> 0.0041229099 | C44: =Factors!Z46 -> 0.022550604 | D44: =Factors!J46 -> 0.0019128344 | E44: =Factors!N46 - Factors!D46 -> -0.039741875 | F44: =Factors!E46 -> 0.020308133 | H44: {=TREND(B8:B43, C8:F43, C44:F44, TRUE)} -> -0.0010215555 | I44: =B44 - H44 -> 0.0051444655 | J44: =IF(OR(YEAR(A44)=2008, YEAR(A44)=2009), "", I44) -> 0.0051444655 | K44: =IF(OR(YEAR(A44)=2008, YEAR(A44)=2009), "", B44) -> 0.0041229099
A45: =Data!A45 -> 39325 | B45: =Data!E45 - Factors!AB47 -> -0.026040932 | C45: =Factors!Z47 -> 0.013548096 | D45: =Factors!J47 -> -0.021834293 | E45: =Factors!N47 - Factors!D47 -> -0.0011101182 | F45: =Factors!E47 -> 0.012312678 | H45: {=TREND(B9:B44, C9:F44, C45:F45, TRUE)} -> -0.017235676 | I45: =B45 - H45 -> -0.0088052568 | J45: =IF(OR(YEAR(A45)=2008, YEAR(A45)=2009), "", I45) -> -0.0088052568 | K45: =IF(OR(YEAR(A45)=2008, YEAR(A45)=2009), "", B45) -> -0.026040932
A46: =Data!A46 -> 39353 | B46: =Data!E46 - Factors!AB48 -> 0.028787166 | C46: =Factors!Z48 -> 0.10441111 | D46: =Factors!J48 -> 0.018790038 | E46: =Factors!N48 - Factors!D48 -> 0.016853228 | F46: =Factors!E48 -> 0.022443581 | H46: {=TREND(B10:B45, C10:F45, C46:F46, TRUE)} -> 0.018180566 | I46: =B46 - H46 -> 0.0106066 | J46: =IF(OR(YEAR(A46)=2008, YEAR(A46)=2009), "", I46) -> 0.0106066 | K46: =IF(OR(YEAR(A46)=2008, YEAR(A46)=2009), "", B46) -> 0.028787166
A47: =Data!A47 -> 39386 | B47: =Data!E47 - Factors!AB49 -> 0.029567013 | C47: =Factors!Z49 -> 0.071543841 | D47: =Factors!J49 -> 0.030656165 | E47: =Factors!N49 - Factors!D49 -> -0.0029284122 | F47: =Factors!E49 -> 0.016299287 | H47: {=TREND(B11:B46, C11:F46, C47:F47, TRUE)} -> 0.026441139 | I47: =B47 - H47 -> 0.003125874 | J47: =IF(OR(YEAR(A47)=2008, YEAR(A47)=2009), "", I47) -> 0.003125874 | K47: =IF(OR(YEAR(A47)=2008, YEAR(A47)=2009), "", B47) -> 0.029567013
A48: =Data!A48 -> 39416 | B48: =Data!E48 - Factors!AB50 -> -0.012781413 | C48: =Factors!Z50 -> -0.016629016 | D48: =Factors!J50 -> -0.014675704 | E48: =Factors!N50 - Factors!D50 -> -0.03844679 | F48: =Factors!E50 -> 0.019110525 | H48: {=TREND(B12:B47, C12:F47, C48:F48, TRUE)} -> -0.014508752 | I48: =B48 - H48 -> 0.0017273389 | J48: =IF(OR(YEAR(A48)=2008, YEAR(A48)=2009), "", I48) -> 0.0017273389 | K48: =IF(OR(YEAR(A48)=2008, YEAR(A48)=2009), "", B48) -> -0.012781413
A49: =Data!A49 -> 39447 | B49: =Data!E49 - Factors!AB51 -> 0.0070711374 | C49: =Factors!Z51 -> 0.064003573 | D49: =Factors!J51 -> 0.0033379196 | E49: =Factors!N51 - Factors!D51 -> 0.00012305996 | F49: =Factors!E51 -> -0.002981283 | H49: {=TREND(B13:B48, C13:F48, C49:F49, TRUE)} -> 0.0056531356 | I49: =B49 - H49 -> 0.0014180018 | J49: =IF(OR(YEAR(A49)=2008, YEAR(A49)=2009), "", I49) -> 0.0014180018 | K49: =IF(OR(YEAR(A49)=2008, YEAR(A49)=2009), "", B49) -> 0.0070711374
... A121: =Data!A121 -> 41639 | B121: =Data!E121 - Factors!AB123 -> 0.0046525741 | C121: =Factors!Z123 -> -0.04125743 | D121: =Factors!J123 -> 0.015226749 | E121: =Factors!N123 - Factors!D123 -> 0.01113092 | F121: =Factors!E123 -> -0.005970907 | H121: {=TREND(B85:B120, C85:F120, C121:F121, TRUE)} -> 0.010484598 | I121: =B121 - H121 -> -0.0058320241 | J121: =IF(OR(YEAR(A121)=2008, YEAR(A121)=2009), "", I121) -> -0.0058320241 | K121: =IF(OR(YEAR(A121)=2008, YEAR(A121)=2009), "", B121) -> 0.0046525741

Sheet A5_3factor
A1: Date | B1: xAsset5 | C1: TIPs | D1: Relative Value HF | E1: High Yield | G1: Predicted | H1: Residual | I1: Resid_ex0809 | J1: xAsset_ex0809 | L1: Factor | M1: R^2 aux | N1: VIF
A2: =Data!A2 -> 38016 | B2: =Data!F2 - Factors!AB4 -> 0.011096091 | C2: =Factors!M4 -> 0.012326082 | D2: =Factors!K4 -> 0.012109999 | E2: =Factors!N4 -> 0.016153008 | L2: TIPs | M2: =INDEX(LINEST(C2:C121, D2:E121, TRUE, TRUE), 3, 1) -> 0.070013672 | N2: =1/(1-M2) -> 1.0752846
A3: =Data!A3 -> 38044 | B3: =Data!F3 - Factors!AB5 -> 0.023027653 | C3: =Factors!M5 -> 0.024775375 | D3: =Factors!K5 -> 0.0055000077 | E3: =Factors!N5 -> -0.001096591 | L3: RelativeValueHF | M3: =INDEX(LINEST(D2:D121, CHOOSE({1,2}, C2:C121, E2:E121), TRUE, TRUE), 3, 1) -> 0.72829004 | N3: =1/(1-M3) -> 3.6803951
A4: =Data!A4 -> 38077 | B4: =Data!F4 - Factors!AB6 -> 0.015724601 | C4: =Factors!M6 -> 0.017390173 | D4: =Factors!K6 -> 0.0043299894 | E4: =Factors!N6 -> 0.0066713818 | L4: High Yield | M4: =INDEX(LINEST(E2:E121, C2:D121, TRUE, TRUE), 3, 1) -> 0.73634075 | N4: =1/(1-M4) -> 3.7927741
A5: =Data!A5 -> 38107 | B5: =Data!F5 - Factors!AB7 -> -0.044654521 | C5: =Factors!M7 -> -0.046496063 | D5: =Factors!K7 -> -0.0050599988 | E5: =Factors!N7 -> -0.0066013073 | G5: SUMMARY OUTPUT
A6: =Data!A6 -> 38138 | B6: =Data!F6 - Factors!AB8 -> 0.014467795 | C6: =Factors!M8 -> 0.016443736 | D6: =Factors!K8 -> -0.0034499938 | E6: =Factors!N8 -> -0.015711509
A7: =Data!A7 -> 38168 | B7: =Data!F7 - Factors!AB9 -> -0.0020867511 | C7: =Factors!M9 -> -0.0026148152 | D7: =Factors!K9 -> 0.0016100011 | E7: =Factors!N9 -> 0.014527413 | G7: Regression Statistics
A8: =Data!A8 -> 38198 | B8: =Data!F8 - Factors!AB10 -> 0.013772822 | C8: =Factors!M10 -> 0.016134553 | D8: =Factors!K10 -> 0.0065199865 | E8: =Factors!N10 -> 0.013476433 | G8: Multiple R | H8: 0.98179388
A9: =Data!A9 -> 38230 | B9: =Data!F9 - Factors!AB11 -> 0.022482399 | C9: =Factors!M11 -> 0.025976512 | D9: =Factors!K11 -> 0.0082500151 | E9: =Factors!N11 -> 0.018171957 | G9: R Square | H9: 0.96391922
A10: =Data!A10 -> 38260 | B10: =Data!F10 - Factors!AB12 -> 0.0010415318 | C10: =Factors!M12 -> 0.0015744976 | D10: =Factors!K12 -> 0.003559986 | E10: =Factors!N12 -> 0.013931553 | G10: Adjusted R Square | H10: 0.96298609
A11: =Data!A11 -> 38289 | B11: =Data!F11 - Factors!AB13 -> 0.012832717 | C11: =Factors!M13 -> 0.014200355 | D11: =Factors!K13 -> 0.0031099991 | E11: =Factors!N13 -> 0.019280206 | G11: Standard Error | H11: 0.0039725188
A12: =Data!A12 -> 38321 | B12: =Data!F12 - Factors!AB14 -> -0.0059628895 | C12: =Factors!M14 -> -0.0070595322 | D12: =Factors!K14 -> 0.010670007 | E12: =Factors!N14 -> 0.01040404 | G12: Observations | H12: 120
A13: =Data!A13 -> 38352 | B13: =Data!F13 - Factors!AB15 -> 0.010277841 | C13: =Factors!M15 -> 0.013768153 | D13: =Factors!K15 -> 0.0074600062 | E13: =Factors!N15 -> 0.015081436
A14: =Data!A14 -> 38383 | B14: =Data!F14 - Factors!AB16 -> 0.00064688463 | C14: =Factors!M16 -> 0.0054076539 | D14: =Factors!K16 -> 0.0030099913 | E14: =Factors!N16 -> -0.001018961 | G14: ANOVA
A15: =Data!A15 -> 38411 | B15: =Data!F15 - Factors!AB17 -> -0.0074695158 | C15: =Factors!M17 -> -0.0071714246 | D15: =Factors!K17 -> 0.0078299976 | E15: =Factors!N17 -> 0.014283982 | H15: df | I15: SS | J15: MS | K15: F | L15: Significance F
A16: =Data!A16 -> 38442 | B16: =Data!F16 - Factors!AB18 -> -0.0051539433 | C16: =Factors!M18 -> -0.0044377509 | D16: =Factors!K18 -> -0.0034999927 | E16: =Factors!N18 -> -0.027312914 | G16: Regression | H16: 3 | I16: 0.048905147 | J16: 0.016301716 | K16: 1033.0026 | L16: 1.7828934e-83
A17: =Data!A17 -> 38471 | B17: =Data!F17 - Factors!AB19 -> 0.019528423 | C17: =Factors!M19 -> 0.025283828 | D17: =Factors!K19 -> -0.0084399998 | E17: =Factors!N19 -> -0.010727702 | G17: Residual | H17: 116 | I17: 0.001830585 | J17: 1.5780905e-05
A18: =Data!A18 -> 38503 | B18: =Data!F18 - Factors!AB20 -> 0.0032890235 | C18: =Factors!M20 -> 0.0069189282 | D18: =Factors!K20 -> -0.001040004 | E18: =Factors!N20 -> 0.017902944 | G18: Total | H18: 119 | I18: 0.050735732
A19: =Data!A19 -> 38533 | B19: =Data!F19 - Factors!AB21 -> 0.00085154205 | C19: =Factors!M21 -> 0.0036562031 | D19: =Factors!K21 -> 0.00959001 | E19: =Factors!N21 -> 0.019031055
A20: =Data!A20 -> 38562 | B20: =Data!F20 - Factors!AB22 -> -0.019395522 | C20: =Factors!M22 -> -0.018193158 | D20: =Factors!K22 -> 0.013399988 | E20: =Factors!N22 -> 0.015700184 | H20: Coefficients | I20: Standard Error | J20: t Stat | K20: P-value | L20: Lower 95% | M20: Upper 95% | N20: Lower 95.0% | O20: Upper 95.0%
A21: =Data!A21 -> 38595 | B21: =Data!F21 - Factors!AB23 -> 0.019822141 | C21: =Factors!M23 -> 0.024976539 | D21: =Factors!K23 -> 0.0069099986 | E21: =Factors!N23 -> 0.0036197695 | G21: Intercept | H21: -0.0013749023 | I21: 0.00039547444 | J21: -3.4765895 | K21: 0.0007155063 | L21: -0.0021581892 | M21: -0.00059161533 | N21: -0.0021581892 | O21: -0.00059161533
A22: =Data!A22 -> 38625 | B22: =Data!F22 - Factors!AB24 -> -0.0063266938 | C22: =Factors!M24 -> -0.0052538911 | D22: =Factors!K24 -> 0.011750014 | E22: =Factors!N24 -> -0.010014797 | G22: TIPs | H22: 0.90932564 | I22: 0.017945656 | J22: 50.671072 | K22: 5.6433247e-81 | L22: 0.87378201 | M22: 0.94486927 | N22: 0.87378201 | O22: 0.94486927
A23: =Data!A23 -> 38656 | B23: =Data!F23 - Factors!AB25 -> -0.014666621 | C23: =Factors!M25 -> -0.012573985 | D23: =Factors!K25 -> -0.003550002 | E23: =Factors!N25 -> -0.0072941845 | G23: Relative Value HF | H23: -0.1227804 | I23: 0.048781905 | J23: -2.5169251 | K23: 0.013203982 | L23: -0.21939911 | M23: -0.026161691 | N23: -0.21939911 | O23: -0.026161691
A24: =Data!A24 -> 38686 | B24: =Data!F24 - Factors!AB26 -> -0.0015948266 | C24: =Factors!M26 -> 0.0019717785 | D24: =Factors!K26 -> 0.0082399924 | E24: =Factors!N26 -> 0.0048246766 | G24: High Yield | H24: 0.15794486 | I24: 0.023757199 | J24: 6.6482947 | K24: 1.0171386e-09 | L24: 0.11089073 | M24: 0.20499899 | N24: 0.11089073 | O24: 0.20499899
A25: =Data!A25 -> 38716 | B25: =Data!F25 - Factors!AB27 -> 0.0045252174 | C25: =Factors!M27 -> 0.0084798523 | D25: =Factors!K27 -> 0.014750003 | E25: =Factors!N27 -> 0.0091542824
A26: =Data!A26 -> 38748 | B26: =Data!F26 - Factors!AB28 -> -0.0021828452 | C26: =Factors!M28 -> 0.00078054042 | D26: =Factors!K28 -> 0.021990006 | E26: =Factors!N28 -> 0.01584954
A27: =Data!A27 -> 38776 | B27: =Data!F27 - Factors!AB29 -> -0.0061157804 | C27: =Factors!M29 -> -0.0034033381 | D27: =Factors!K29 -> 0.0062299896 | E27: =Factors!N29 -> 0.0063223564
A28: =Data!A28 -> 38807 | B28: =Data!F28 - Factors!AB30 -> -0.02057989 | C28: =Factors!M30 -> -0.020532449 | D28: =Factors!K30 -> 0.013340008 | E28: =Factors!N30 -> 0.0062504846
A29: =Data!A29 -> 38835 | B29: =Data!F29 - Factors!AB31 -> -0.0012021032 | C29: =Factors!M31 -> 0.00010169098 | D29: =Factors!K31 -> 0.011150001 | E29: =Factors!N31 -> 0.0064259187
A30: =Data!A30 -> 38868 | B30: =Data!F30 - Factors!AB32 -> -0.0017257024 | C30: =Factors!M32 -> 0.0021352933 | D30: =Factors!K32 -> 0.0020399909 | E30: =Factors!N32 -> -0.00063120585 | H30: OOS R Square | I30: =1 - SUMSQ(H38:H121) / DEVSQ(B38:B121) -> 0.93509034
A31: =Data!A31 -> 38898 | B31: =Data!F31 - Factors!AB33 -> 0.00015052875 | C31: =Factors!M33 -> 0.0035947239 | D31: =Factors!K33 -> 0.0055200083 | E31: =Factors!N33 -> -0.0037914958 | H31: OOS RMSE | I31: =SQRT( SUMSQ(H38:H121) / COUNT(H38:H121) ) -> 0.0057839382
A32: =Data!A32 -> 38929 | B32: =Data!F32 - Factors!AB34 -> 0.010643188 | C32: =Factors!M34 -> 0.016696034 | D32: =Factors!K34 -> 0.0041799914 | E32: =Factors!N34 -> 0.010669348 | H32: ex0809 OOS R^2 | I32: =1 - SUMSQ(I38:I121) / DEVSQ(J38:J121) -> 0.97206871
A33: =Data!A33 -> 38960 | B33: =Data!F33 - Factors!AB35 -> 0.011870238 | C33: =Factors!M35 -> 0.018765804 | D33: =Factors!K35 -> 0.0071100053 | E33: =Factors!N35 -> 0.016180281
A34: =Data!A34 -> 38989 | B34: =Data!F34 - Factors!AB36 -> -0.0012218407 | C34: =Factors!M36 -> 0.0025169072 | D34: =Factors!K36 -> 0.0036999919 | E34: =Factors!N36 -> 0.013153809
A35: =Data!A35 -> 39021 | B35: =Data!F35 - Factors!AB37 -> -0.0060934197 | C35: =Factors!M37 -> -0.0015995438 | D35: =Factors!K37 -> 0.012270006 | E35: =Factors!N37 -> 0.014601856
A36: =Data!A36 -> 39051 | B36: =Data!F36 - Factors!AB38 -> 0.0071053827 | C36: =Factors!M38 -> 0.012412842 | D36: =Factors!K38 -> 0.013730003 | E36: =Factors!N38 -> 0.015962361
A37: =Data!A37 -> 39080 | B37: =Data!F37 - Factors!AB39 -> -0.026965697 | C37: =Factors!M39 -> -0.024954762 | D37: =Factors!K39 -> 0.016109996 | E37: =Factors!N39 -> 0.01100894 | G37: 36 Month Rolling
A38: =Data!A38 -> 39113 | B38: =Data!F38 - Factors!AB40 -> -0.0014838815 | C38: =Factors!M40 -> 0.0023074318 | D38: =Factors!K40 -> 0.01366871 | E38: =Factors!N40 -> 0.01074376 | G38: {=TREND(B2:B37, C2:E37, C38:E38, TRUE)} -> -0.00034293177 | H38: =B38 - G38 -> -0.0011409497 | I38: =IF(OR(YEAR(A38)=2008, YEAR(A38)=2009), "", H38) -> -0.0011409497 | J38: =IF(OR(YEAR(A38)=2008, YEAR(A38)=2009), "", B38) -> -0.0014838815
A39: =Data!A39 -> 39141 | B39: =Data!F39 - Factors!AB41 -> 0.017089466 | C39: =Factors!M41 -> 0.022753673 | D39: =Factors!K41 -> 0.0075626638 | E39: =Factors!N41 -> 0.013929155 | G39: {=TREND(B3:B38, C3:E38, C39:E39, TRUE)} -> 0.018404436 | H39: =B39 - G39 -> -0.00131497 | I39: =IF(OR(YEAR(A39)=2008, YEAR(A39)=2009), "", H39) -> -0.00131497 | J39: =IF(OR(YEAR(A39)=2008, YEAR(A39)=2009), "", B39) -> 0.017089466
A40: =Data!A40 -> 39171 | B40: =Data!F40 - Factors!AB42 -> 0.00034742056 | C40: =Factors!M42 -> 0.0030425056 | D40: =Factors!K42 -> 0.0075347265 | E40: =Factors!N42 -> 0.0023225471 | G40: {=TREND(B4:B39, C4:E39, C40:E40, TRUE)} -> 0.00021814542 | H40: =B40 - G40 -> 0.00012927514 | I40: =IF(OR(YEAR(A40)=2008, YEAR(A40)=2009), "", H40) -> 0.00012927514 | J40: =IF(OR(YEAR(A40)=2008, YEAR(A40)=2009), "", B40) -> 0.00034742056
A41: =Data!A41 -> 39202 | B41: =Data!F41 - Factors!AB43 -> 0.0036137696 | C41: =Factors!M43 -> 0.0078096584 | D41: =Factors!K43 -> 0.014190543 | E41: =Factors!N43 -> 0.013232766 | G41: {=TREND(B5:B40, C5:E40, C41:E41, TRUE)} -> 0.0042312246 | H41: =B41 - G41 -> -0.00061745491 | I41: =IF(OR(YEAR(A41)=2008, YEAR(A41)=2009), "", H41) -> -0.00061745491 | J41: =IF(OR(YEAR(A41)=2008, YEAR(A41)=2009), "", B41) -> 0.0036137696
A42: =Data!A42 -> 39233 | B42: =Data!F42 - Factors!AB44 -> -0.018720259 | C42: =Factors!M44 -> -0.016758027 | D42: =Factors!K44 -> 0.014873413 | E42: =Factors!N44 -> 0.007114995 | G42: {=TREND(B6:B41, C6:E41, C42:E42, TRUE)} -> -0.017861264 | H42: =B42 - G42 -> -0.0008589953 | I42: =IF(OR(YEAR(A42)=2008, YEAR(A42)=2009), "", H42) -> -0.0008589953 | J42: =IF(OR(YEAR(A42)=2008, YEAR(A42)=2009), "", B42) -> -0.018720259
A43: =Data!A43 -> 39262 | B43: =Data!F43 - Factors!AB45 -> -0.0056159441 | C43: =Factors!M45 -> -0.0023823705 | D43: =Factors!K45 -> 0.0056216336 | E43: =Factors!N45 -> -0.016854025 | G43: {=TREND(B7:B42, C7:E42, C43:E43, TRUE)} -> -0.0051672132 | H43: =B43 - G43 -> -0.00044873084 | I43: =IF(OR(YEAR(A43)=2008, YEAR(A43)=2009), "", H43) -> -0.00044873084 | J43: =IF(OR(YEAR(A43)=2008, YEAR(A43)=2009), "", B43) -> -0.0056159441
A44: =Data!A44 -> 39294 | B44: =Data!F44 - Factors!AB46 -> 0.019022065 | C44: =Factors!M46 -> 0.023700104 | D44: =Factors!K46 -> -0.0058038811 | E44: =Factors!N46 -> -0.031400492 | G44: {=TREND(B8:B43, C8:E43, C44:E44, TRUE)} -> 0.018423625 | H44: =B44 - G44 -> 0.00059844023 | I44: =IF(OR(YEAR(A44)=2008, YEAR(A44)=2009), "", H44) -> 0.00059844023 | J44: =IF(OR(YEAR(A44)=2008, YEAR(A44)=2009), "", B44) -> 0.019022065
A45: =Data!A45 -> 39325 | B45: =Data!F45 - Factors!AB47 -> 0.0052633422 | C45: =Factors!M47 -> 0.01334563 | D45: =Factors!K47 -> -0.006881385 | E45: =Factors!N47 -> 0.011146386 | G45: {=TREND(B9:B44, C9:E44, C45:E45, TRUE)} -> 0.0097500693 | H45: =B45 - G45 -> -0.0044867271 | I45: =IF(OR(YEAR(A45)=2008, YEAR(A45)=2009), "", H45) -> -0.0044867271 | J45: =IF(OR(YEAR(A45)=2008, YEAR(A45)=2009), "", B45) -> 0.0052633422
A46: =Data!A46 -> 39353 | B46: =Data!F46 - Factors!AB48 -> 0.0065596174 | C46: =Factors!M48 -> 0.0088736014 | D46: =Factors!K48 -> 0.013501838 | E46: =Factors!N48 -> 0.024439569 | G46: {=TREND(B10:B45, C10:E45, C46:E46, TRUE)} -> 0.0047899194 | H46: =B46 - G46 -> 0.0017696979 | I46: =IF(OR(YEAR(A46)=2008, YEAR(A46)=2009), "", H46) -> 0.0017696979 | J46: =IF(OR(YEAR(A46)=2008, YEAR(A46)=2009), "", B46) -> 0.0065596174
A47: =Data!A47 -> 39386 | B47: =Data!F47 - Factors!AB49 -> 0.011182572 | C47: =Factors!M49 -> 0.013770414 | D47: =Factors!K49 -> 0.021002545 | E47: =Factors!N49 -> 0.0060544718 | G47: {=TREND(B11:B46, C11:E46, C47:E47, TRUE)} -> 0.0098813231 | H47: =B47 - G47 -> 0.001301249 | I47: =IF(OR(YEAR(A47)=2008, YEAR(A47)=2009), "", H47) -> 0.001301249 | J47: =IF(OR(YEAR(A47)=2008, YEAR(A47)=2009), "", B47) -> 0.011182572
A48: =Data!A48 -> 39416 | B48: =Data!F48 - Factors!AB50 -> 0.040146906 | C48: =Factors!M50 -> 0.046900559 | D48: =Factors!K50 -> -0.0053199226 | E48: =Factors!N50 -> -0.02046365 | G48: {=TREND(B12:B47, C12:E47, C48:E48, TRUE)} -> 0.03915388 | H48: =B48 - G48 -> 0.00099302594 | I48: =IF(OR(YEAR(A48)=2008, YEAR(A48)=2009), "", H48) -> 0.00099302594 | J48: =IF(OR(YEAR(A48)=2008, YEAR(A48)=2009), "", B48) -> 0.040146906
A49: =Data!A49 -> 39447 | B49: =Data!F49 - Factors!AB51 -> -0.0047841932 | C49: =Factors!M51 -> -0.0046936913 | D49: =Factors!K51 -> 0.00643647 | E49: =Factors!N51 -> 0.0029318245 | G49: {=TREND(B13:B48, C13:E48, C49:E49, TRUE)} -> -0.0073251429 | H49: =B49 - G49 -> 0.0025409497 | I49: =IF(OR(YEAR(A49)=2008, YEAR(A49)=2009), "", H49) -> 0.0025409497 | J49: =IF(OR(YEAR(A49)=2008, YEAR(A49)=2009), "", B49) -> -0.0047841932
... A121: =Data!A121 -> 41639 | B121: =Data!F121 - Factors!AB123 -> -0.020900099 | C121: =Factors!M123 -> -0.020891371 | D121: =Factors!K123 -> 0.0076849904 | E121: =Factors!N123 -> 0.0054797726 | G121: {=TREND(B85:B120, C85:E120, C121:E121, TRUE)} -> -0.018211859 | H121: =B121 - G121 -> -0.0026882404 | I121: =IF(OR(YEAR(A121)=2008, YEAR(A121)=2009), "", H121) -> -0.0026882404 | J121: =IF(OR(YEAR(A121)=2008, YEAR(A121)=2009), "", B121) -> -0.020900099

Sheet Project_Page_1
B2: Inputs:
B3: Yearly Return | C3: =Project_Page_3!I4 -> 0.062135224 | D3: This mean return is geometric mean of the monthy return of equal weighted protfolio.
B4: Initial Wealth | C4: 18000000
B5: Yearly Spending | C5: 0.02
B6: Annual Salary | C6: 200000 | D6: Paid for first 5 years (months 1-60), then $0
B7: Retirement Month | C7: 60 | D7: Month salary stops (after month C7, salary = 0)
B9: Historical Simulation (2004–2013, Monthly Rebalancing)
B11: Month | C11: Date | D11: Monthly Return | E11: Salary | F11: Wealth (End of Month) | G11: Running Peak | H11: Drawdown
B12: 0 | C12: Start | E12: 0 | F12: =C4 -> 18000000 | G12: =F12 -> 18000000 | H12: 0
B13: =B12+1 -> 1 | C13: =Project_Page_3!A4 -> 38016 | D13: =Project_Page_3!G4 -> 0.018386675 | E13: =IF(B13<=$C$7,$C$6/12,0) -> 16666.667 | F13: =F12*(1+D13)-F12*($C$5/12)+E13 -> 18317627 | G13: =MAX(G12,F13) -> 18317627 | H13: =(F13-G13)/G13 -> 0
B14: =B13+1 -> 2 | C14: =Project_Page_3!A5 -> 38044 | D14: =Project_Page_3!G5 -> 0.020723036 | E14: =IF(B14<=$C$7,$C$6/12,0) -> 16666.667 | F14: =F13*(1+D14)-F13*($C$5/12)+E14 -> 18683361 | G14: =MAX(G13,F14) -> 18683361 | H14: =(F14-G14)/G14 -> 0
B15: =B14+1 -> 3 | C15: =Project_Page_3!A6 -> 38077 | D15: =Project_Page_3!G6 -> 0.00037386828 | E15: =IF(B15<=$C$7,$C$6/12,0) -> 16666.667 | F15: =F14*(1+D15)-F14*($C$5/12)+E15 -> 18675874 | G15: =MAX(G14,F15) -> 18683361 | H15: =(F15-G15)/G15 -> -0.00040073904
B16: =B15+1 -> 4 | C16: =Project_Page_3!A7 -> 38107 | D16: =Project_Page_3!G7 -> -0.044443735 | E16: =IF(B16<=$C$7,$C$6/12,0) -> 16666.667 | F16: =F15*(1+D16)-F15*($C$5/12)+E16 -> 17831388 | G16: =MAX(G15,F16) -> 18683361 | H16: =(F16-G16)/G16 -> -0.045600603
B17: =B16+1 -> 5 | C17: =Project_Page_3!A8 -> 38138 | D17: =Project_Page_3!G8 -> 0.019877074 | E17: =IF(B17<=$C$7,$C$6/12,0) -> 16666.667 | F17: =F16*(1+D17)-F16*($C$5/12)+E17 -> 18172772 | G17: =MAX(G16,F17) -> 18683361 | H17: =(F17-G17)/G17 -> -0.027328541
B18: =B17+1 -> 6 | C18: =Project_Page_3!A9 -> 38168 | D18: =Project_Page_3!G9 -> 0.0061192547 | E18: =IF(B18<=$C$7,$C$6/12,0) -> 16666.667 | F18: =F17*(1+D18)-F17*($C$5/12)+E18 -> 18270354 | G18: =MAX(G17,F18) -> 18683361 | H18: =(F18-G18)/G18 -> -0.022105577
B19: =B18+1 -> 7 | C19: =Project_Page_3!A10 -> 38198 | D19: =Project_Page_3!G10 -> -0.0070648619 | E19: =IF(B19<=$C$7,$C$6/12,0) -> 16666.667 | F19: =F18*(1+D19)-F18*($C$5/12)+E19 -> 18127493 | G19: =MAX(G18,F19) -> 18683361 | H19: =(F19-G19)/G19 -> -0.029752031
B20: =B19+1 -> 8 | C20: =Project_Page_3!A11 -> 38230 | D20: =Project_Page_3!G11 -> -0.0081745899 | E20: =IF(B20<=$C$7,$C$6/12,0) -> 16666.667 | F20: =F19*(1+D20)-F19*($C$5/12)+E20 -> 17965762 | G20: =MAX(G19,F20) -> 18683361 | H20: =(F20-G20)/G20 -> -0.03840843
B21: =B20+1 -> 9 | C21: =Project_Page_3!A12 -> 38260 | D21: =Project_Page_3!G12 -> 0.032582951 | E21: =IF(B21<=$C$7,$C$6/12,0) -> 16666.667 | F21: =F20*(1+D21)-F20*($C$5/12)+E21 -> 18537864 | G21: =MAX(G20,F21) -> 18683361 | H21: =(F21-G21)/G21 -> -0.0077875328
B22: =B21+1 -> 10 | C22: =Project_Page_3!A13 -> 38289 | D22: =Project_Page_3!G13 -> 0.0081611922 | E22: =IF(B22<=$C$7,$C$6/12,0) -> 16666.667 | F22: =F21*(1+D22)-F21*($C$5/12)+E22 -> 18674925 | G22: =MAX(G21,F22) -> 18683361 | H22: =(F22-G22)/G22 -> -0.0004515242
B23: =B22+1 -> 11 | C23: =Project_Page_3!A14 -> 38321 | D23: =Project_Page_3!G14 -> 0.024102779 | E23: =IF(B23<=$C$7,$C$6/12,0) -> 16666.667 | F23: =F22*(1+D23)-F22*($C$5/12)+E23 -> 19110584 | G23: =MAX(G22,F23) -> 19110584 | H23: =(F23-G23)/G23 -> 0
B24: =B23+1 -> 12 | C24: =Project_Page_3!A15 -> 38352 | D24: =Project_Page_3!G15 -> 0.02094335 | E24: =IF(B24<=$C$7,$C$6/12,0) -> 16666.667 | F24: =F23*(1+D24)-F23*($C$5/12)+E24 -> 19495640 | G24: =MAX(G23,F24) -> 19495640 | H24: =(F24-G24)/G24 -> 0
... B132: =B131+1 -> 120 | C132: =Project_Page_3!A123 -> 41639 | D132: =Project_Page_3!G123 -> 0.01388093 | E132: =IF(B132<=$C$7,$C$6/12,0) -> 0 | F132: =F131*(1+D132)-F131*($C$5/12)+E132 -> 28205038 | G132: =MAX(G131,F132) -> 29561724 | H132: =(F132-G132)/G132 -> -0.045893359
B134: Simulation Summary
B135: Starting Wealth | C135: =F12 -> 18000000
B136: Ending Wealth (Dec-13) | C136: =F132 -> 28205038
B137: Total Return (cumulative) | C137: =F132/F12-1 -> 0.56694653
B138: Annualized Return (CAGR) | C138: =(F132/F12)^(1/10)-1 -> 0.045936738
B139: Geometric Mean Monthly Return | C139: {=GEOMEAN(1+D13:D132)-1} -> 0.0050360756
B140: Annualized Geo Mean (from monthly) | C140: =(1+C139)^12-1 -> 0.062135224
B141: Monthly Return Std Dev | C141: =STDEV(D13:D132) -> 0.024248535
B142: Annualized Volatility | C142: =C141*SQRT(12) -> 0.083999388
B143: Min Monthly Return | C143: =MIN(D13:D132) -> -0.10746518
B144: Max Monthly Return | C144: =MAX(D13:D132) -> 0.062360912
B145: Max Drawdown | C145: =MIN(H13:H132) -> -0.24691946
B146: Downside Deviation (monthly, annualised) | C146: {=SQRT(SUMPRODUCT((D13:D132<0)*D13:D132^2)/60)*SQRT(12)} -> 0.078650661
B147: Sortino Ratio | C147: =C140/C146 -> 0.79001528
B148: Omega Ratio (threshold = 6.02% p.a.) | C148: {=SUMPRODUCT((D13:D132>(1.0602^(1/12)-1))*((D13:D132-(1.0602^(1/12)-1))))/SUMPRODUCT((D13:D132<(1.0602^(1/12)-1))*((1.0602^(1/12)-1)-D13:D132))} -> 1.0507365
B149: Ulcer Index | C149: {=SQRT(SUMPRODUCT(H13:H132^2)/60)} -> 0.088756185
B150: Ulcer Performance Index (Rf = cash) | C150: {=(C140-((GEOMEAN(1+Factors!AB4:AB123)^12)-1))/C149} -> 0.52091484
B151: Sharpe Ratio (monthly) | C151: =(C139 - AVERAGE(Factors!AB4:AB123)) / C141 -> 0.15338502
B152: Sharpe Ratio (annualized) | C152: =C151 *SQRT(12) -> 0.5313413
B153: Skewness | C153: =SKEW(D13:D132) -> -0.93395702
B154: Excess kurtosis | C154: =KURT(D13:D132) -> 3.4420508
B155: Jarque-Bera stat | C155: =120/6 * (C153^2 + C154^2/4) -> 76.684081
B156: JB p-value | C156: =_xlfn.CHISQ.DIST.RT(C155, 2) -> 2.2297867e-17
B157: Normality | C157: =IF(C156<0.05, "REJECT", "PASS") -> REJECT
B158: 95% historical VaR | C158: =_xlfn.PERCENTILE.INC(D13:D132, 0.05) -> -0.035031015
B159: 99% historical VaR | C159: =_xlfn.PERCENTILE.INC(D13:D132, 0.01) -> -0.058945619
B160: 95% historical CVaR | C160: =AVERAGEIF(D13:D132, "<="&C158) -> -0.056549147
B161: 99% historical CVaR | C161: =AVERAGEIF(D13:D132, "<="&C159) -> -0.084346645

Sheet Project_Page_2
B3: Asset 1 | C3: Factor | D3: R^2 aux | E3: VIF
C4: US AGG | D4: 0.69636819 | E4: 3.2934626
C5: EM Bond | D5: 0.79122174 | E5: 4.7897707
C6: Credit Spread | D6: 0.6418213 | E6: 2.7919025
B9: Asset 2 | C9: Factor | D9: R^2 aux | E9: VIF
C10: US Growth | D10: 0.22127521 | E10: 1.2841507
C11: Growth-Value | D11: 0.024522283 | E11: 1.0251387
C12: Small-S&P500 | D12: 0.21107913 | E12: 1.2675542
B15: Asset 3 | C15: Factors | D15: R^2 aux | E15: VIF
C16: Commodities | D16: 0.34946274 | E16: 1.537191
C17: Event Driven HF | D17: 0.35016791 | E17: 1.5388591
B20: Asset 4 | C20: Factors | D20: R^2 aux | E20: VIF
C21: Gold | D21: 0.091420223 | E21: 1.1006188
C22: HF FOF Div | D22: 0.12563652 | E22: 1.1436891
C23: HF FOF Div - Relative Value HF | D23: 0.024900212 | E23: 1.0255361
C24: Long Short HF - S&P500 | D24: 0.14358925 | E24: 1.167664
B27: Asset 5 | C27: Factor | D27: R^2 aux | E27: VIF
C28: TIPs | D28: 0.070013672 | E28: 1.0752846
C29: RelativeValueHF | D29: 0.72829004 | E29: 3.6803951
C30: High Yield | D30: 0.73634075 | E30: 3.7927741

Sheet Project_Page_3
W1: Asset 1 Factors | AM1: Asset 2 Factors | BC1: Asset 3 Factors | BR1: Asset 4 Factors | CI1: Asset 5 Factors
A2: Weighting | B2: 0.2 | C2: 0.2 | D2: 0.2 | E2: 0.2 | F2: 0.2 | N2: VaR-Covar | W2: =AC20 -> 0.59460301 | X2: =AC21 -> 0.052414433 | Y2: =AC22 -> -0.06979396 | Z2: 1 | AM2: =AS20 -> 1.101134 | AN2: =AS21 -> 0.45214917 | AO2: =AS22 -> 0.17417433 | AP2: 1 | BC2: =BH20 -> 0.68741539 | BD2: =BH21 -> 1.3398941 | BE2: 1 | BR2: =BY20 -> 0.088277653 | BS2: =BY21 -> 0.31472457 | BT2: =BY22 -> 0.75331525 | BU2: =BY23 -> 0.036420312 | BV2: 1 | CI2: =CO20 -> 0.90932564 | CJ2: =CO21 -> -0.1227804 | CK2: =CO22 -> 0.15794486 | CL2: 1
A3: Returns | B3: Asset 1 | C3: Asset 2 | D3: Asset 3 | E3: Asset 4 | F3: Asset 5 | G3: Equal-Weighting Assets Port. Return | I3: Weighted Yearly Mean Return | O3: Asset 1 | P3: Asset 2 | Q3: Asset 3 | R3: Asset 4 | S3: Asset 5 | W3: US AGG | X3: EM Bond | Y3: Credit Spread | Z3: Error | AB3: SUMMARY OUTPUT | AM3: US Growth | AN3: Growth - Value | AO3: Small - S&P500 | AP3: Error | AR3: SUMMARY OUTPUT | BC3: Commodities | BD3: Event Driven HF | BE3: Error | BG3: SUMMARY OUTPUT | BR3: Gold | BS3: HF FOF Div | BT3: HF FOF Div - Relative Value HF | BU3: Long Short HF - S&P500 | BV3: Error | BX3: SUMMARY OUTPUT | CI3: TIPs | CJ3: Relative Value HF | CK3: High Yield | CL3: Error | CN3: SUMMARY OUTPUT
A4: 38016 | B4: =Data!B2 -> 0.006265643 | C4: =Data!C2 -> 0.034770515 | D4: =Data!D2 -> 0.032609824 | E4: =Data!E2 -> 0.0064599983 | F4: =Data!F2 -> 0.011827397 | G4: =SUMPRODUCT($B$2:$F$2,B4:F4) -> 0.018386675 | I4: {=(GEOMEAN(1+G4:G123)^12)-1} -> 0.062135224 | M4: {=TRANSPOSE(B2:F2)} -> 0.2 | N4: Asset 1 | O4: =VARP($B$4:$B$123) -> 5.8133494e-05 | P4: =_xlfn.COVARIANCE.S($B$4:$B$123,$C$4:$C$123) -> -5.8006583e-05 | Q4: =_xlfn.COVARIANCE.S($B$4:$B$123,$D$4:$D$123) -> -3.8632081e-05 | R4: =_xlfn.COVARIANCE.S($B$4:$B$123,$E$4:$E$123) -> 3.494477e-06 | S4: =_xlfn.COVARIANCE.S($B$4:$B$123,$F$4:$F$123) -> 0.00010501967 | W4: 0.0080453023 | X4: 0.0051267546 | Y4: 0.0081077053 | Z4: =B4-SUMPRODUCT(W4:Y4, W$2:Y$2) -> 0.0017790349 | AM4: 0.020422332 | AN4: 0.002838608 | AO4: 0.025090927 | AP4: =C4-SUMPRODUCT(AM4:AO4, AM$2:AO$2) -> 0.0066291217 | BC4: 0.018131402 | BD4: 0.027989998 | BE4: =D4-SUMPRODUCT(BC4:BD4, BC$2:BD$2) -> -0.017357614 | BR4: -0.031291371 | BS4: 0.01538002 | BT4: 0.0032700206 | BU4: 0.0011450297 | BV4: =E4-SUMPRODUCT(BR4:BU4, BR$2:BU$2) -> 0.0018767982 | CI4: 0.012326082 | CJ4: 0.012109999 | CK4: 0.016153008 | CL4: =F4-SUMPRODUCT(CI4:CK4, CI$2:CK$2) -> -0.0004454391
A5: 38044 | B5: =Data!B3 -> 0.0084282173 | C5: =Data!C3 -> -0.032526882 | D5: =Data!D3 -> 0.083965425 | E5: =Data!E3 -> 0.019989996 | F5: =Data!F3 -> 0.023758424 | G5: =SUMPRODUCT($B$2:$F$2,B5:F5) -> 0.020723036 | M5: 0.2 | N5: Asset 2 | O5: =_xlfn.COVARIANCE.S($B$4:$B$123,$C$4:$C$123) -> -5.8006583e-05 | P5: =VARP($C$4:$C$123) -> 0.0028672049 | Q5: =_xlfn.COVARIANCE.S($C$4:$C$123,$D$4:$D$123) -> 0.0018845084 | R5: =_xlfn.COVARIANCE.S($C$4:$C$123,$E$4:$E$123) -> 0.00017045495 | S5: =_xlfn.COVARIANCE.S($C$4:$C$123,$F$4:$F$123) -> 0.00013861374 | W5: 0.010824142 | X5: 0.0034824821 | Y5: -0.011920733 | Z5: =B5-SUMPRODUCT(W5:Y5, W$2:Y$2) -> 0.00097762241 | AB5: Regression Statistics | AM5: 0.0063532895 | AN5: -0.01507851 | AO5: -0.0049351123 | AP5: =C5-SUMPRODUCT(AM5:AO5, AM$2:AO$2) -> -0.031845399 | AR5: Regression Statistics | BC5: 0.06488201 | BD5: 0.012020003 | BE5: =D5-SUMPRODUCT(BC5:BD5, BC$2:BD$2) -> 0.023259003 | BG5: Regression Statistics | BR5: -0.015654119 | BS5: 0.010909983 | BT5: 0.0054099752 | BU5: -0.002799445 | BV5: =E5-SUMPRODUCT(BR5:BU5, BR$2:BU$2) -> 0.013964805 | BX5: Regression Statistics | CI5: 0.024775375 | CJ5: 0.0055000077 | CK5: -0.001096591 | CL5: =F5-SUMPRODUCT(CI5:CK5, CI$2:CK$2) -> 0.0020780345 | CN5: Regression Statistics
A6: 38077 | B6: =Data!B4 -> 0.0043830411 | C6: =Data!C4 -> -0.026674076 | D6: =Data!D4 -> -0.003585315 | E6: =Data!E4 -> 0.01123 | F6: =Data!F4 -> 0.016515692 | G6: =SUMPRODUCT($B$2:$F$2,B6:F6) -> 0.00037386828 | M6: 0.2 | N6: Asset 3 | O6: =_xlfn.COVARIANCE.S($B$4:$B$123,$D$4:$D$123) -> -3.8632081e-05 | P6: =_xlfn.COVARIANCE.S($C$4:$C$123,$D$4:$D$123) -> 0.0018845084 | Q6: =VARP($D$4:$D$123) -> 0.0051488146 | R6: =_xlfn.COVARIANCE.S($D$4:$D$123,$E$4:$E$123) -> 0.00038588805 | S6: =_xlfn.COVARIANCE.S($D$4:$D$123,$F$4:$F$123) -> 0.00033336315 | W6: 0.0074889868 | X6: 0.024958811 | Y6: -0.00081760495 | Z6: =B6-SUMPRODUCT(W6:Y6, W$2:Y$2) -> -0.0014351988 | AB6: Multiple R | AC6: 0.90414418 | AM6: -0.01855019 | AN6: -0.0097981116 | AO6: 0.024405898 | AP6: =C6-SUMPRODUCT(AM6:AO6, AM$2:AO$2) -> -0.0060685041 | AR6: Multiple R | AS6: 0.94872255 | BC6: 0.030877435 | BD6: 0.00057999971 | BE6: =D6-SUMPRODUCT(BC6:BD6, BC$2:BD$2) -> -0.025588077 | BG6: Multiple R | BH6: 0.76428934 | BR6: 0.076486179 | BS6: 0.0044400219 | BT6: 0.00011003248 | BU6: 0.01867623 | BV6: =E6-SUMPRODUCT(BR6:BU6, BR$2:BU$2) -> 0.002317512 | BX6: Multiple R | BY6: 0.79179941 | CI6: 0.017390173 | CJ6: 0.0043299894 | CK6: 0.0066713818 | CL6: =F6-SUMPRODUCT(CI6:CK6, CI$2:CK$2) -> 0.00018028866 | CN6: Multiple R | CO6: 0.98179388
A7: 38107 | B7: =Data!B5 -> -0.017804105 | C7: =Data!C5 -> -0.046674279 | D7: =Data!D5 -> -0.085476236 | E7: =Data!E5 -> -0.028399998 | F7: =Data!F5 -> -0.043864055 | G7: =SUMPRODUCT($B$2:$F$2,B7:F7) -> -0.044443735 | M7: 0.2 | N7: Asset 4 | O7: =_xlfn.COVARIANCE.S($B$4:$B$123,$E$4:$E$123) -> 3.494477e-06 | P7: =_xlfn.COVARIANCE.S($C$4:$C$123,$E$4:$E$123) -> 0.00017045495 | Q7: =_xlfn.COVARIANCE.S($D$4:$D$123,$E$4:$E$123) -> 0.00038588805 | R7: =VARP($E$4:$E$123) -> 0.00019495628 | S7: =_xlfn.COVARIANCE.S($E$4:$E$123,$F$4:$F$123) -> 4.3873146e-05 | W7: -0.026016616 | X7: -0.054311023 | Y7: 0.019415308 | Z7: =B7-SUMPRODUCT(W7:Y7, W$2:Y$2) -> 0.0018672057 | AB7: R Square | AC7: 0.8174767 | AM7: -0.011625293 | AN7: 0.012814313 | AO7: -0.035285976 | AP7: =C7-SUMPRODUCT(AM7:AO7, AM$2:AO$2) -> -0.033521344 | AR7: R Square | AS7: 0.90007447 | BC7: -0.017736548 | BD7: -0.005619991 | BE7: =D7-SUMPRODUCT(BC7:BD7, BC$2:BD$2) -> -0.065753667 | BG7: R Square | BH7: 0.5841382 | BR7: -0.093094149 | BS7: -0.0070900013 | BT7: -0.0020300026 | BU7: -0.0050815692 | BV7: =E7-SUMPRODUCT(BR7:BU7, BR$2:BU$2) -> -0.016236163 | BX7: R Square | BY7: 0.62694631 | CI7: -0.046496063 | CJ7: -0.0050599988 | CK7: -0.0066013073 | CL7: =F7-SUMPRODUCT(CI7:CK7, CI$2:CK$2) -> -0.0011626185 | CN7: R Square | CO7: 0.96391922
A8: 38138 | B8: =Data!B6 -> -0.0021877217 | C8: =Data!C6 -> 0.049558317 | D8: =Data!D6 -> 0.043707136 | E8: =Data!E6 -> -0.0069499962 | F8: =Data!F6 -> 0.015257637 | G8: =SUMPRODUCT($B$2:$F$2,B8:F8) -> 0.019877074 | M8: 0.2 | N8: Asset 5 | O8: =_xlfn.COVARIANCE.S($B$4:$B$123,$F$4:$F$123) -> 0.00010501967 | P8: =_xlfn.COVARIANCE.S($C$4:$C$123,$F$4:$F$123) -> 0.00013861374 | Q8: =_xlfn.COVARIANCE.S($D$4:$D$123,$F$4:$F$123) -> 0.00033336315 | R8: =_xlfn.COVARIANCE.S($E$4:$E$123,$F$4:$F$123) -> 4.3873146e-05 | S8: =VARP($F$4:$F$123) -> 0.00042050091 | W8: -0.0040058707 | X8: -0.014827674 | Y8: -0.011705638 | Z8: =B8-SUMPRODUCT(W8:Y8, W$2:Y$2) -> 0.0001543823 | AB8: Adjusted R Square | AC8: 0.81275627 | AM8: 0.018638848 | AN8: 0.008440504 | AO8: 0.002193387 | AP8: =C8-SUMPRODUCT(AM8:AO8, AM$2:AO$2) -> 0.02483605 | AR8: Adjusted R Square | AS8: 0.89749019 | BC8: 0.016954736 | BD8: -0.0031200008 | BE8: =D8-SUMPRODUCT(BC8:BD8, BC$2:BD$2) -> 0.03623266 | BG8: Adjusted R Square | BH8: 0.57702945 | BR8: 0.022753717 | BS8: -0.008780017 | BT8: -0.0053300232 | BU8: -0.015632896 | BV8: =E8-SUMPRODUCT(BR8:BU8, BR$2:BU$2) -> -0.0016108111 | BX8: Adjusted R Square | BY8: 0.61397053 | CI8: 0.016443736 | CJ8: -0.0034499938 | CK8: -0.015711509 | CL8: =F8-SUMPRODUCT(CI8:CK8, CI$2:CK$2) -> 0.0023628861 | CN8: Adjusted R Square | CO8: 0.96298609
A9: 38168 | B9: =Data!B7 -> 0.0088462613 | C9: =Data!C7 -> 0.02767475 | D9: =Data!D7 -> -0.003405782 | E9: =Data!E7 -> -0.0011000051 | F9: =Data!F7 -> -0.0014189512 | G9: =SUMPRODUCT($B$2:$F$2,B9:F9) -> 0.0061192547 | W9: 0.0056515785 | X9: 0.014683749 | Y9: 0.0088758343 | Z9: =B9-SUMPRODUCT(W9:Y9, W$2:Y$2) -> 0.005335655 | AB9: Standard Error | AC9: 0.003322406 | AM9: 0.012495751 | AN9: -0.011132447 | AO9: 0.022668462 | AP9: =C9-SUMPRODUCT(AM9:AO9, AM$2:AO$2) -> 0.015000518 | AR9: Standard Error | AS9: 0.017268149 | BC9: -0.041462267 | BD9: 0.017579991 | BE9: =D9-SUMPRODUCT(BC9:BD9, BC$2:BD$2) -> 0.0015406921 | BG9: Standard Error | BH9: 0.046755563 | BR9: -0.003286563 | BS9: 0.0036000126 | BT9: 0.0019900115 | BU9: -0.0087949416 | BV9: =E9-SUMPRODUCT(BR9:BU9, BR$2:BU$2) -> -0.003121679 | BX9: Standard Error | BY9: 0.0086184021 | CI9: -0.0026148152 | CJ9: 0.0016100011 | CK9: 0.014527413 | CL9: =F9-SUMPRODUCT(CI9:CK9, CI$2:CK$2) -> -0.0011380863 | CN9: Standard Error | CO9: 0.0039725188
